Workbook

Sheet Retail Sales
A1: Order ID | B1: Order Date | C1: Customer ID | D1: Customer Name | E1: Age | F1: Age Group | G1: Gender | H1: Region | I1: City | J1: Product Category | K1: Product Name | L1: Quantity | M1: Unit Price | N1: Discount_Product | O1: Sales Amount | P1: Profit | Q1: Profit Margin | R1: Shipping Cost | S1: Payment Method | T1: Customer Satisfaction | U1: Return Flag | V1: Order Status | W1: Days to Ship
A2: ORD-00011 | B2: =_xlfn.XLOOKUP(A2,A1:A600,[1]Sheet3!C78:C677) -> 43833 | C2: =_xlfn.XLOOKUP(A2,A1:A600,[1]Sheet3!D78:D677) -> CUST64950 | D2: =_xlfn.XLOOKUP(A2,A1:A600,[1]Sheet3!E78:E677) -> Nisha Mehta | E2: =_xlfn.XLOOKUP(A2,A1:A600,[1]Sheet3!G78:G677) -> 23 | F2: =_xlfn.XLOOKUP('Retail Sales'!A79,'Retail Sales'!A78:A677,[1]Sheet3!H78:H677) -> Young Adult | G2: =_xlfn.XLOOKUP(A2,A1:A600,[1]Sheet3!J78:J677) -> Female | H2: =_xlfn.XLOOKUP(A2,A1:A600,[1]Sheet3!K78:K677) -> South | I2: =_xlfn.XLOOKUP(A2,A1:A600,[1]Sheet3!L78:L677) -> Hyderabad | J2: =_xlfn.XLOOKUP(A2,A1:A600,[1]Sheet3!M78:M677) -> Furniture | K2: =_xlfn.XLOOKUP('Retail Sales'!A79,'Retail Sales'!A78:A677,[1]Sheet3!N78:N677) -> Sofa | L2: =_xlfn.XLOOKUP(A2,A1:A600,[1]Sheet3!P78:P677) -> 8 | M2: =_xlfn.XLOOKUP(A2,A1:A600,[1]Sheet3!Q78:Q677) -> 22523.15 | N2: =_xlfn.XLOOKUP(A2,A1:A600,[1]Sheet3!S78:S677) -> 0.34 | O2: =_xlfn.XLOOKUP(A2,A1:A600,[1]Sheet3!T78:T677) -> 95036.79 | P2: =_xlfn.XLOOKUP(A2,A1:A600,[1]Sheet3!U78:U677) -> 29818.97 | Q2: =_xlfn.XLOOKUP(A2,A1:A600,[1]Sheet3!V78:V677) -> 0.31376239 | R2: =_xlfn.XLOOKUP(A2,A1:A600,[1]Sheet3!W78:W677) -> 65.72 | S2: =_xlfn.XLOOKUP(A2,A1:A600,[1]Sheet3!X78:X677) -> EMI | T2: =_xlfn.XLOOKUP(A2,A1:A600,[1]Sheet3!Z78:Z677) -> 2 | U2: =_xlfn.XLOOKUP(A2,A1:A600,[1]Sheet3!AA78:AA677) -> FALSE | V2: =_xlfn.XLOOKUP(A2,A1:A600,[1]Sheet3!AC78:AC677) -> Delivered | W2: =_xlfn.XLOOKUP(A2,A1:A600,[1]Sheet3!AE78:AE677) -> 5
A3: ORD-00020 | B3: =_xlfn.XLOOKUP(A3,A2:A601,[1]Sheet3!C462:C1061) -> 43838 | C3: =_xlfn.XLOOKUP(A3,A2:A601,[1]Sheet3!D462:D1061) -> CUST05879 | D3: =_xlfn.XLOOKUP(A3,A2:A601,[1]Sheet3!E462:E1061) -> Nisha Nair | E3: =_xlfn.XLOOKUP(A3,A2:A601,[1]Sheet3!G462:G1061) -> 12 | F3: =_xlfn.XLOOKUP('Retail Sales'!A463,'Retail Sales'!A462:A1061,[1]Sheet3!H462:H1061) -> Child | G3: =_xlfn.XLOOKUP(A3,A2:A601,[1]Sheet3!J462:J1061) -> Other | H3: =_xlfn.XLOOKUP(A3,A2:A601,[1]Sheet3!K462:K1061) -> Central | I3: =_xlfn.XLOOKUP(A3,A2:A601,[1]Sheet3!L462:L1061) -> Nagpur | J3: =_xlfn.XLOOKUP(A3,A2:A601,[1]Sheet3!M462:M1061) -> Sports | K3: =_xlfn.XLOOKUP('Retail Sales'!A463,'Retail Sales'!A462:A1061,[1]Sheet3!N462:N1061) -> Dumbbells | L3: =_xlfn.XLOOKUP(A3,A2:A601,[1]Sheet3!P462:P1061) -> 2 | M3: =_xlfn.XLOOKUP(A3,A2:A601,[1]Sheet3!Q462:Q1061) -> 2448.88 | N3: =_xlfn.XLOOKUP(A3,A2:A601,[1]Sheet3!S462:S1061) -> 0.08 | O3: =_xlfn.XLOOKUP(A3,A2:A601,[1]Sheet3!T462:T1061) -> 3192.22 | P3: =_xlfn.XLOOKUP(A3,A2:A601,[1]Sheet3!U462:U1061) -> 355.63 | Q3: =_xlfn.XLOOKUP(A3,A2:A601,[1]Sheet3!V462:V1061) -> 0.11140523 | R3: =_xlfn.XLOOKUP(A3,A2:A601,[1]Sheet3!W462:W1061) -> 47.54 | S3: =_xlfn.XLOOKUP(A3,A2:A601,[1]Sheet3!X462:X1061) -> Cash on Delivery | T3: =_xlfn.XLOOKUP(A3,A2:A601,[1]Sheet3!Z462:Z1061) -> 3 | U3: =_xlfn.XLOOKUP(A3,A2:A601,[1]Sheet3!AA462:AA1061) -> FALSE | V3: =_xlfn.XLOOKUP(A3,A2:A601,[1]Sheet3!AC462:AC1061) -> Delivered | W3: =_xlfn.XLOOKUP(A3,A2:A601,[1]Sheet3!AE462:AE1061) -> 9
A4: ORD-00025 | B4: =_xlfn.XLOOKUP(A4,A3:A602,[1]Sheet3!C40:C639) -> 43840 | C4: =_xlfn.XLOOKUP(A4,A3:A602,[1]Sheet3!D40:D639) -> CUST91373 | D4: =_xlfn.XLOOKUP(A4,A3:A602,[1]Sheet3!E40:E639) -> Karan Iyer | E4: =_xlfn.XLOOKUP(A4,A3:A602,[1]Sheet3!G40:G639) -> 52 | F4: =_xlfn.XLOOKUP('Retail Sales'!A41,'Retail Sales'!A40:A639,[1]Sheet3!H40:H639) -> Senior | G4: =_xlfn.XLOOKUP(A4,A3:A602,[1]Sheet3!J40:J639) -> Female | H4: =_xlfn.XLOOKUP(A4,A3:A602,[1]Sheet3!K40:K639) -> West | I4: =_xlfn.XLOOKUP(A4,A3:A602,[1]Sheet3!L40:L639) -> Mumbai | J4: =_xlfn.XLOOKUP(A4,A3:A602,[1]Sheet3!M40:M639) -> Books | K4: =_xlfn.XLOOKUP('Retail Sales'!A41,'Retail Sales'!A40:A639,[1]Sheet3!N40:N639) -> Cook Book | L4: =_xlfn.XLOOKUP(A4,A3:A602,[1]Sheet3!P40:P639) -> 10 | M4: =_xlfn.XLOOKUP(A4,A3:A602,[1]Sheet3!Q40:Q639) -> 324.41 | N4: =_xlfn.XLOOKUP(A4,A3:A602,[1]Sheet3!S40:S639) -> 0.32 | O4: =_xlfn.XLOOKUP(A4,A3:A602,[1]Sheet3!T40:T639) -> 1810.18 | P4: =_xlfn.XLOOKUP(A4,A3:A602,[1]Sheet3!U40:U639) -> 903.99 | Q4: =_xlfn.XLOOKUP(A4,A3:A602,[1]Sheet3!V40:V639) -> 0.49939233 | R4: =_xlfn.XLOOKUP(A4,A3:A602,[1]Sheet3!W40:W639) -> 48.24 | S4: =_xlfn.XLOOKUP(A4,A3:A602,[1]Sheet3!X40:X639) -> UPI | T4: =_xlfn.XLOOKUP(A4,A3:A602,[1]Sheet3!Z40:Z639) -> 3 | U4: =_xlfn.XLOOKUP(A4,A3:A602,[1]Sheet3!AA40:AA639) -> FALSE | V4: =_xlfn.XLOOKUP(A4,A3:A602,[1]Sheet3!AC40:AC639) -> Delivered | W4: =_xlfn.XLOOKUP(A4,A3:A602,[1]Sheet3!AE40:AE639) -> 4
A5: ORD-00028 | B5: =_xlfn.XLOOKUP(A5,A4:A603,[1]Sheet3!C554:C1153) -> 43841 | C5: =_xlfn.XLOOKUP(A5,A4:A603,[1]Sheet3!D554:D1153) -> CUST03400 | D5: =_xlfn.XLOOKUP(A5,A4:A603,[1]Sheet3!E554:E1153) -> Karan Mishra | E5: =_xlfn.XLOOKUP(A5,A4:A603,[1]Sheet3!G554:G1153) -> 23 | F5: =_xlfn.XLOOKUP('Retail Sales'!A555,'Retail Sales'!A554:A1153,[1]Sheet3!H554:H1153) -> Young Adult | G5: =_xlfn.XLOOKUP(A5,A4:A603,[1]Sheet3!J554:J1153) -> Male | H5: =_xlfn.XLOOKUP(A5,A4:A603,[1]Sheet3!K554:K1153) -> Central | I5: =_xlfn.XLOOKUP(A5,A4:A603,[1]Sheet3!L554:L1153) -> Indore | J5: =_xlfn.XLOOKUP(A5,A4:A603,[1]Sheet3!M554:M1153) -> Sports | K5: =_xlfn.XLOOKUP('Retail Sales'!A555,'Retail Sales'!A554:A1153,[1]Sheet3!N554:N1153) -> Football | L5: =_xlfn.XLOOKUP(A5,A4:A603,[1]Sheet3!P554:P1153) -> 7 | M5: =_xlfn.XLOOKUP(A5,A4:A603,[1]Sheet3!Q554:Q1153) -> 12178.99 | N5: =_xlfn.XLOOKUP(A5,A4:A603,[1]Sheet3!S554:S1153) -> 0.01 | O5: =_xlfn.XLOOKUP(A5,A4:A603,[1]Sheet3!T554:T1153) -> 66009.55 | P5: =_xlfn.XLOOKUP(A5,A4:A603,[1]Sheet3!U554:U1153) -> 17076.44 | Q5: =_xlfn.XLOOKUP(A5,A4:A603,[1]Sheet3!V554:V1153) -> 0.25869651 | R5: =_xlfn.XLOOKUP(A5,A4:A603,[1]Sheet3!W554:W1153) -> 51.51 | S5: =_xlfn.XLOOKUP(A5,A4:A603,[1]Sheet3!X554:X1153) -> UPI | T5: =_xlfn.XLOOKUP(A5,A4:A603,[1]Sheet3!Z554:Z1153) -> 5 | U5: =_xlfn.XLOOKUP(A5,A4:A603,[1]Sheet3!AA554:AA1153) -> FALSE | V5: =_xlfn.XLOOKUP(A5,A4:A603,[1]Sheet3!AC554:AC1153) -> Cancelled | W5: =_xlfn.XLOOKUP(A5,A4:A603,[1]Sheet3!AE554:AE1153) -> 10
A6: ORD-00034 | B6: =_xlfn.XLOOKUP(A6,A5:A604,[1]Sheet3!C294:C893) -> 43842 | C6: =_xlfn.XLOOKUP(A6,A5:A604,[1]Sheet3!D294:D893) -> CUST21613 | D6: =_xlfn.XLOOKUP(A6,A5:A604,[1]Sheet3!E294:E893) -> Arjun Das | E6: =_xlfn.XLOOKUP(A6,A5:A604,[1]Sheet3!G294:G893) -> 49 | F6: =_xlfn.XLOOKUP('Retail Sales'!A295,'Retail Sales'!A294:A893,[1]Sheet3!H294:H893) -> Adult | G6: =_xlfn.XLOOKUP(A6,A5:A604,[1]Sheet3!J294:J893) -> Other | H6: =_xlfn.XLOOKUP(A6,A5:A604,[1]Sheet3!K294:K893) -> West | I6: =_xlfn.XLOOKUP(A6,A5:A604,[1]Sheet3!L294:L893) -> Mumbai | J6: =_xlfn.XLOOKUP(A6,A5:A604,[1]Sheet3!M294:M893) -> Groceries | K6: =_xlfn.XLOOKUP('Retail Sales'!A295,'Retail Sales'!A294:A893,[1]Sheet3!N294:N893) -> Flour | L6: =_xlfn.XLOOKUP(A6,A5:A604,[1]Sheet3!P294:P893) -> 7.0954861 | M6: =_xlfn.XLOOKUP(A6,A5:A604,[1]Sheet3!Q294:Q893) -> 315.85 | N6: =_xlfn.XLOOKUP(A6,A5:A604,[1]Sheet3!S294:S893) -> 0.13 | O6: =_xlfn.XLOOKUP(A6,A5:A604,[1]Sheet3!T294:T893) -> 203.41 | P6: =_xlfn.XLOOKUP(A6,A5:A604,[1]Sheet3!U294:U893) -> 13.82 | Q6: =_xlfn.XLOOKUP(A6,A5:A604,[1]Sheet3!V294:V893) -> 0.067941596 | R6: =_xlfn.XLOOKUP(A6,A5:A604,[1]Sheet3!W294:W893) -> 60.46 | S6: =_xlfn.XLOOKUP(A6,A5:A604,[1]Sheet3!X294:X893) -> Cash on Delivery | T6: =_xlfn.XLOOKUP(A6,A5:A604,[1]Sheet3!Z294:Z893) -> 5 | U6: =_xlfn.XLOOKUP(A6,A5:A604,[1]Sheet3!AA294:AA893) -> FALSE | V6: =_xlfn.XLOOKUP(A6,A5:A604,[1]Sheet3!AC294:AC893) -> Delivered | W6: =_xlfn.XLOOKUP(A6,A5:A604,[1]Sheet3!AE294:AE893) -> 10
A7: ORD-00038 | B7: =_xlfn.XLOOKUP(A7,A6:A605,[1]Sheet3!C253:C852) -> 43844 | C7: =_xlfn.XLOOKUP(A7,A6:A605,[1]Sheet3!D253:D852) -> CUST79223 | D7: =_xlfn.XLOOKUP(A7,A6:A605,[1]Sheet3!E253:E852) -> Sunita Reddy | E7: =_xlfn.XLOOKUP(A7,A6:A605,[1]Sheet3!G253:G852) -> 20 | F7: =_xlfn.XLOOKUP('Retail Sales'!A254,'Retail Sales'!A253:A852,[1]Sheet3!H253:H852) -> Young Adult | G7: =_xlfn.XLOOKUP(A7,A6:A605,[1]Sheet3!J253:J852) -> Male | H7: =_xlfn.XLOOKUP(A7,A6:A605,[1]Sheet3!K253:K852) -> East | I7: =_xlfn.XLOOKUP(A7,A6:A605,[1]Sheet3!L253:L852) -> Kolkata | J7: =_xlfn.XLOOKUP(A7,A6:A605,[1]Sheet3!M253:M852) -> Books | K7: =_xlfn.XLOOKUP('Retail Sales'!A254,'Retail Sales'!A253:A852,[1]Sheet3!N253:N852) -> Fiction Novel | L7: =_xlfn.XLOOKUP(A7,A6:A605,[1]Sheet3!P253:P852) -> 1 | M7: =_xlfn.XLOOKUP(A7,A6:A605,[1]Sheet3!Q253:Q852) -> 1172.06 | N7: =_xlfn.XLOOKUP(A7,A6:A605,[1]Sheet3!S253:S852) -> 0.18 | O7: =_xlfn.XLOOKUP(A7,A6:A605,[1]Sheet3!T253:T852) -> 613.66 | P7: =_xlfn.XLOOKUP(A7,A6:A605,[1]Sheet3!U253:U852) -> 243.99 | Q7: =_xlfn.XLOOKUP(A7,A6:A605,[1]Sheet3!V253:V852) -> 0.39759802 | R7: =_xlfn.XLOOKUP(A7,A6:A605,[1]Sheet3!W253:W852) -> 62.05 | S7: =_xlfn.XLOOKUP(A7,A6:A605,[1]Sheet3!X253:X852) -> Cash on Delivery | T7: =_xlfn.XLOOKUP(A7,A6:A605,[1]Sheet3!Z253:Z852) -> 4 | U7: =_xlfn.XLOOKUP(A7,A6:A605,[1]Sheet3!AA253:AA852) -> FALSE | V7: =_xlfn.XLOOKUP(A7,A6:A605,[1]Sheet3!AC253:AC852) -> Delivered | W7: =_xlfn.XLOOKUP(A7,A6:A605,[1]Sheet3!AE253:AE852) -> 1
A8: ORD-00049 | B8: =_xlfn.XLOOKUP(A8,A7:A606,[1]Sheet3!C20:C619) -> 43849 | C8: =_xlfn.XLOOKUP(A8,A7:A606,[1]Sheet3!D20:D619) -> CUST43401 | D8: =_xlfn.XLOOKUP(A8,A7:A606,[1]Sheet3!E20:E619) -> Sanjay Bose | E8: =_xlfn.XLOOKUP(A8,A7:A606,[1]Sheet3!G20:G619) -> 21 | F8: =_xlfn.XLOOKUP('Retail Sales'!A21,'Retail Sales'!A20:A619,[1]Sheet3!H20:H619) -> Young Adult | G8: =_xlfn.XLOOKUP(A8,A7:A606,[1]Sheet3!J20:J619) -> Other | H8: =_xlfn.XLOOKUP(A8,A7:A606,[1]Sheet3!K20:K619) -> North | I8: =_xlfn.XLOOKUP(A8,A7:A606,[1]Sheet3!L20:L619) -> Delhi | J8: =_xlfn.XLOOKUP(A8,A7:A606,[1]Sheet3!M20:M619) -> Furniture | K8: =_xlfn.XLOOKUP('Retail Sales'!A21,'Retail Sales'!A20:A619,[1]Sheet3!N20:N619) -> Sofa | L8: =_xlfn.XLOOKUP(A8,A7:A606,[1]Sheet3!P20:P619) -> 3 | M8: =_xlfn.XLOOKUP(A8,A7:A606,[1]Sheet3!Q20:Q619) -> 34890.63 | N8: =_xlfn.XLOOKUP(A8,A7:A606,[1]Sheet3!S20:S619) -> 0.29 | O8: =_xlfn.XLOOKUP(A8,A7:A606,[1]Sheet3!T20:T619) -> 64727.53 | P8: =_xlfn.XLOOKUP(A8,A7:A606,[1]Sheet3!U20:U619) -> 18067.63 | Q8: =_xlfn.XLOOKUP(A8,A7:A606,[1]Sheet3!V20:V619) -> 0.27913362 | R8: =_xlfn.XLOOKUP(A8,A7:A606,[1]Sheet3!W20:W619) -> 40.97 | S8: =_xlfn.XLOOKUP(A8,A7:A606,[1]Sheet3!X20:X619) -> Net Banking | T8: =_xlfn.XLOOKUP(A8,A7:A606,[1]Sheet3!Z20:Z619) -> 5 | U8: =_xlfn.XLOOKUP(A8,A7:A606,[1]Sheet3!AA20:AA619) -> FALSE | V8: =_xlfn.XLOOKUP(A8,A7:A606,[1]Sheet3!AC20:AC619) -> Shipped | W8: =_xlfn.XLOOKUP(A8,A7:A606,[1]Sheet3!AE20:AE619) -> 3
A9: ORD-00051 | B9: =_xlfn.XLOOKUP(A9,A8:A607,[1]Sheet3!C586:C1185) -> 43850 | C9: =_xlfn.XLOOKUP(A9,A8:A607,[1]Sheet3!D586:D1185) -> CUST27973 | D9: =_xlfn.XLOOKUP(A9,A8:A607,[1]Sheet3!E586:E1185) -> Shreya Pillai | E9: =_xlfn.XLOOKUP(A9,A8:A607,[1]Sheet3!G586:G1185) -> 13 | F9: =_xlfn.XLOOKUP('Retail Sales'!A587,'Retail Sales'!A586:A1185,[1]Sheet3!H586:H1185) -> Teen | G9: =_xlfn.XLOOKUP(A9,A8:A607,[1]Sheet3!J586:J1185) -> Male | H9: =_xlfn.XLOOKUP(A9,A8:A607,[1]Sheet3!K586:K1185) -> South | I9: =_xlfn.XLOOKUP(A9,A8:A607,[1]Sheet3!L586:L1185) -> Hyderabad | J9: =_xlfn.XLOOKUP(A9,A8:A607,[1]Sheet3!M586:M1185) -> Beauty | K9: =_xlfn.XLOOKUP('Retail Sales'!A587,'Retail Sales'!A586:A1185,[1]Sheet3!N586:N1185) -> Perfume | L9: =_xlfn.XLOOKUP(A9,A8:A607,[1]Sheet3!P586:P1185) -> 6 | M9: =_xlfn.XLOOKUP(A9,A8:A607,[1]Sheet3!Q586:Q1185) -> 1952.59 | N9: =_xlfn.XLOOKUP(A9,A8:A607,[1]Sheet3!S586:S1185) -> 0.14 | O9: =_xlfn.XLOOKUP(A9,A8:A607,[1]Sheet3!T586:T1185) -> 6658.21 | P9: =_xlfn.XLOOKUP(A9,A8:A607,[1]Sheet3!U586:U1185) -> 3867.94 | Q9: =_xlfn.XLOOKUP(A9,A8:A607,[1]Sheet3!V586:V1185) -> 0.58092791 | R9: =_xlfn.XLOOKUP(A9,A8:A607,[1]Sheet3!W586:W1185) -> 38.17 | S9: =_xlfn.XLOOKUP(A9,A8:A607,[1]Sheet3!X586:X1185) -> Credit Card | T9: =_xlfn.XLOOKUP(A9,A8:A607,[1]Sheet3!Z586:Z1185) -> 1 | U9: =_xlfn.XLOOKUP(A9,A8:A607,[1]Sheet3!AA586:AA1185) -> FALSE | V9: =_xlfn.XLOOKUP(A9,A8:A607,[1]Sheet3!AC586:AC1185) -> Shipped | W9: =_xlfn.XLOOKUP(A9,A8:A607,[1]Sheet3!AE586:AE1185) -> 8
A10: ORD-00053 | B10: =_xlfn.XLOOKUP(A10,A9:A608,[1]Sheet3!C211:C810) -> 43851 | C10: =_xlfn.XLOOKUP(A10,A9:A608,[1]Sheet3!D211:D810) -> CUST07190 | D10: =_xlfn.XLOOKUP(A10,A9:A608,[1]Sheet3!E211:E810) -> Deepa Kapoor | E10: =_xlfn.XLOOKUP(A10,A9:A608,[1]Sheet3!G211:G810) -> 33 | F10: =_xlfn.XLOOKUP('Retail Sales'!A212,'Retail Sales'!A211:A810,[1]Sheet3!H211:H810) -> Young Adult | G10: =_xlfn.XLOOKUP(A10,A9:A608,[1]Sheet3!J211:J810) -> Other | H10: =_xlfn.XLOOKUP(A10,A9:A608,[1]Sheet3!K211:K810) -> East | I10: =_xlfn.XLOOKUP(A10,A9:A608,[1]Sheet3!L211:L810) -> Guwahati | J10: =_xlfn.XLOOKUP(A10,A9:A608,[1]Sheet3!M211:M810) -> Beauty | K10: =_xlfn.XLOOKUP('Retail Sales'!A212,'Retail Sales'!A211:A810,[1]Sheet3!N211:N810) -> Lipstick | L10: =_xlfn.XLOOKUP(A10,A9:A608,[1]Sheet3!P211:P810) -> 9 | M10: =_xlfn.XLOOKUP(A10,A9:A608,[1]Sheet3!Q211:Q810) -> 1931.61 | N10: =_xlfn.XLOOKUP(A10,A9:A608,[1]Sheet3!S211:S810) -> 0.35 | O10: =_xlfn.XLOOKUP(A10,A9:A608,[1]Sheet3!T211:T810) -> 10532.18 | P10: =_xlfn.XLOOKUP(A10,A9:A608,[1]Sheet3!U211:U810) -> 5257.88 | Q10: =_xlfn.XLOOKUP(A10,A9:A608,[1]Sheet3!V211:V810) -> 0.49922048 | R10: =_xlfn.XLOOKUP(A10,A9:A608,[1]Sheet3!W211:W810) -> 98.73 | S10: =_xlfn.XLOOKUP(A10,A9:A608,[1]Sheet3!X211:X810) -> Net Banking | T10: =_xlfn.XLOOKUP(A10,A9:A608,[1]Sheet3!Z211:Z810) -> 5 | U10: =_xlfn.XLOOKUP(A10,A9:A608,[1]Sheet3!AA211:AA810) -> FALSE | V10: =_xlfn.XLOOKUP(A10,A9:A608,[1]Sheet3!AC211:AC810) -> Delivered | W10: =_xlfn.XLOOKUP(A10,A9:A608,[1]Sheet3!AE211:AE810) -> 3
A11: ORD-00058 | B11: =_xlfn.XLOOKUP(A11,A10:A609,[1]Sheet3!C79:C678) -> 43852 | C11: =_xlfn.XLOOKUP(A11,A10:A609,[1]Sheet3!D79:D678) -> CUST60127 | D11: =_xlfn.XLOOKUP(A11,A10:A609,[1]Sheet3!E79:E678) -> Ritu Kapoor | E11: =_xlfn.XLOOKUP(A11,A10:A609,[1]Sheet3!G79:G678) -> 16 | F11: =_xlfn.XLOOKUP('Retail Sales'!A80,'Retail Sales'!A79:A678,[1]Sheet3!H79:H678) -> Teen | G11: =_xlfn.XLOOKUP(A11,A10:A609,[1]Sheet3!J79:J678) -> Other | H11: =_xlfn.XLOOKUP(A11,A10:A609,[1]Sheet3!K79:K678) -> South | I11: =_xlfn.XLOOKUP(A11,A10:A609,[1]Sheet3!L79:L678) -> Bangalore | J11: =_xlfn.XLOOKUP(A11,A10:A609,[1]Sheet3!M79:M678) -> Books | K11: =_xlfn.XLOOKUP('Retail Sales'!A80,'Retail Sales'!A79:A678,[1]Sheet3!N79:N678) -> Textbook | L11: =_xlfn.XLOOKUP(A11,A10:A609,[1]Sheet3!P79:P678) -> 4 | M11: =_xlfn.XLOOKUP(A11,A10:A609,[1]Sheet3!Q79:Q678) -> 363.32 | N11: =_xlfn.XLOOKUP(A11,A10:A609,[1]Sheet3!S79:S678) -> 0.07 | O11: =_xlfn.XLOOKUP(A11,A10:A609,[1]Sheet3!T79:T678) -> 1026.5 | P11: =_xlfn.XLOOKUP(A11,A10:A609,[1]Sheet3!U79:U678) -> 410.28 | Q11: =_xlfn.XLOOKUP(A11,A10:A609,[1]Sheet3!V79:V678) -> 0.39968826 | R11: =_xlfn.XLOOKUP(A11,A10:A609,[1]Sheet3!W79:W678) -> 89.93 | S11: =_xlfn.XLOOKUP(A11,A10:A609,[1]Sheet3!X79:X678) -> EMI | T11: =_xlfn.XLOOKUP(A11,A10:A609,[1]Sheet3!Z79:Z678) -> 5 | U11: =_xlfn.XLOOKUP(A11,A10:A609,[1]Sheet3!AA79:AA678) -> FALSE | V11: =_xlfn.XLOOKUP(A11,A10:A609,[1]Sheet3!AC79:AC678) -> Shipped | W11: =_xlfn.XLOOKUP(A11,A10:A609,[1]Sheet3!AE79:AE678) -> 5
A12: ORD-00073 | B12: =_xlfn.XLOOKUP(A12,A11:A610,[1]Sheet3!C147:C746) -> 43858 | C12: =_xlfn.XLOOKUP(A12,A11:A610,[1]Sheet3!D147:D746) -> CUST44662 | D12: =_xlfn.XLOOKUP(A12,A11:A610,[1]Sheet3!E147:E746) -> Ananya Nair | E12: =_xlfn.XLOOKUP(A12,A11:A610,[1]Sheet3!G147:G746) -> 34.294221 | F12: =_xlfn.XLOOKUP('Retail Sales'!A148,'Retail Sales'!A147:A746,[1]Sheet3!H147:H746) -> Young Adult | G12: =_xlfn.XLOOKUP(A12,A11:A610,[1]Sheet3!J147:J746) -> Male | H12: =_xlfn.XLOOKUP(A12,A11:A610,[1]Sheet3!K147:K746) -> North | I12: =_xlfn.XLOOKUP(A12,A11:A610,[1]Sheet3!L147:L746) -> Delhi | J12: =_xlfn.XLOOKUP(A12,A11:A610,[1]Sheet3!M147:M746) -> Sports | K12: =_xlfn.XLOOKUP('Retail Sales'!A148,'Retail Sales'!A147:A746,[1]Sheet3!N147:N746) -> Dumbbells | L12: =_xlfn.XLOOKUP(A12,A11:A610,[1]Sheet3!P147:P746) -> 4 | M12: =_xlfn.XLOOKUP(A12,A11:A610,[1]Sheet3!Q147:Q746) -> 12945.28 | N12: =_xlfn.XLOOKUP(A12,A11:A610,[1]Sheet3!S147:S746) -> 0.13 | O12: =_xlfn.XLOOKUP(A12,A11:A610,[1]Sheet3!T147:T746) -> 31129.56 | P12: =_xlfn.XLOOKUP(A12,A11:A610,[1]Sheet3!U147:U746) -> 7042.29 | Q12: =_xlfn.XLOOKUP(A12,A11:A610,[1]Sheet3!V147:V746) -> 0.22622517 | R12: =_xlfn.XLOOKUP(A12,A11:A610,[1]Sheet3!W147:W746) -> 65.38 | S12: =_xlfn.XLOOKUP(A12,A11:A610,[1]Sheet3!X147:X746) -> Credit Card | T12: =_xlfn.XLOOKUP(A12,A11:A610,[1]Sheet3!Z147:Z746) -> 5 | U12: =_xlfn.XLOOKUP(A12,A11:A610,[1]Sheet3!AA147:AA746) -> FALSE | V12: =_xlfn.XLOOKUP(A12,A11:A610,[1]Sheet3!AC147:AC746) -> Delivered | W12: =_xlfn.XLOOKUP(A12,A11:A610,[1]Sheet3!AE147:AE746) -> 4
A13: ORD-00086 | B13: =_xlfn.XLOOKUP(A13,A12:A611,[1]Sheet3!C119:C718) -> 43864 | C13: =_xlfn.XLOOKUP(A13,A12:A611,[1]Sheet3!D119:D718) -> CUST63884 | D13: =_xlfn.XLOOKUP(A13,A12:A611,[1]Sheet3!E119:E718) -> Amit Das | E13: =_xlfn.XLOOKUP(A13,A12:A611,[1]Sheet3!G119:G718) -> 29 | F13: =_xlfn.XLOOKUP('Retail Sales'!A120,'Retail Sales'!A119:A718,[1]Sheet3!H119:H718) -> Young Adult | G13: =_xlfn.XLOOKUP(A13,A12:A611,[1]Sheet3!J119:J718) -> Female | H13: =_xlfn.XLOOKUP(A13,A12:A611,[1]Sheet3!K119:K718) -> West | I13: =_xlfn.XLOOKUP(A13,A12:A611,[1]Sheet3!L119:L718) -> Ahmedabad | J13: =_xlfn.XLOOKUP(A13,A12:A611,[1]Sheet3!M119:M718) -> Furniture | K13: =_xlfn.XLOOKUP('Retail Sales'!A120,'Retail Sales'!A119:A718,[1]Sheet3!N119:N718) -> Chair | L13: =_xlfn.XLOOKUP(A13,A12:A611,[1]Sheet3!P119:P718) -> 10 | M13: =_xlfn.XLOOKUP(A13,A12:A611,[1]Sheet3!Q119:Q718) -> 9468.07 | N13: =_xlfn.XLOOKUP(A13,A12:A611,[1]Sheet3!S119:S718) -> 0.32 | O13: =_xlfn.XLOOKUP(A13,A12:A611,[1]Sheet3!T119:T718) -> 57174.24 | P13: =_xlfn.XLOOKUP(A13,A12:A611,[1]Sheet3!U119:U718) -> 15202.22 | Q13: =_xlfn.XLOOKUP(A13,A12:A611,[1]Sheet3!V119:V718) -> 0.26589282 | R13: =_xlfn.XLOOKUP(A13,A12:A611,[1]Sheet3!W119:W718) -> 40.98 | S13: =_xlfn.XLOOKUP(A13,A12:A611,[1]Sheet3!X119:X718) -> EMI | T13: =_xlfn.XLOOKUP(A13,A12:A611,[1]Sheet3!Z119:Z718) -> 3 | U13: =_xlfn.XLOOKUP(A13,A12:A611,[1]Sheet3!AA119:AA718) -> FALSE | V13: =_xlfn.XLOOKUP(A13,A12:A611,[1]Sheet3!AC119:AC718) -> Delivered | W13: =_xlfn.XLOOKUP(A13,A12:A611,[1]Sheet3!AE119:AE718) -> 2
A14: ORD-00093 | B14: =_xlfn.XLOOKUP(A14,A13:A612,[1]Sheet3!C529:C1128) -> 43867 | C14: =_xlfn.XLOOKUP(A14,A13:A612,[1]Sheet3!D529:D1128) -> CUST28742 | D14: =_xlfn.XLOOKUP(A14,A13:A612,[1]Sheet3!E529:E1128) -> Kavya Bhat | E14: =_xlfn.XLOOKUP(A14,A13:A612,[1]Sheet3!G529:G1128) -> 38 | F14: =_xlfn.XLOOKUP('Retail Sales'!A530,'Retail Sales'!A529:A1128,[1]Sheet3!H529:H1128) -> Adult | G14: =_xlfn.XLOOKUP(A14,A13:A612,[1]Sheet3!J529:J1128) -> Female | H14: =_xlfn.XLOOKUP(A14,A13:A612,[1]Sheet3!K529:K1128) -> East | I14: =_xlfn.XLOOKUP(A14,A13:A612,[1]Sheet3!L529:L1128) -> Kolkata | J14: =_xlfn.XLOOKUP(A14,A13:A612,[1]Sheet3!M529:M1128) -> Beauty | K14: =_xlfn.XLOOKUP('Retail Sales'!A530,'Retail Sales'!A529:A1128,[1]Sheet3!N529:N1128) -> Hair Oil | L14: =_xlfn.XLOOKUP(A14,A13:A612,[1]Sheet3!P529:P1128) -> 3 | M14: =_xlfn.XLOOKUP(A14,A13:A612,[1]Sheet3!Q529:Q1128) -> 1535.87 | N14: =_xlfn.XLOOKUP(A14,A13:A612,[1]Sheet3!S529:S1128) -> 0.04 | O14: =_xlfn.XLOOKUP(A14,A13:A612,[1]Sheet3!T529:T1128) -> 3186.03 | P14: =_xlfn.XLOOKUP(A14,A13:A612,[1]Sheet3!U529:U1128) -> 1346.8 | Q14: =_xlfn.XLOOKUP(A14,A13:A612,[1]Sheet3!V529:V1128) -> 0.42272044 | R14: =_xlfn.XLOOKUP(A14,A13:A612,[1]Sheet3!W529:W1128) -> 86.51 | S14: =_xlfn.XLOOKUP(A14,A13:A612,[1]Sheet3!X529:X1128) -> Cash on Delivery | T14: =_xlfn.XLOOKUP(A14,A13:A612,[1]Sheet3!Z529:Z1128) -> 5 | U14: =_xlfn.XLOOKUP(A14,A13:A612,[1]Sheet3!AA529:AA1128) -> TRUE | V14: =_xlfn.XLOOKUP(A14,A13:A612,[1]Sheet3!AC529:AC1128) -> Returned | W14: =_xlfn.XLOOKUP(A14,A13:A612,[1]Sheet3!AE529:AE1128) -> 7
A15: ORD-00099 | B15: =_xlfn.XLOOKUP(A15,A14:A613,[1]Sheet3!C69:C668) -> 43869 | C15: =_xlfn.XLOOKUP(A15,A14:A613,[1]Sheet3!D69:D668) -> CUST15599 | D15: =_xlfn.XLOOKUP(A15,A14:A613,[1]Sheet3!E69:E668) -> Karan Shah | E15: =_xlfn.XLOOKUP(A15,A14:A613,[1]Sheet3!G69:G668) -> 33 | F15: =_xlfn.XLOOKUP('Retail Sales'!A70,'Retail Sales'!A69:A668,[1]Sheet3!H69:H668) -> Young Adult | G15: =_xlfn.XLOOKUP(A15,A14:A613,[1]Sheet3!J69:J668) -> Other | H15: =_xlfn.XLOOKUP(A15,A14:A613,[1]Sheet3!K69:K668) -> West | I15: =_xlfn.XLOOKUP(A15,A14:A613,[1]Sheet3!L69:L668) -> Pune | J15: =_xlfn.XLOOKUP(A15,A14:A613,[1]Sheet3!M69:M668) -> Furniture | K15: =_xlfn.XLOOKUP('Retail Sales'!A70,'Retail Sales'!A69:A668,[1]Sheet3!N69:N668) -> Chair | L15: =_xlfn.XLOOKUP(A15,A14:A613,[1]Sheet3!P69:P668) -> 9 | M15: =_xlfn.XLOOKUP(A15,A14:A613,[1]Sheet3!Q69:Q668) -> 22687.65 | N15: =_xlfn.XLOOKUP(A15,A14:A613,[1]Sheet3!S69:S668) -> 0.33 | O15: =_xlfn.XLOOKUP(A15,A14:A613,[1]Sheet3!T69:T668) -> 117568.37 | P15: =_xlfn.XLOOKUP(A15,A14:A613,[1]Sheet3!U69:U668) -> 33050.92 | Q15: =_xlfn.XLOOKUP(A15,A14:A613,[1]Sheet3!V69:V668) -> 0.28112085 | R15: =_xlfn.XLOOKUP(A15,A14:A613,[1]Sheet3!W69:W668) -> 45.04 | S15: =_xlfn.XLOOKUP(A15,A14:A613,[1]Sheet3!X69:X668) -> Net Banking | T15: =_xlfn.XLOOKUP(A15,A14:A613,[1]Sheet3!Z69:Z668) -> 3 | U15: =_xlfn.XLOOKUP(A15,A14:A613,[1]Sheet3!AA69:AA668) -> FALSE | V15: =_xlfn.XLOOKUP(A15,A14:A613,[1]Sheet3!AC69:AC668) -> Delivered | W15: =_xlfn.XLOOKUP(A15,A14:A613,[1]Sheet3!AE69:AE668) -> 2
A16: ORD-00101 | B16: =_xlfn.XLOOKUP(A16,A15:A614,[1]Sheet3!C111:C710) -> 43869 | C16: =_xlfn.XLOOKUP(A16,A15:A614,[1]Sheet3!D111:D710) -> CUST45487 | D16: =_xlfn.XLOOKUP(A16,A15:A614,[1]Sheet3!E111:E710) -> Sunita Joshi | E16: =_xlfn.XLOOKUP(A16,A15:A614,[1]Sheet3!G111:G710) -> 34 | F16: =_xlfn.XLOOKUP('Retail Sales'!A112,'Retail Sales'!A111:A710,[1]Sheet3!H111:H710) -> Young Adult | G16: =_xlfn.XLOOKUP(A16,A15:A614,[1]Sheet3!J111:J710) -> Other | H16: =_xlfn.XLOOKUP(A16,A15:A614,[1]Sheet3!K111:K710) -> West | I16: =_xlfn.XLOOKUP(A16,A15:A614,[1]Sheet3!L111:L710) -> Pune | J16: =_xlfn.XLOOKUP(A16,A15:A614,[1]Sheet3!M111:M710) -> Books | K16: =_xlfn.XLOOKUP('Retail Sales'!A112,'Retail Sales'!A111:A710,[1]Sheet3!N111:N710) -> Cook Book | L16: =_xlfn.XLOOKUP(A16,A15:A614,[1]Sheet3!P111:P710) -> 8 | M16: =_xlfn.XLOOKUP(A16,A15:A614,[1]Sheet3!Q111:Q710) -> 1325.02 | N16: =_xlfn.XLOOKUP(A16,A15:A614,[1]Sheet3!S111:S710) -> 0.09 | O16: =_xlfn.XLOOKUP(A16,A15:A614,[1]Sheet3!T111:T710) -> 8717.89 | P16: =_xlfn.XLOOKUP(A16,A15:A614,[1]Sheet3!U111:U710) -> 3265.49 | Q16: =_xlfn.XLOOKUP(A16,A15:A614,[1]Sheet3!V111:V710) -> 0.37457343 | R16: =_xlfn.XLOOKUP(A16,A15:A614,[1]Sheet3!W111:W710) -> 41.67 | S16: =_xlfn.XLOOKUP(A16,A15:A614,[1]Sheet3!X111:X710) -> Debit Card | T16: =_xlfn.XLOOKUP(A16,A15:A614,[1]Sheet3!Z111:Z710) -> 2 | U16: =_xlfn.XLOOKUP(A16,A15:A614,[1]Sheet3!AA111:AA710) -> FALSE | V16: =_xlfn.XLOOKUP(A16,A15:A614,[1]Sheet3!AC111:AC710) -> Cancelled | W16: =_xlfn.XLOOKUP(A16,A15:A614,[1]Sheet3!AE111:AE710) -> 5
A17: ORD-00105 | B17: =_xlfn.XLOOKUP(A17,A16:A615,[1]Sheet3!C10:C609) -> 43870 | C17: =_xlfn.XLOOKUP(A17,A16:A615,[1]Sheet3!D10:D609) -> CUST75337 | D17: =_xlfn.XLOOKUP(A17,A16:A615,[1]Sheet3!E10:E609) -> Arjun Das | E17: =_xlfn.XLOOKUP(A17,A16:A615,[1]Sheet3!G10:G609) -> 17 | F17: =_xlfn.XLOOKUP('Retail Sales'!A11,'Retail Sales'!A10:A609,[1]Sheet3!H10:H609) -> Teen | G17: =_xlfn.XLOOKUP(A17,A16:A615,[1]Sheet3!J10:J609) -> Female | H17: =_xlfn.XLOOKUP(A17,A16:A615,[1]Sheet3!K10:K609) -> East | I17: =_xlfn.XLOOKUP(A17,A16:A615,[1]Sheet3!L10:L609) -> Patna | J17: =_xlfn.XLOOKUP(A17,A16:A615,[1]Sheet3!M10:M609) -> Clothing | K17: =_xlfn.XLOOKUP('Retail Sales'!A11,'Retail Sales'!A10:A609,[1]Sheet3!N10:N609) -> Kurta | L17: =_xlfn.XLOOKUP(A17,A16:A615,[1]Sheet3!P10:P609) -> 9 | M17: =_xlfn.XLOOKUP(A17,A16:A615,[1]Sheet3!Q10:Q609) -> 2128.77 | N17: =_xlfn.XLOOKUP(A17,A16:A615,[1]Sheet3!S10:S609) -> 0.1 | O17: =_xlfn.XLOOKUP(A17,A16:A615,[1]Sheet3!T10:T609) -> 14568.16 | P17: =_xlfn.XLOOKUP(A17,A16:A615,[1]Sheet3!U10:U609) -> 4173.45 | Q17: =_xlfn.XLOOKUP(A17,A16:A615,[1]Sheet3!V10:V609) -> 0.2864775 | R17: =_xlfn.XLOOKUP(A17,A16:A615,[1]Sheet3!W10:W609) -> 75.33 | S17: =_xlfn.XLOOKUP(A17,A16:A615,[1]Sheet3!X10:X609) -> UPI | T17: =_xlfn.XLOOKUP(A17,A16:A615,[1]Sheet3!Z10:Z609) -> 3 | U17: =_xlfn.XLOOKUP(A17,A16:A615,[1]Sheet3!AA10:AA609) -> FALSE | V17: =_xlfn.XLOOKUP(A17,A16:A615,[1]Sheet3!AC10:AC609) -> Delivered | W17: =_xlfn.XLOOKUP(A17,A16:A615,[1]Sheet3!AE10:AE609) -> 8
A18: ORD-00115 | B18: =_xlfn.XLOOKUP(A18,A17:A616,[1]Sheet3!C459:C1058) -> 43873 | C18: =_xlfn.XLOOKUP(A18,A17:A616,[1]Sheet3!D459:D1058) -> CUST05374 | D18: =_xlfn.XLOOKUP(A18,A17:A616,[1]Sheet3!E459:E1058) -> Aditya Chatterjee | E18: =_xlfn.XLOOKUP(A18,A17:A616,[1]Sheet3!G459:G1058) -> 39 | F18: =_xlfn.XLOOKUP('Retail Sales'!A460,'Retail Sales'!A459:A1058,[1]Sheet3!H459:H1058) -> Adult | G18: =_xlfn.XLOOKUP(A18,A17:A616,[1]Sheet3!J459:J1058) -> Female | H18: =_xlfn.XLOOKUP(A18,A17:A616,[1]Sheet3!K459:K1058) -> South | I18: =_xlfn.XLOOKUP(A18,A17:A616,[1]Sheet3!L459:L1058) -> Chennai | J18: =_xlfn.XLOOKUP(A18,A17:A616,[1]Sheet3!M459:M1058) -> Beauty | K18: =_xlfn.XLOOKUP('Retail Sales'!A460,'Retail Sales'!A459:A1058,[1]Sheet3!N459:N1058) -> Hair Oil | L18: =_xlfn.XLOOKUP(A18,A17:A616,[1]Sheet3!P459:P1058) -> 6 | M18: =_xlfn.XLOOKUP(A18,A17:A616,[1]Sheet3!Q459:Q1058) -> 1270.36 | N18: =_xlfn.XLOOKUP(A18,A17:A616,[1]Sheet3!S459:S1058) -> 0.06 | O18: =_xlfn.XLOOKUP(A18,A17:A616,[1]Sheet3!T459:T1058) -> 5747.77 | P18: =_xlfn.XLOOKUP(A18,A17:A616,[1]Sheet3!U459:U1058) -> 2669 | Q18: =_xlfn.XLOOKUP(A18,A17:A616,[1]Sheet3!V459:V1058) -> 0.464354 | R18: =_xlfn.XLOOKUP(A18,A17:A616,[1]Sheet3!W459:W1058) -> 62.46 | S18: =_xlfn.XLOOKUP(A18,A17:A616,[1]Sheet3!X459:X1058) -> EMI | T18: =_xlfn.XLOOKUP(A18,A17:A616,[1]Sheet3!Z459:Z1058) -> 3 | U18: =_xlfn.XLOOKUP(A18,A17:A616,[1]Sheet3!AA459:AA1058) -> FALSE | V18: =_xlfn.XLOOKUP(A18,A17:A616,[1]Sheet3!AC459:AC1058) -> Delivered | W18: =_xlfn.XLOOKUP(A18,A17:A616,[1]Sheet3!AE459:AE1058) -> 8
A19: ORD-00117 | B19: =_xlfn.XLOOKUP(A19,A18:A617,[1]Sheet3!C60:C659) -> 43873 | C19: =_xlfn.XLOOKUP(A19,A18:A617,[1]Sheet3!D60:D659) -> CUST33188 | D19: =_xlfn.XLOOKUP(A19,A18:A617,[1]Sheet3!E60:E659) -> Sanjay Joshi | E19: =_xlfn.XLOOKUP(A19,A18:A617,[1]Sheet3!G60:G659) -> 48 | F19: =_xlfn.XLOOKUP('Retail Sales'!A61,'Retail Sales'!A60:A659,[1]Sheet3!H60:H659) -> Adult | G19: =_xlfn.XLOOKUP(A19,A18:A617,[1]Sheet3!J60:J659) -> Female | H19: =_xlfn.XLOOKUP(A19,A18:A617,[1]Sheet3!K60:K659) -> South | I19: =_xlfn.XLOOKUP(A19,A18:A617,[1]Sheet3!L60:L659) -> Kochi | J19: =_xlfn.XLOOKUP(A19,A18:A617,[1]Sheet3!M60:M659) -> Sports | K19: =_xlfn.XLOOKUP('Retail Sales'!A61,'Retail Sales'!A60:A659,[1]Sheet3!N60:N659) -> Cycle | L19: =_xlfn.XLOOKUP(A19,A18:A617,[1]Sheet3!P60:P659) -> 3 | M19: =_xlfn.XLOOKUP(A19,A18:A617,[1]Sheet3!Q60:Q659) -> 6047.51 | N19: =_xlfn.XLOOKUP(A19,A18:A617,[1]Sheet3!S60:S659) -> 0.08 | O19: =_xlfn.XLOOKUP(A19,A18:A617,[1]Sheet3!T60:T659) -> 13365.94 | P19: =_xlfn.XLOOKUP(A19,A18:A617,[1]Sheet3!U60:U659) -> 2741.49 | Q19: =_xlfn.XLOOKUP(A19,A18:A617,[1]Sheet3!V60:V659) -> 0.20511015 | R19: =_xlfn.XLOOKUP(A19,A18:A617,[1]Sheet3!W60:W659) -> 36.15 | S19: =_xlfn.XLOOKUP(A19,A18:A617,[1]Sheet3!X60:X659) -> Debit Card | T19: =_xlfn.XLOOKUP(A19,A18:A617,[1]Sheet3!Z60:Z659) -> 4 | U19: =_xlfn.XLOOKUP(A19,A18:A617,[1]Sheet3!AA60:AA659) -> FALSE | V19: =_xlfn.XLOOKUP(A19,A18:A617,[1]Sheet3!AC60:AC659) -> Delivered | W19: =_xlfn.XLOOKUP(A19,A18:A617,[1]Sheet3!AE60:AE659) -> 3
A20: ORD-00129 | B20: =_xlfn.XLOOKUP(A20,A19:A618,[1]Sheet3!C569:C1168) -> 43880 | C20: =_xlfn.XLOOKUP(A20,A19:A618,[1]Sheet3!D569:D1168) -> CUST20302 | D20: =_xlfn.XLOOKUP(A20,A19:A618,[1]Sheet3!E569:E1168) -> Aditya Gupta | E20: =_xlfn.XLOOKUP(A20,A19:A618,[1]Sheet3!G569:G1168) -> 48 | F20: =_xlfn.XLOOKUP('Retail Sales'!A570,'Retail Sales'!A569:A1168,[1]Sheet3!H569:H1168) -> Adult | G20: =_xlfn.XLOOKUP(A20,A19:A618,[1]Sheet3!J569:J1168) -> Other | H20: =_xlfn.XLOOKUP(A20,A19:A618,[1]Sheet3!K569:K1168) -> South | I20: =_xlfn.XLOOKUP(A20,A19:A618,[1]Sheet3!L569:L1168) -> Bangalore | J20: =_xlfn.XLOOKUP(A20,A19:A618,[1]Sheet3!M569:M1168) -> Clothing | K20: =_xlfn.XLOOKUP('Retail Sales'!A570,'Retail Sales'!A569:A1168,[1]Sheet3!N569:N1168) -> Saree | L20: =_xlfn.XLOOKUP(A20,A19:A618,[1]Sheet3!P569:P1168) -> 8 | M20: =_xlfn.XLOOKUP(A20,A19:A618,[1]Sheet3!Q569:Q1168) -> 967.73 | N20: =_xlfn.XLOOKUP(A20,A19:A618,[1]Sheet3!S569:S1168) -> 0.36 | O20: =_xlfn.XLOOKUP(A20,A19:A618,[1]Sheet3!T569:T1168) -> 4117.6 | P20: =_xlfn.XLOOKUP(A20,A19:A618,[1]Sheet3!U569:U1168) -> 1596.92 | Q20: =_xlfn.XLOOKUP(A20,A19:A618,[1]Sheet3!V569:V1168) -> 0.38782786 | R20: =_xlfn.XLOOKUP(A20,A19:A618,[1]Sheet3!W569:W1168) -> 73.93 | S20: =_xlfn.XLOOKUP(A20,A19:A618,[1]Sheet3!X569:X1168) -> Credit Card | T20: =_xlfn.XLOOKUP(A20,A19:A618,[1]Sheet3!Z569:Z1168) -> 3 | U20: =_xlfn.XLOOKUP(A20,A19:A618,[1]Sheet3!AA569:AA1168) -> TRUE | V20: =_xlfn.XLOOKUP(A20,A19:A618,[1]Sheet3!AC569:AC1168) -> Returned | W20: =_xlfn.XLOOKUP(A20,A19:A618,[1]Sheet3!AE569:AE1168) -> 6
A21: ORD-00130 | B21: =_xlfn.XLOOKUP(A21,A20:A619,[1]Sheet3!C331:C930) -> 43881 | C21: =_xlfn.XLOOKUP(A21,A20:A619,[1]Sheet3!D331:D930) -> CUST73625 | D21: =_xlfn.XLOOKUP(A21,A20:A619,[1]Sheet3!E331:E930) -> Nisha Bose | E21: =_xlfn.XLOOKUP(A21,A20:A619,[1]Sheet3!G331:G930) -> 28 | F21: =_xlfn.XLOOKUP('Retail Sales'!A332,'Retail Sales'!A331:A930,[1]Sheet3!H331:H930) -> Young Adult | G21: =_xlfn.XLOOKUP(A21,A20:A619,[1]Sheet3!J331:J930) -> Other | H21: =_xlfn.XLOOKUP(A21,A20:A619,[1]Sheet3!K331:K930) -> East | I21: =_xlfn.XLOOKUP(A21,A20:A619,[1]Sheet3!L331:L930) -> Guwahati | J21: =_xlfn.XLOOKUP(A21,A20:A619,[1]Sheet3!M331:M930) -> Books | K21: =_xlfn.XLOOKUP('Retail Sales'!A332,'Retail Sales'!A331:A930,[1]Sheet3!N331:N930) -> Textbook | L21: =_xlfn.XLOOKUP(A21,A20:A619,[1]Sheet3!P331:P930) -> 10 | M21: =_xlfn.XLOOKUP(A21,A20:A619,[1]Sheet3!Q331:Q930) -> 327.54 | N21: =_xlfn.XLOOKUP(A21,A20:A619,[1]Sheet3!S331:S930) -> 0.15 | O21: =_xlfn.XLOOKUP(A21,A20:A619,[1]Sheet3!T331:T930) -> 2755.17 | P21: =_xlfn.XLOOKUP(A21,A20:A619,[1]Sheet3!U331:U930) -> 1528.85 | Q21: =_xlfn.XLOOKUP(A21,A20:A619,[1]Sheet3!V331:V930) -> 0.55490224 | R21: =_xlfn.XLOOKUP(A21,A20:A619,[1]Sheet3!W331:W930) -> 80.58 | S21: =_xlfn.XLOOKUP(A21,A20:A619,[1]Sheet3!X331:X930) -> Debit Card | T21: =_xlfn.XLOOKUP(A21,A20:A619,[1]Sheet3!Z331:Z930) -> 5 | U21: =_xlfn.XLOOKUP(A21,A20:A619,[1]Sheet3!AA331:AA930) -> TRUE | V21: =_xlfn.XLOOKUP(A21,A20:A619,[1]Sheet3!AC331:AC930) -> Returned | W21: =_xlfn.XLOOKUP(A21,A20:A619,[1]Sheet3!AE331:AE930) -> 2
A22: ORD-00132 | B22: =_xlfn.XLOOKUP(A22,A21:A620,[1]Sheet3!C347:C946) -> 43881 | C22: =_xlfn.XLOOKUP(A22,A21:A620,[1]Sheet3!D347:D946) -> CUST20387 | D22: =_xlfn.XLOOKUP(A22,A21:A620,[1]Sheet3!E347:E946) -> Ritu Mishra | E22: =_xlfn.XLOOKUP(A22,A21:A620,[1]Sheet3!G347:G946) -> 26 | F22: =_xlfn.XLOOKUP('Retail Sales'!A348,'Retail Sales'!A347:A946,[1]Sheet3!H347:H946) -> Young Adult | G22: =_xlfn.XLOOKUP(A22,A21:A620,[1]Sheet3!J347:J946) -> Female | H22: =_xlfn.XLOOKUP(A22,A21:A620,[1]Sheet3!K347:K946) -> South | I22: =_xlfn.XLOOKUP(A22,A21:A620,[1]Sheet3!L347:L946) -> Kochi | J22: =_xlfn.XLOOKUP(A22,A21:A620,[1]Sheet3!M347:M946) -> Beauty | K22: =_xlfn.XLOOKUP('Retail Sales'!A348,'Retail Sales'!A347:A946,[1]Sheet3!N347:N946) -> Lipstick | L22: =_xlfn.XLOOKUP(A22,A21:A620,[1]Sheet3!P347:P946) -> 2 | M22: =_xlfn.XLOOKUP(A22,A21:A620,[1]Sheet3!Q347:Q946) -> 959.97 | N22: =_xlfn.XLOOKUP(A22,A21:A620,[1]Sheet3!S347:S946) -> 0.05 | O22: =_xlfn.XLOOKUP(A22,A21:A620,[1]Sheet3!T347:T946) -> 1563.91 | P22: =_xlfn.XLOOKUP(A22,A21:A620,[1]Sheet3!U347:U946) -> 630.51 | Q22: =_xlfn.XLOOKUP(A22,A21:A620,[1]Sheet3!V347:V946) -> 0.40316259 | R22: =_xlfn.XLOOKUP(A22,A21:A620,[1]Sheet3!W347:W946) -> 71.85 | S22: =_xlfn.XLOOKUP(A22,A21:A620,[1]Sheet3!X347:X946) -> EMI | T22: =_xlfn.XLOOKUP(A22,A21:A620,[1]Sheet3!Z347:Z946) -> 4 | U22: =_xlfn.XLOOKUP(A22,A21:A620,[1]Sheet3!AA347:AA946) -> FALSE | V22: =_xlfn.XLOOKUP(A22,A21:A620,[1]Sheet3!AC347:AC946) -> Delivered | W22: =_xlfn.XLOOKUP(A22,A21:A620,[1]Sheet3!AE347:AE946) -> 2
A23: ORD-00138 | B23: =_xlfn.XLOOKUP(A23,A22:A621,[1]Sheet3!C497:C1096) -> 43885 | C23: =_xlfn.XLOOKUP(A23,A22:A621,[1]Sheet3!D497:D1096) -> CUST54691 | D23: =_xlfn.XLOOKUP(A23,A22:A621,[1]Sheet3!E497:E1096) -> Priya Shah | E23: =_xlfn.XLOOKUP(A23,A22:A621,[1]Sheet3!G497:G1096) -> 27 | F23: =_xlfn.XLOOKUP('Retail Sales'!A498,'Retail Sales'!A497:A1096,[1]Sheet3!H497:H1096) -> Young Adult | G23: =_xlfn.XLOOKUP(A23,A22:A621,[1]Sheet3!J497:J1096) -> Female | H23: =_xlfn.XLOOKUP(A23,A22:A621,[1]Sheet3!K497:K1096) -> East | I23: =_xlfn.XLOOKUP(A23,A22:A621,[1]Sheet3!L497:L1096) -> Patna | J23: =_xlfn.XLOOKUP(A23,A22:A621,[1]Sheet3!M497:M1096) -> Beauty | K23: =_xlfn.XLOOKUP('Retail Sales'!A498,'Retail Sales'!A497:A1096,[1]Sheet3!N497:N1096) -> Sunscreen | L23: =_xlfn.XLOOKUP(A23,A22:A621,[1]Sheet3!P497:P1096) -> 3 | M23: =_xlfn.XLOOKUP(A23,A22:A621,[1]Sheet3!Q497:Q1096) -> 1655.54 | N23: =_xlfn.XLOOKUP(A23,A22:A621,[1]Sheet3!S497:S1096) -> 0.25 | O23: =_xlfn.XLOOKUP(A23,A22:A621,[1]Sheet3!T497:T1096) -> 2825.92 | P23: =_xlfn.XLOOKUP(A23,A22:A621,[1]Sheet3!U497:U1096) -> 1777.23 | Q23: =_xlfn.XLOOKUP(A23,A22:A621,[1]Sheet3!V497:V1096) -> 0.62890315 | R23: =_xlfn.XLOOKUP(A23,A22:A621,[1]Sheet3!W497:W1096) -> 81.69 | S23: =_xlfn.XLOOKUP(A23,A22:A621,[1]Sheet3!X497:X1096) -> UPI | T23: =_xlfn.XLOOKUP(A23,A22:A621,[1]Sheet3!Z497:Z1096) -> 3 | U23: =_xlfn.XLOOKUP(A23,A22:A621,[1]Sheet3!AA497:AA1096) -> FALSE | V23: =_xlfn.XLOOKUP(A23,A22:A621,[1]Sheet3!AC497:AC1096) -> Delivered | W23: =_xlfn.XLOOKUP(A23,A22:A621,[1]Sheet3!AE497:AE1096) -> 5
A24: ORD-00142 | B24: =_xlfn.XLOOKUP(A24,A23:A622,[1]Sheet3!C395:C994) -> 43888 | C24: =_xlfn.XLOOKUP(A24,A23:A622,[1]Sheet3!D395:D994) -> CUST82516 | D24: =_xlfn.XLOOKUP(A24,A23:A622,[1]Sheet3!E395:E994) -> Ritu Joshi | E24: =_xlfn.XLOOKUP(A24,A23:A622,[1]Sheet3!G395:G994) -> 40 | F24: =_xlfn.XLOOKUP('Retail Sales'!A396,'Retail Sales'!A395:A994,[1]Sheet3!H395:H994) -> Adult | G24: =_xlfn.XLOOKUP(A24,A23:A622,[1]Sheet3!J395:J994) -> Female | H24: =_xlfn.XLOOKUP(A24,A23:A622,[1]Sheet3!K395:K994) -> East | I24: =_xlfn.XLOOKUP(A24,A23:A622,[1]Sheet3!L395:L994) -> Bhubaneswar | J24: =_xlfn.XLOOKUP(A24,A23:A622,[1]Sheet3!M395:M994) -> Sports | K24: =_xlfn.XLOOKUP('Retail Sales'!A396,'Retail Sales'!A395:A994,[1]Sheet3!N395:N994) -> Tennis Racket | L24: =_xlfn.XLOOKUP(A24,A23:A622,[1]Sheet3!P395:P994) -> 1 | M24: =_xlfn.XLOOKUP(A24,A23:A622,[1]Sheet3!Q395:Q994) -> 11227.96 | N24: =_xlfn.XLOOKUP(A24,A23:A622,[1]Sheet3!S395:S994) -> 0.31 | O24: =_xlfn.XLOOKUP(A24,A23:A622,[1]Sheet3!T395:T994) -> 6220.68 | P24: =_xlfn.XLOOKUP(A24,A23:A622,[1]Sheet3!U395:U994) -> 1706.13 | Q24: =_xlfn.XLOOKUP(A24,A23:A622,[1]Sheet3!V395:V994) -> 0.27426744 | R24: =_xlfn.XLOOKUP(A24,A23:A622,[1]Sheet3!W395:W994) -> 87.6 | S24: =_xlfn.XLOOKUP(A24,A23:A622,[1]Sheet3!X395:X994) -> Net Banking | T24: =_xlfn.XLOOKUP(A24,A23:A622,[1]Sheet3!Z395:Z994) -> 2 | U24: =_xlfn.XLOOKUP(A24,A23:A622,[1]Sheet3!AA395:AA994) -> FALSE | V24: =_xlfn.XLOOKUP(A24,A23:A622,[1]Sheet3!AC395:AC994) -> Shipped | W24: =_xlfn.XLOOKUP(A24,A23:A622,[1]Sheet3!AE395:AE994) -> 3
A25: ORD-00158 | B25: =_xlfn.XLOOKUP(A25,A24:A623,[1]Sheet3!C99:C698) -> 43897 | C25: =_xlfn.XLOOKUP(A25,A24:A623,[1]Sheet3!D99:D698) -> CUST56042 | D25: =_xlfn.XLOOKUP(A25,A24:A623,[1]Sheet3!E99:E698) -> Deepa Rao | E25: =_xlfn.XLOOKUP(A25,A24:A623,[1]Sheet3!G99:G698) -> 35 | F25: =_xlfn.XLOOKUP('Retail Sales'!A100,'Retail Sales'!A99:A698,[1]Sheet3!H99:H698) -> Young Adult | G25: =_xlfn.XLOOKUP(A25,A24:A623,[1]Sheet3!J99:J698) -> Female | H25: =_xlfn.XLOOKUP(A25,A24:A623,[1]Sheet3!K99:K698) -> East | I25: =_xlfn.XLOOKUP(A25,A24:A623,[1]Sheet3!L99:L698) -> Bhubaneswar | J25: =_xlfn.XLOOKUP(A25,A24:A623,[1]Sheet3!M99:M698) -> Furniture | K25: =_xlfn.XLOOKUP('Retail Sales'!A100,'Retail Sales'!A99:A698,[1]Sheet3!N99:N698) -> Desk | L25: =_xlfn.XLOOKUP(A25,A24:A623,[1]Sheet3!P99:P698) -> 8 | M25: =_xlfn.XLOOKUP(A25,A24:A623,[1]Sheet3!Q99:Q698) -> 25624.31 | N25: =_xlfn.XLOOKUP(A25,A24:A623,[1]Sheet3!S99:S698) -> 0.12 | O25: =_xlfn.XLOOKUP(A25,A24:A623,[1]Sheet3!T99:T698) -> 188109.47 | P25: =_xlfn.XLOOKUP(A25,A24:A623,[1]Sheet3!U99:U698) -> 45753.79 | Q25: =_xlfn.XLOOKUP(A25,A24:A623,[1]Sheet3!V99:V698) -> 0.24322959 | R25: =_xlfn.XLOOKUP(A25,A24:A623,[1]Sheet3!W99:W698) -> 65.63 | S25: =_xlfn.XLOOKUP(A25,A24:A623,[1]Sheet3!X99:X698) -> Credit Card | T25: =_xlfn.XLOOKUP(A25,A24:A623,[1]Sheet3!Z99:Z698) -> 1 | U25: =_xlfn.XLOOKUP(A25,A24:A623,[1]Sheet3!AA99:AA698) -> FALSE | V25: =_xlfn.XLOOKUP(A25,A24:A623,[1]Sheet3!AC99:AC698) -> Delivered | W25: =_xlfn.XLOOKUP(A25,A24:A623,[1]Sheet3!AE99:AE698) -> 3
A26: ORD-00164 | B26: =_xlfn.XLOOKUP(A26,A25:A624,[1]Sheet3!C514:C1113) -> 43902 | C26: =_xlfn.XLOOKUP(A26,A25:A624,[1]Sheet3!D514:D1113) -> CUST97663 | D26: =_xlfn.XLOOKUP(A26,A25:A624,[1]Sheet3!E514:E1113) -> Aarav Singh | E26: =_xlfn.XLOOKUP(A26,A25:A624,[1]Sheet3!G514:G1113) -> 34.294221 | F26: =_xlfn.XLOOKUP('Retail Sales'!A515,'Retail Sales'!A514:A1113,[1]Sheet3!H514:H1113) -> Young Adult | G26: =_xlfn.XLOOKUP(A26,A25:A624,[1]Sheet3!J514:J1113) -> Male | H26: =_xlfn.XLOOKUP(A26,A25:A624,[1]Sheet3!K514:K1113) -> North | I26: =_xlfn.XLOOKUP(A26,A25:A624,[1]Sheet3!L514:L1113) -> Ludhiana | J26: =_xlfn.XLOOKUP(A26,A25:A624,[1]Sheet3!M514:M1113) -> Clothing | K26: =_xlfn.XLOOKUP('Retail Sales'!A515,'Retail Sales'!A514:A1113,[1]Sheet3!N514:N1113) -> Kurta | L26: =_xlfn.XLOOKUP(A26,A25:A624,[1]Sheet3!P514:P1113) -> 9 | M26: =_xlfn.XLOOKUP(A26,A25:A624,[1]Sheet3!Q514:Q1113) -> 3971.91 | N26: =_xlfn.XLOOKUP(A26,A25:A624,[1]Sheet3!S514:S1113) -> 0.18 | O26: =_xlfn.XLOOKUP(A26,A25:A624,[1]Sheet3!T514:T1113) -> 32366.71 | P26: =_xlfn.XLOOKUP(A26,A25:A624,[1]Sheet3!U514:U1113) -> 14702.14 | Q26: =_xlfn.XLOOKUP(A26,A25:A624,[1]Sheet3!V514:V1113) -> 0.45423647 | R26: =_xlfn.XLOOKUP(A26,A25:A624,[1]Sheet3!W514:W1113) -> 47.38 | S26: =_xlfn.XLOOKUP(A26,A25:A624,[1]Sheet3!X514:X1113) -> Cash on Delivery | T26: =_xlfn.XLOOKUP(A26,A25:A624,[1]Sheet3!Z514:Z1113) -> 3 | U26: =_xlfn.XLOOKUP(A26,A25:A624,[1]Sheet3!AA514:AA1113) -> FALSE | V26: =_xlfn.XLOOKUP(A26,A25:A624,[1]Sheet3!AC514:AC1113) -> Pending | W26: =_xlfn.XLOOKUP(A26,A25:A624,[1]Sheet3!AE514:AE1113) -> 4
A27: ORD-00170 | B27: =_xlfn.XLOOKUP(A27,A26:A625,[1]Sheet3!C268:C867) -> 43905 | C27: =_xlfn.XLOOKUP(A27,A26:A625,[1]Sheet3!D268:D867) -> CUST53622 | D27: =_xlfn.XLOOKUP(A27,A26:A625,[1]Sheet3!E268:E867) -> Aditya Chatterjee | E27: =_xlfn.XLOOKUP(A27,A26:A625,[1]Sheet3!G268:G867) -> 31 | F27: =_xlfn.XLOOKUP('Retail Sales'!A269,'Retail Sales'!A268:A867,[1]Sheet3!H268:H867) -> Young Adult | G27: =_xlfn.XLOOKUP(A27,A26:A625,[1]Sheet3!J268:J867) -> Male | H27: =_xlfn.XLOOKUP(A27,A26:A625,[1]Sheet3!K268:K867) -> South | I27: =_xlfn.XLOOKUP(A27,A26:A625,[1]Sheet3!L268:L867) -> Bangalore | J27: =_xlfn.XLOOKUP(A27,A26:A625,[1]Sheet3!M268:M867) -> Groceries | K27: =_xlfn.XLOOKUP('Retail Sales'!A269,'Retail Sales'!A268:A867,[1]Sheet3!N268:N867) -> Sugar | L27: =_xlfn.XLOOKUP(A27,A26:A625,[1]Sheet3!P268:P867) -> 9 | M27: =_xlfn.XLOOKUP(A27,A26:A625,[1]Sheet3!Q268:Q867) -> 236.54 | N27: =_xlfn.XLOOKUP(A27,A26:A625,[1]Sheet3!S268:S867) -> 0.19 | O27: =_xlfn.XLOOKUP(A27,A26:A625,[1]Sheet3!T268:T867) -> 1658.66 | P27: =_xlfn.XLOOKUP(A27,A26:A625,[1]Sheet3!U268:U867) -> 140.16 | Q27: =_xlfn.XLOOKUP(A27,A26:A625,[1]Sheet3!V268:V867) -> 0.084501947 | R27: =_xlfn.XLOOKUP(A27,A26:A625,[1]Sheet3!W268:W867) -> 101.07 | S27: =_xlfn.XLOOKUP(A27,A26:A625,[1]Sheet3!X268:X867) -> Credit Card | T27: =_xlfn.XLOOKUP(A27,A26:A625,[1]Sheet3!Z268:Z867) -> 3 | U27: =_xlfn.XLOOKUP(A27,A26:A625,[1]Sheet3!AA268:AA867) -> TRUE | V27: =_xlfn.XLOOKUP(A27,A26:A625,[1]Sheet3!AC268:AC867) -> Returned | W27: =_xlfn.XLOOKUP(A27,A26:A625,[1]Sheet3!AE268:AE867) -> 1
A28: ORD-00172 | B28: =_xlfn.XLOOKUP(A28,A27:A626,[1]Sheet3!C450:C1049) -> 43905 | C28: =_xlfn.XLOOKUP(A28,A27:A626,[1]Sheet3!D450:D1049) -> CUST40704 | D28: =_xlfn.XLOOKUP(A28,A27:A626,[1]Sheet3!E450:E1049) -> Aarav Rao | E28: =_xlfn.XLOOKUP(A28,A27:A626,[1]Sheet3!G450:G1049) -> 16 | F28: =_xlfn.XLOOKUP('Retail Sales'!A451,'Retail Sales'!A450:A1049,[1]Sheet3!H450:H1049) -> Teen | G28: =_xlfn.XLOOKUP(A28,A27:A626,[1]Sheet3!J450:J1049) -> Other | H28: =_xlfn.XLOOKUP(A28,A27:A626,[1]Sheet3!K450:K1049) -> East | I28: =_xlfn.XLOOKUP(A28,A27:A626,[1]Sheet3!L450:L1049) -> Guwahati | J28: =_xlfn.XLOOKUP(A28,A27:A626,[1]Sheet3!M450:M1049) -> Clothing | K28: =_xlfn.XLOOKUP('Retail Sales'!A451,'Retail Sales'!A450:A1049,[1]Sheet3!N450:N1049) -> Saree | L28: =_xlfn.XLOOKUP(A28,A27:A626,[1]Sheet3!P450:P1049) -> 2 | M28: =_xlfn.XLOOKUP(A28,A27:A626,[1]Sheet3!Q450:Q1049) -> 2448.31 | N28: =_xlfn.XLOOKUP(A28,A27:A626,[1]Sheet3!S450:S1049) -> 0.35 | O28: =_xlfn.XLOOKUP(A28,A27:A626,[1]Sheet3!T450:T1049) -> 3584.88 | P28: =_xlfn.XLOOKUP(A28,A27:A626,[1]Sheet3!U450:U1049) -> 1270.16 | Q28: =_xlfn.XLOOKUP(A28,A27:A626,[1]Sheet3!V450:V1049) -> 0.35431033 | R28: =_xlfn.XLOOKUP(A28,A27:A626,[1]Sheet3!W450:W1049) -> 79.97 | S28: =_xlfn.XLOOKUP(A28,A27:A626,[1]Sheet3!X450:X1049) -> Credit Card | T28: =_xlfn.XLOOKUP(A28,A27:A626,[1]Sheet3!Z450:Z1049) -> 4 | U28: =_xlfn.XLOOKUP(A28,A27:A626,[1]Sheet3!AA450:AA1049) -> FALSE | V28: =_xlfn.XLOOKUP(A28,A27:A626,[1]Sheet3!AC450:AC1049) -> Delivered | W28: =_xlfn.XLOOKUP(A28,A27:A626,[1]Sheet3!AE450:AE1049) -> 7
A29: ORD-00183 | B29: =_xlfn.XLOOKUP(A29,A28:A627,[1]Sheet3!C222:C821) -> 43912 | C29: =_xlfn.XLOOKUP(A29,A28:A627,[1]Sheet3!D222:D821) -> CUST16395 | D29: =_xlfn.XLOOKUP(A29,A28:A627,[1]Sheet3!E222:E821) -> Sunita Pillai | E29: =_xlfn.XLOOKUP(A29,A28:A627,[1]Sheet3!G222:G821) -> 19 | F29: =_xlfn.XLOOKUP('Retail Sales'!A223,'Retail Sales'!A222:A821,[1]Sheet3!H222:H821) -> Teen | G29: =_xlfn.XLOOKUP(A29,A28:A627,[1]Sheet3!J222:J821) -> Other | H29: =_xlfn.XLOOKUP(A29,A28:A627,[1]Sheet3!K222:K821) -> Central | I29: =_xlfn.XLOOKUP(A29,A28:A627,[1]Sheet3!L222:L821) -> Raipur | J29: =_xlfn.XLOOKUP(A29,A28:A627,[1]Sheet3!M222:M821) -> Beauty | K29: =_xlfn.XLOOKUP('Retail Sales'!A223,'Retail Sales'!A222:A821,[1]Sheet3!N222:N821) -> Sunscreen | L29: =_xlfn.XLOOKUP(A29,A28:A627,[1]Sheet3!P222:P821) -> 9 | M29: =_xlfn.XLOOKUP(A29,A28:A627,[1]Sheet3!Q222:Q821) -> 646.01 | N29: =_xlfn.XLOOKUP(A29,A28:A627,[1]Sheet3!S222:S821) -> 0.38 | O29: =_xlfn.XLOOKUP(A29,A28:A627,[1]Sheet3!T222:T821) -> 3807.56 | P29: =_xlfn.XLOOKUP(A29,A28:A627,[1]Sheet3!U222:U821) -> 1281.84 | Q29: =_xlfn.XLOOKUP(A29,A28:A627,[1]Sheet3!V222:V821) -> 0.33665655 | R29: =_xlfn.XLOOKUP(A29,A28:A627,[1]Sheet3!W222:W821) -> 51.72 | S29: =_xlfn.XLOOKUP(A29,A28:A627,[1]Sheet3!X222:X821) -> Credit Card | T29: =_xlfn.XLOOKUP(A29,A28:A627,[1]Sheet3!Z222:Z821) -> 2 | U29: =_xlfn.XLOOKUP(A29,A28:A627,[1]Sheet3!AA222:AA821) -> FALSE | V29: =_xlfn.XLOOKUP(A29,A28:A627,[1]Sheet3!AC222:AC821) -> Pending | W29: =_xlfn.XLOOKUP(A29,A28:A627,[1]Sheet3!AE222:AE821) -> 3
A30: ORD-00197 | B30: =_xlfn.XLOOKUP(A30,A29:A628,[1]Sheet3!C360:C959) -> 43918 | C30: =_xlfn.XLOOKUP(A30,A29:A628,[1]Sheet3!D360:D959) -> CUST04223 | D30: =_xlfn.XLOOKUP(A30,A29:A628,[1]Sheet3!E360:E959) -> Pooja Joshi | E30: =_xlfn.XLOOKUP(A30,A29:A628,[1]Sheet3!G360:G959) -> 12 | F30: =_xlfn.XLOOKUP('Retail Sales'!A361,'Retail Sales'!A360:A959,[1]Sheet3!H360:H959) -> Child | G30: =_xlfn.XLOOKUP(A30,A29:A628,[1]Sheet3!J360:J959) -> Other | H30: =_xlfn.XLOOKUP(A30,A29:A628,[1]Sheet3!K360:K959) -> North | I30: =_xlfn.XLOOKUP(A30,A29:A628,[1]Sheet3!L360:L959) -> Amritsar | J30: =_xlfn.XLOOKUP(A30,A29:A628,[1]Sheet3!M360:M959) -> Sports | K30: =_xlfn.XLOOKUP('Retail Sales'!A361,'Retail Sales'!A360:A959,[1]Sheet3!N360:N959) -> Cycle | L30: =_xlfn.XLOOKUP(A30,A29:A628,[1]Sheet3!P360:P959) -> 8 | M30: =_xlfn.XLOOKUP(A30,A29:A628,[1]Sheet3!Q360:Q959) -> 10282.68 | N30: =_xlfn.XLOOKUP(A30,A29:A628,[1]Sheet3!S360:S959) -> 0.11 | O30: =_xlfn.XLOOKUP(A30,A29:A628,[1]Sheet3!T360:T959) -> 66340.96 | P30: =_xlfn.XLOOKUP(A30,A29:A628,[1]Sheet3!U360:U959) -> 13106.07 | Q30: =_xlfn.XLOOKUP(A30,A29:A628,[1]Sheet3!V360:V959) -> 0.19755623 | R30: =_xlfn.XLOOKUP(A30,A29:A628,[1]Sheet3!W360:W959) -> 65.44 | S30: =_xlfn.XLOOKUP(A30,A29:A628,[1]Sheet3!X360:X959) -> Net Banking | T30: =_xlfn.XLOOKUP(A30,A29:A628,[1]Sheet3!Z360:Z959) -> 1 | U30: =_xlfn.XLOOKUP(A30,A29:A628,[1]Sheet3!AA360:AA959) -> FALSE | V30: =_xlfn.XLOOKUP(A30,A29:A628,[1]Sheet3!AC360:AC959) -> Delivered | W30: =_xlfn.XLOOKUP(A30,A29:A628,[1]Sheet3!AE360:AE959) -> 3
A31: ORD-00200 | B31: =_xlfn.XLOOKUP(A31,A30:A629,[1]Sheet3!C233:C832) -> 43920 | C31: =_xlfn.XLOOKUP(A31,A30:A629,[1]Sheet3!D233:D832) -> CUST79644 | D31: =_xlfn.XLOOKUP(A31,A30:A629,[1]Sheet3!E233:E832) -> Aarav Verma | E31: =_xlfn.XLOOKUP(A31,A30:A629,[1]Sheet3!G233:G832) -> 23 | F31: =_xlfn.XLOOKUP('Retail Sales'!A234,'Retail Sales'!A233:A832,[1]Sheet3!H233:H832) -> Young Adult | G31: =_xlfn.XLOOKUP(A31,A30:A629,[1]Sheet3!J233:J832) -> Female | H31: =_xlfn.XLOOKUP(A31,A30:A629,[1]Sheet3!K233:K832) -> West | I31: =_xlfn.XLOOKUP(A31,A30:A629,[1]Sheet3!L233:L832) -> Mumbai | J31: =_xlfn.XLOOKUP(A31,A30:A629,[1]Sheet3!M233:M832) -> Sports | K31: =_xlfn.XLOOKUP('Retail Sales'!A234,'Retail Sales'!A233:A832,[1]Sheet3!N233:N832) -> Cycle | L31: =_xlfn.XLOOKUP(A31,A30:A629,[1]Sheet3!P233:P832) -> 5 | M31: =_xlfn.XLOOKUP(A31,A30:A629,[1]Sheet3!Q233:Q832) -> 9009.65 | N31: =_xlfn.XLOOKUP(A31,A30:A629,[1]Sheet3!S233:S832) -> 0.08 | O31: =_xlfn.XLOOKUP(A31,A30:A629,[1]Sheet3!T233:T832) -> 44971.39 | P31: =_xlfn.XLOOKUP(A31,A30:A629,[1]Sheet3!U233:U832) -> 10004.34 | Q31: =_xlfn.XLOOKUP(A31,A30:A629,[1]Sheet3!V233:V832) -> 0.2224601 | R31: =_xlfn.XLOOKUP(A31,A30:A629,[1]Sheet3!W233:W832) -> 58.16 | S31: =_xlfn.XLOOKUP(A31,A30:A629,[1]Sheet3!X233:X832) -> EMI | T31: =_xlfn.XLOOKUP(A31,A30:A629,[1]Sheet3!Z233:Z832) -> 3 | U31: =_xlfn.XLOOKUP(A31,A30:A629,[1]Sheet3!AA233:AA832) -> FALSE | V31: =_xlfn.XLOOKUP(A31,A30:A629,[1]Sheet3!AC233:AC832) -> Delivered | W31: =_xlfn.XLOOKUP(A31,A30:A629,[1]Sheet3!AE233:AE832) -> 4
A32: ORD-00201 | B32: =_xlfn.XLOOKUP(A32,A31:A630,[1]Sheet3!C537:C1136) -> 43920 | C32: =_xlfn.XLOOKUP(A32,A31:A630,[1]Sheet3!D537:D1136) -> CUST39806 | D32: =_xlfn.XLOOKUP(A32,A31:A630,[1]Sheet3!E537:E1136) -> Sanjay Bhat | E32: =_xlfn.XLOOKUP(A32,A31:A630,[1]Sheet3!G537:G1136) -> 27 | F32: =_xlfn.XLOOKUP('Retail Sales'!A538,'Retail Sales'!A537:A1136,[1]Sheet3!H537:H1136) -> Young Adult | G32: =_xlfn.XLOOKUP(A32,A31:A630,[1]Sheet3!J537:J1136) -> Other | H32: =_xlfn.XLOOKUP(A32,A31:A630,[1]Sheet3!K537:K1136) -> West | I32: =_xlfn.XLOOKUP(A32,A31:A630,[1]Sheet3!L537:L1136) -> Mumbai | J32: =_xlfn.XLOOKUP(A32,A31:A630,[1]Sheet3!M537:M1136) -> Beauty | K32: =_xlfn.XLOOKUP('Retail Sales'!A538,'Retail Sales'!A537:A1136,[1]Sheet3!N537:N1136) -> Face Cream | L32: =_xlfn.XLOOKUP(A32,A31:A630,[1]Sheet3!P537:P1136) -> 4 | M32: =_xlfn.XLOOKUP(A32,A31:A630,[1]Sheet3!Q537:Q1136) -> 2430.1 | N32: =_xlfn.XLOOKUP(A32,A31:A630,[1]Sheet3!S537:S1136) -> 0.03 | O32: =_xlfn.XLOOKUP(A32,A31:A630,[1]Sheet3!T537:T1136) -> 8709.27 | P32: =_xlfn.XLOOKUP(A32,A31:A630,[1]Sheet3!U537:U1136) -> 5472.38 | Q32: =_xlfn.XLOOKUP(A32,A31:A630,[1]Sheet3!V537:V1136) -> 0.62833969 | R32: =_xlfn.XLOOKUP(A32,A31:A630,[1]Sheet3!W537:W1136) -> 60.42 | S32: =_xlfn.XLOOKUP(A32,A31:A630,[1]Sheet3!X537:X1136) -> Debit Card | T32: =_xlfn.XLOOKUP(A32,A31:A630,[1]Sheet3!Z537:Z1136) -> 5 | U32: =_xlfn.XLOOKUP(A32,A31:A630,[1]Sheet3!AA537:AA1136) -> FALSE | V32: =_xlfn.XLOOKUP(A32,A31:A630,[1]Sheet3!AC537:AC1136) -> Delivered | W32: =_xlfn.XLOOKUP(A32,A31:A630,[1]Sheet3!AE537:AE1136) -> 1
A33: ORD-00219 | B33: =_xlfn.XLOOKUP(A33,A32:A631,[1]Sheet3!C496:C1095) -> 43926 | C33: =_xlfn.XLOOKUP(A33,A32:A631,[1]Sheet3!D496:D1095) -> CUST81881 | D33: =_xlfn.XLOOKUP(A33,A32:A631,[1]Sheet3!E496:E1095) -> Sanjay Mishra | E33: =_xlfn.XLOOKUP(A33,A32:A631,[1]Sheet3!G496:G1095) -> 34.294221 | F33: =_xlfn.XLOOKUP('Retail Sales'!A497,'Retail Sales'!A496:A1095,[1]Sheet3!H496:H1095) -> Young Adult | G33: =_xlfn.XLOOKUP(A33,A32:A631,[1]Sheet3!J496:J1095) -> Male | H33: =_xlfn.XLOOKUP(A33,A32:A631,[1]Sheet3!K496:K1095) -> Central | I33: =_xlfn.XLOOKUP(A33,A32:A631,[1]Sheet3!L496:L1095) -> Indore | J33: =_xlfn.XLOOKUP(A33,A32:A631,[1]Sheet3!M496:M1095) -> Beauty | K33: =_xlfn.XLOOKUP('Retail Sales'!A497,'Retail Sales'!A496:A1095,[1]Sheet3!N496:N1095) -> Face Cream | L33: =_xlfn.XLOOKUP(A33,A32:A631,[1]Sheet3!P496:P1095) -> 9 | M33: =_xlfn.XLOOKUP(A33,A32:A631,[1]Sheet3!Q496:Q1095) -> 1356.81 | N33: =_xlfn.XLOOKUP(A33,A32:A631,[1]Sheet3!S496:S1095) -> 0.01 | O33: =_xlfn.XLOOKUP(A33,A32:A631,[1]Sheet3!T496:T1095) -> 13938.43 | P33: =_xlfn.XLOOKUP(A33,A32:A631,[1]Sheet3!U496:U1095) -> 5273.14 | Q33: =_xlfn.XLOOKUP(A33,A32:A631,[1]Sheet3!V496:V1095) -> 0.37831664 | R33: =_xlfn.XLOOKUP(A33,A32:A631,[1]Sheet3!W496:W1095) -> 76.63 | S33: =_xlfn.XLOOKUP(A33,A32:A631,[1]Sheet3!X496:X1095) -> Credit Card | T33: =_xlfn.XLOOKUP(A33,A32:A631,[1]Sheet3!Z496:Z1095) -> 3 | U33: =_xlfn.XLOOKUP(A33,A32:A631,[1]Sheet3!AA496:AA1095) -> FALSE | V33: =_xlfn.XLOOKUP(A33,A32:A631,[1]Sheet3!AC496:AC1095) -> Delivered | W33: =_xlfn.XLOOKUP(A33,A32:A631,[1]Sheet3!AE496:AE1095) -> 4
A34: ORD-00225 | B34: =_xlfn.XLOOKUP(A34,A33:A632,[1]Sheet3!C61:C660) -> 43929 | C34: =_xlfn.XLOOKUP(A34,A33:A632,[1]Sheet3!D61:D660) -> CUST97307 | D34: =_xlfn.XLOOKUP(A34,A33:A632,[1]Sheet3!E61:E660) -> Ritu Gupta | E34: =_xlfn.XLOOKUP(A34,A33:A632,[1]Sheet3!G61:G660) -> 37 | F34: =_xlfn.XLOOKUP('Retail Sales'!A62,'Retail Sales'!A61:A660,[1]Sheet3!H61:H660) -> Adult | G34: =_xlfn.XLOOKUP(A34,A33:A632,[1]Sheet3!J61:J660) -> Male | H34: =_xlfn.XLOOKUP(A34,A33:A632,[1]Sheet3!K61:K660) -> Central | I34: =_xlfn.XLOOKUP(A34,A33:A632,[1]Sheet3!L61:L660) -> Nagpur | J34: =_xlfn.XLOOKUP(A34,A33:A632,[1]Sheet3!M61:M660) -> Sports | K34: =_xlfn.XLOOKUP('Retail Sales'!A62,'Retail Sales'!A61:A660,[1]Sheet3!N61:N660) -> Tennis Racket | L34: =_xlfn.XLOOKUP(A34,A33:A632,[1]Sheet3!P61:P660) -> 1 | M34: =_xlfn.XLOOKUP(A34,A33:A632,[1]Sheet3!Q61:Q660) -> 5935.12 | N34: =_xlfn.XLOOKUP(A34,A33:A632,[1]Sheet3!S61:S660) -> 0.08 | O34: =_xlfn.XLOOKUP(A34,A33:A632,[1]Sheet3!T61:T660) -> 6293.66 | P34: =_xlfn.XLOOKUP(A34,A33:A632,[1]Sheet3!U61:U660) -> 1165.63 | Q34: =_xlfn.XLOOKUP(A34,A33:A632,[1]Sheet3!V61:V660) -> 0.18520702 | R34: =_xlfn.XLOOKUP(A34,A33:A632,[1]Sheet3!W61:W660) -> 47.97 | S34: =_xlfn.XLOOKUP(A34,A33:A632,[1]Sheet3!X61:X660) -> Credit Card | T34: =_xlfn.XLOOKUP(A34,A33:A632,[1]Sheet3!Z61:Z660) -> 5 | U34: =_xlfn.XLOOKUP(A34,A33:A632,[1]Sheet3!AA61:AA660) -> FALSE | V34: =_xlfn.XLOOKUP(A34,A33:A632,[1]Sheet3!AC61:AC660) -> Delivered | W34: =_xlfn.XLOOKUP(A34,A33:A632,[1]Sheet3!AE61:AE660) -> 7
A35: ORD-00232 | B35: =_xlfn.XLOOKUP(A35,A34:A633,[1]Sheet3!C437:C1036) -> 43932 | C35: =_xlfn.XLOOKUP(A35,A34:A633,[1]Sheet3!D437:D1036) -> CUST30800 | D35: =_xlfn.XLOOKUP(A35,A34:A633,[1]Sheet3!E437:E1036) -> Rohan Chatterjee | E35: =_xlfn.XLOOKUP(A35,A34:A633,[1]Sheet3!G437:G1036) -> 36 | F35: =_xlfn.XLOOKUP('Retail Sales'!A438,'Retail Sales'!A437:A1036,[1]Sheet3!H437:H1036) -> Adult | G35: =_xlfn.XLOOKUP(A35,A34:A633,[1]Sheet3!J437:J1036) -> Other | H35: =_xlfn.XLOOKUP(A35,A34:A633,[1]Sheet3!K437:K1036) -> Central | I35: =_xlfn.XLOOKUP(A35,A34:A633,[1]Sheet3!L437:L1036) -> Nagpur | J35: =_xlfn.XLOOKUP(A35,A34:A633,[1]Sheet3!M437:M1036) -> Beauty | K35: =_xlfn.XLOOKUP('Retail Sales'!A438,'Retail Sales'!A437:A1036,[1]Sheet3!N437:N1036) -> Perfume | L35: =_xlfn.XLOOKUP(A35,A34:A633,[1]Sheet3!P437:P1036) -> 4 | M35: =_xlfn.XLOOKUP(A35,A34:A633,[1]Sheet3!Q437:Q1036) -> 171.85 | N35: =_xlfn.XLOOKUP(A35,A34:A633,[1]Sheet3!S437:S1036) -> 0.03 | O35: =_xlfn.XLOOKUP(A35,A34:A633,[1]Sheet3!T437:T1036) -> 902.31 | P35: =_xlfn.XLOOKUP(A35,A34:A633,[1]Sheet3!U437:U1036) -> 591.14 | Q35: =_xlfn.XLOOKUP(A35,A34:A633,[1]Sheet3!V437:V1036) -> 0.65514069 | R35: =_xlfn.XLOOKUP(A35,A34:A633,[1]Sheet3!W437:W1036) -> 34.27 | S35: =_xlfn.XLOOKUP(A35,A34:A633,[1]Sheet3!X437:X1036) -> Debit Card | T35: =_xlfn.XLOOKUP(A35,A34:A633,[1]Sheet3!Z437:Z1036) -> 3 | U35: =_xlfn.XLOOKUP(A35,A34:A633,[1]Sheet3!AA437:AA1036) -> FALSE | V35: =_xlfn.XLOOKUP(A35,A34:A633,[1]Sheet3!AC437:AC1036) -> Shipped | W35: =_xlfn.XLOOKUP(A35,A34:A633,[1]Sheet3!AE437:AE1036) -> 8
A36: ORD-00251 | B36: =_xlfn.XLOOKUP(A36,A35:A634,[1]Sheet3!C388:C987) -> 43941 | C36: =_xlfn.XLOOKUP(A36,A35:A634,[1]Sheet3!D388:D987) -> CUST66007 | D36: =_xlfn.XLOOKUP(A36,A35:A634,[1]Sheet3!E388:E987) -> Sunita Bose | E36: =_xlfn.XLOOKUP(A36,A35:A634,[1]Sheet3!G388:G987) -> 26 | F36: =_xlfn.XLOOKUP('Retail Sales'!A389,'Retail Sales'!A388:A987,[1]Sheet3!H388:H987) -> Young Adult | G36: =_xlfn.XLOOKUP(A36,A35:A634,[1]Sheet3!J388:J987) -> Male | H36: =_xlfn.XLOOKUP(A36,A35:A634,[1]Sheet3!K388:K987) -> North | I36: =_xlfn.XLOOKUP(A36,A35:A634,[1]Sheet3!L388:L987) -> Ludhiana | J36: =_xlfn.XLOOKUP(A36,A35:A634,[1]Sheet3!M388:M987) -> Furniture | K36: =_xlfn.XLOOKUP('Retail Sales'!A389,'Retail Sales'!A388:A987,[1]Sheet3!N388:N987) -> Sofa | L36: =_xlfn.XLOOKUP(A36,A35:A634,[1]Sheet3!P388:P987) -> 1 | M36: =_xlfn.XLOOKUP(A36,A35:A634,[1]Sheet3!Q388:Q987) -> 6470.7 | N36: =_xlfn.XLOOKUP(A36,A35:A634,[1]Sheet3!S388:S987) -> 0.34 | O36: =_xlfn.XLOOKUP(A36,A35:A634,[1]Sheet3!T388:T987) -> 4394.74 | P36: =_xlfn.XLOOKUP(A36,A35:A634,[1]Sheet3!U388:U987) -> 1235.03 | Q36: =_xlfn.XLOOKUP(A36,A35:A634,[1]Sheet3!V388:V987) -> 0.28102459 | R36: =_xlfn.XLOOKUP(A36,A35:A634,[1]Sheet3!W388:W987) -> 66.87 | S36: =_xlfn.XLOOKUP(A36,A35:A634,[1]Sheet3!X388:X987) -> Net Banking | T36: =_xlfn.XLOOKUP(A36,A35:A634,[1]Sheet3!Z388:Z987) -> 4 | U36: =_xlfn.XLOOKUP(A36,A35:A634,[1]Sheet3!AA388:AA987) -> FALSE | V36: =_xlfn.XLOOKUP(A36,A35:A634,[1]Sheet3!AC388:AC987) -> Delivered | W36: =_xlfn.XLOOKUP(A36,A35:A634,[1]Sheet3!AE388:AE987) -> 7
A37: ORD-00262 | B37: =_xlfn.XLOOKUP(A37,A36:A635,[1]Sheet3!C243:C842) -> 43946 | C37: =_xlfn.XLOOKUP(A37,A36:A635,[1]Sheet3!D243:D842) -> CUST33827 | D37: =_xlfn.XLOOKUP(A37,A36:A635,[1]Sheet3!E243:E842) -> Rahul Bose | E37: =_xlfn.XLOOKUP(A37,A36:A635,[1]Sheet3!G243:G842) -> 24 | F37: =_xlfn.XLOOKUP('Retail Sales'!A244,'Retail Sales'!A243:A842,[1]Sheet3!H243:H842) -> Young Adult | G37: =_xlfn.XLOOKUP(A37,A36:A635,[1]Sheet3!J243:J842) -> Male | H37: =_xlfn.XLOOKUP(A37,A36:A635,[1]Sheet3!K243:K842) -> West | I37: =_xlfn.XLOOKUP(A37,A36:A635,[1]Sheet3!L243:L842) -> Surat | J37: =_xlfn.XLOOKUP(A37,A36:A635,[1]Sheet3!M243:M842) -> Furniture | K37: =_xlfn.XLOOKUP('Retail Sales'!A244,'Retail Sales'!A243:A842,[1]Sheet3!N243:N842) -> Wardrobe | L37: =_xlfn.XLOOKUP(A37,A36:A635,[1]Sheet3!P243:P842) -> 2 | M37: =_xlfn.XLOOKUP(A37,A36:A635,[1]Sheet3!Q243:Q842) -> 3582.55 | N37: =_xlfn.XLOOKUP(A37,A36:A635,[1]Sheet3!S243:S842) -> 0.08 | O37: =_xlfn.XLOOKUP(A37,A36:A635,[1]Sheet3!T243:T842) -> 8506.99 | P37: =_xlfn.XLOOKUP(A37,A36:A635,[1]Sheet3!U243:U842) -> 2610.08 | Q37: =_xlfn.XLOOKUP(A37,A36:A635,[1]Sheet3!V243:V842) -> 0.30681592 | R37: =_xlfn.XLOOKUP(A37,A36:A635,[1]Sheet3!W243:W842) -> 54.88 | S37: =_xlfn.XLOOKUP(A37,A36:A635,[1]Sheet3!X243:X842) -> Debit Card | T37: =_xlfn.XLOOKUP(A37,A36:A635,[1]Sheet3!Z243:Z842) -> 3 | U37: =_xlfn.XLOOKUP(A37,A36:A635,[1]Sheet3!AA243:AA842) -> FALSE | V37: =_xlfn.XLOOKUP(A37,A36:A635,[1]Sheet3!AC243:AC842) -> Delivered | W37: =_xlfn.XLOOKUP(A37,A36:A635,[1]Sheet3!AE243:AE842) -> 7
A38: ORD-00267 | B38: =_xlfn.XLOOKUP(A38,A37:A636,[1]Sheet3!C366:C965) -> 43948 | C38: =_xlfn.XLOOKUP(A38,A37:A636,[1]Sheet3!D366:D965) -> CUST76356 | D38: =_xlfn.XLOOKUP(A38,A37:A636,[1]Sheet3!E366:E965) -> Aditya Pillai | E38: =_xlfn.XLOOKUP(A38,A37:A636,[1]Sheet3!G366:G965) -> 21 | F38: =_xlfn.XLOOKUP('Retail Sales'!A367,'Retail Sales'!A366:A965,[1]Sheet3!H366:H965) -> Young Adult | G38: =_xlfn.XLOOKUP(A38,A37:A636,[1]Sheet3!J366:J965) -> Female | H38: =_xlfn.XLOOKUP(A38,A37:A636,[1]Sheet3!K366:K965) -> East | I38: =_xlfn.XLOOKUP(A38,A37:A636,[1]Sheet3!L366:L965) -> Kolkata | J38: =_xlfn.XLOOKUP(A38,A37:A636,[1]Sheet3!M366:M965) -> Sports | K38: =_xlfn.XLOOKUP('Retail Sales'!A367,'Retail Sales'!A366:A965,[1]Sheet3!N366:N965) -> Football | L38: =_xlfn.XLOOKUP(A38,A37:A636,[1]Sheet3!P366:P965) -> 6 | M38: =_xlfn.XLOOKUP(A38,A37:A636,[1]Sheet3!Q366:Q965) -> 7876.81 | N38: =_xlfn.XLOOKUP(A38,A37:A636,[1]Sheet3!S366:S965) -> 0.02 | O38: =_xlfn.XLOOKUP(A38,A37:A636,[1]Sheet3!T366:T965) -> 58868.95 | P38: =_xlfn.XLOOKUP(A38,A37:A636,[1]Sheet3!U366:U965) -> 12406.43 | Q38: =_xlfn.XLOOKUP(A38,A37:A636,[1]Sheet3!V366:V965) -> 0.21074658 | R38: =_xlfn.XLOOKUP(A38,A37:A636,[1]Sheet3!W366:W965) -> 62.09 | S38: =_xlfn.XLOOKUP(A38,A37:A636,[1]Sheet3!X366:X965) -> Debit Card | T38: =_xlfn.XLOOKUP(A38,A37:A636,[1]Sheet3!Z366:Z965) -> 4 | U38: =_xlfn.XLOOKUP(A38,A37:A636,[1]Sheet3!AA366:AA965) -> FALSE | V38: =_xlfn.XLOOKUP(A38,A37:A636,[1]Sheet3!AC366:AC965) -> Shipped | W38: =_xlfn.XLOOKUP(A38,A37:A636,[1]Sheet3!AE366:AE965) -> 3
A39: ORD-00268 | B39: =_xlfn.XLOOKUP(A39,A38:A637,[1]Sheet3!C128:C727) -> 43948 | C39: =_xlfn.XLOOKUP(A39,A38:A637,[1]Sheet3!D128:D727) -> CUST64785 | D39: =_xlfn.XLOOKUP(A39,A38:A637,[1]Sheet3!E128:E727) -> Sunita Reddy | E39: =_xlfn.XLOOKUP(A39,A38:A637,[1]Sheet3!G128:G727) -> 32 | F39: =_xlfn.XLOOKUP('Retail Sales'!A129,'Retail Sales'!A128:A727,[1]Sheet3!H128:H727) -> Young Adult | G39: =_xlfn.XLOOKUP(A39,A38:A637,[1]Sheet3!J128:J727) -> Female | H39: =_xlfn.XLOOKUP(A39,A38:A637,[1]Sheet3!K128:K727) -> West | I39: =_xlfn.XLOOKUP(A39,A38:A637,[1]Sheet3!L128:L727) -> Mumbai | J39: =_xlfn.XLOOKUP(A39,A38:A637,[1]Sheet3!M128:M727) -> Books | K39: =_xlfn.XLOOKUP('Retail Sales'!A129,'Retail Sales'!A128:A727,[1]Sheet3!N128:N727) -> Cook Book | L39: =_xlfn.XLOOKUP(A39,A38:A637,[1]Sheet3!P128:P727) -> 7 | M39: =_xlfn.XLOOKUP(A39,A38:A637,[1]Sheet3!Q128:Q727) -> 257.18 | N39: =_xlfn.XLOOKUP(A39,A38:A637,[1]Sheet3!S128:S727) -> 0.29 | O39: =_xlfn.XLOOKUP(A39,A38:A637,[1]Sheet3!T128:T727) -> 1452.88 | P39: =_xlfn.XLOOKUP(A39,A38:A637,[1]Sheet3!U128:U727) -> 604.81 | Q39: =_xlfn.XLOOKUP(A39,A38:A637,[1]Sheet3!V128:V727) -> 0.41628352 | R39: =_xlfn.XLOOKUP(A39,A38:A637,[1]Sheet3!W128:W727) -> 60.36 | S39: =_xlfn.XLOOKUP(A39,A38:A637,[1]Sheet3!X128:X727) -> Credit Card | T39: =_xlfn.XLOOKUP(A39,A38:A637,[1]Sheet3!Z128:Z727) -> 1 | U39: =_xlfn.XLOOKUP(A39,A38:A637,[1]Sheet3!AA128:AA727) -> FALSE | V39: =_xlfn.XLOOKUP(A39,A38:A637,[1]Sheet3!AC128:AC727) -> Cancelled | W39: =_xlfn.XLOOKUP(A39,A38:A637,[1]Sheet3!AE128:AE727) -> 5
A40: ORD-00270 | B40: =_xlfn.XLOOKUP(A40,A39:A638,[1]Sheet3!C423:C1022) -> 43949 | C40: =_xlfn.XLOOKUP(A40,A39:A638,[1]Sheet3!D423:D1022) -> CUST73911 | D40: =_xlfn.XLOOKUP(A40,A39:A638,[1]Sheet3!E423:E1022) -> Ritu Patel | E40: =_xlfn.XLOOKUP(A40,A39:A638,[1]Sheet3!G423:G1022) -> 34.294221 | F40: =_xlfn.XLOOKUP('Retail Sales'!A424,'Retail Sales'!A423:A1022,[1]Sheet3!H423:H1022) -> Young Adult | G40: =_xlfn.XLOOKUP(A40,A39:A638,[1]Sheet3!J423:J1022) -> Other | H40: =_xlfn.XLOOKUP(A40,A39:A638,[1]Sheet3!K423:K1022) -> East | I40: =_xlfn.XLOOKUP(A40,A39:A638,[1]Sheet3!L423:L1022) -> Kolkata | J40: =_xlfn.XLOOKUP(A40,A39:A638,[1]Sheet3!M423:M1022) -> Clothing | K40: =_xlfn.XLOOKUP('Retail Sales'!A424,'Retail Sales'!A423:A1022,[1]Sheet3!N423:N1022) -> Jeans | L40: =_xlfn.XLOOKUP(A40,A39:A638,[1]Sheet3!P423:P1022) -> 6 | M40: =_xlfn.XLOOKUP(A40,A39:A638,[1]Sheet3!Q423:Q1022) -> 2934.92 | N40: =_xlfn.XLOOKUP(A40,A39:A638,[1]Sheet3!S423:S1022) -> 0.1 | O40: =_xlfn.XLOOKUP(A40,A39:A638,[1]Sheet3!T423:T1022) -> 18790.52 | P40: =_xlfn.XLOOKUP(A40,A39:A638,[1]Sheet3!U423:U1022) -> 7715.18 | Q40: =_xlfn.XLOOKUP(A40,A39:A638,[1]Sheet3!V423:V1022) -> 0.41058896 | R40: =_xlfn.XLOOKUP(A40,A39:A638,[1]Sheet3!W423:W1022) -> 74.02 | S40: =_xlfn.XLOOKUP(A40,A39:A638,[1]Sheet3!X423:X1022) -> Debit Card | T40: =_xlfn.XLOOKUP(A40,A39:A638,[1]Sheet3!Z423:Z1022) -> 5 | U40: =_xlfn.XLOOKUP(A40,A39:A638,[1]Sheet3!AA423:AA1022) -> FALSE | V40: =_xlfn.XLOOKUP(A40,A39:A638,[1]Sheet3!AC423:AC1022) -> Cancelled | W40: =_xlfn.XLOOKUP(A40,A39:A638,[1]Sheet3!AE423:AE1022) -> 8
A41: ORD-00273 | B41: =_xlfn.XLOOKUP(A41,A40:A639,[1]Sheet3!C179:C778) -> 43952 | C41: =_xlfn.XLOOKUP(A41,A40:A639,[1]Sheet3!D179:D778) -> CUST92554 | D41: =_xlfn.XLOOKUP(A41,A40:A639,[1]Sheet3!E179:E778) -> Nisha Joshi | E41: =_xlfn.XLOOKUP(A41,A40:A639,[1]Sheet3!G179:G778) -> 34 | F41: =_xlfn.XLOOKUP('Retail Sales'!A180,'Retail Sales'!A179:A778,[1]Sheet3!H179:H778) -> Young Adult | G41: =_xlfn.XLOOKUP(A41,A40:A639,[1]Sheet3!J179:J778) -> Other | H41: =_xlfn.XLOOKUP(A41,A40:A639,[1]Sheet3!K179:K778) -> West | I41: =_xlfn.XLOOKUP(A41,A40:A639,[1]Sheet3!L179:L778) -> Pune | J41: =_xlfn.XLOOKUP(A41,A40:A639,[1]Sheet3!M179:M778) -> Electronics | K41: =_xlfn.XLOOKUP('Retail Sales'!A180,'Retail Sales'!A179:A778,[1]Sheet3!N179:N778) -> Laptop | L41: =_xlfn.XLOOKUP(A41,A40:A639,[1]Sheet3!P179:P778) -> 8 | M41: =_xlfn.XLOOKUP(A41,A40:A639,[1]Sheet3!Q179:Q778) -> 74156.48 | N41: =_xlfn.XLOOKUP(A41,A40:A639,[1]Sheet3!S179:S778) -> 0.02 | O41: =_xlfn.XLOOKUP(A41,A40:A639,[1]Sheet3!T179:T778) -> 789939.57 | P41: =_xlfn.XLOOKUP(A41,A40:A639,[1]Sheet3!U179:U778) -> 58250.48 | Q41: =_xlfn.XLOOKUP(A41,A40:A639,[1]Sheet3!V179:V778) -> 0.073740425 | R41: =_xlfn.XLOOKUP(A41,A40:A639,[1]Sheet3!W179:W778) -> 75.8 | S41: =_xlfn.XLOOKUP(A41,A40:A639,[1]Sheet3!X179:X778) -> Credit Card | T41: =_xlfn.XLOOKUP(A41,A40:A639,[1]Sheet3!Z179:Z778) -> 5 | U41: =_xlfn.XLOOKUP(A41,A40:A639,[1]Sheet3!AA179:AA778) -> FALSE | V41: =_xlfn.XLOOKUP(A41,A40:A639,[1]Sheet3!AC179:AC778) -> Delivered | W41: =_xlfn.XLOOKUP(A41,A40:A639,[1]Sheet3!AE179:AE778) -> 2
A42: ORD-00280 | B42: =_xlfn.XLOOKUP(A42,A41:A640,[1]Sheet3!C193:C792) -> 43954 | C42: =_xlfn.XLOOKUP(A42,A41:A640,[1]Sheet3!D193:D792) -> CUST00544 | D42: =_xlfn.XLOOKUP(A42,A41:A640,[1]Sheet3!E193:E792) -> Sanjay Joshi | E42: =_xlfn.XLOOKUP(A42,A41:A640,[1]Sheet3!G193:G792) -> 26 | F42: =_xlfn.XLOOKUP('Retail Sales'!A194,'Retail Sales'!A193:A792,[1]Sheet3!H193:H792) -> Young Adult | G42: =_xlfn.XLOOKUP(A42,A41:A640,[1]Sheet3!J193:J792) -> Male | H42: =_xlfn.XLOOKUP(A42,A41:A640,[1]Sheet3!K193:K792) -> North | I42: =_xlfn.XLOOKUP(A42,A41:A640,[1]Sheet3!L193:L792) -> Ludhiana | J42: =_xlfn.XLOOKUP(A42,A41:A640,[1]Sheet3!M193:M792) -> Books | K42: =_xlfn.XLOOKUP('Retail Sales'!A194,'Retail Sales'!A193:A792,[1]Sheet3!N193:N792) -> Textbook | L42: =_xlfn.XLOOKUP(A42,A41:A640,[1]Sheet3!P193:P792) -> 10 | M42: =_xlfn.XLOOKUP(A42,A41:A640,[1]Sheet3!Q193:Q792) -> 1346.41 | N42: =_xlfn.XLOOKUP(A42,A41:A640,[1]Sheet3!S193:S792) -> 0.24 | O42: =_xlfn.XLOOKUP(A42,A41:A640,[1]Sheet3!T193:T792) -> 12502.33 | P42: =_xlfn.XLOOKUP(A42,A41:A640,[1]Sheet3!U193:U792) -> 5924.88 | Q42: =_xlfn.XLOOKUP(A42,A41:A640,[1]Sheet3!V193:V792) -> 0.47390206 | R42: =_xlfn.XLOOKUP(A42,A41:A640,[1]Sheet3!W193:W792) -> 55.15 | S42: =_xlfn.XLOOKUP(A42,A41:A640,[1]Sheet3!X193:X792) -> UPI | T42: =_xlfn.XLOOKUP(A42,A41:A640,[1]Sheet3!Z193:Z792) -> 1 | U42: =_xlfn.XLOOKUP(A42,A41:A640,[1]Sheet3!AA193:AA792) -> FALSE | V42: =_xlfn.XLOOKUP(A42,A41:A640,[1]Sheet3!AC193:AC792) -> Pending | W42: =_xlfn.XLOOKUP(A42,A41:A640,[1]Sheet3!AE193:AE792) -> 2
A43: ORD-00283 | B43: =_xlfn.XLOOKUP(A43,A42:A641,[1]Sheet3!C399:C998) -> 43956 | C43: =_xlfn.XLOOKUP(A43,A42:A641,[1]Sheet3!D399:D998) -> CUST17741 | D43: =_xlfn.XLOOKUP(A43,A42:A641,[1]Sheet3!E399:E998) -> Arjun Verma | E43: =_xlfn.XLOOKUP(A43,A42:A641,[1]Sheet3!G399:G998) -> 32 | F43: =_xlfn.XLOOKUP('Retail Sales'!A400,'Retail Sales'!A399:A998,[1]Sheet3!H399:H998) -> Young Adult | G43: =_xlfn.XLOOKUP(A43,A42:A641,[1]Sheet3!J399:J998) -> Female | H43: =_xlfn.XLOOKUP(A43,A42:A641,[1]Sheet3!K399:K998) -> East | I43: =_xlfn.XLOOKUP(A43,A42:A641,[1]Sheet3!L399:L998) -> Patna | J43: =_xlfn.XLOOKUP(A43,A42:A641,[1]Sheet3!M399:M998) -> Books | K43: =_xlfn.XLOOKUP('Retail Sales'!A400,'Retail Sales'!A399:A998,[1]Sheet3!N399:N998) -> Cook Book | L43: =_xlfn.XLOOKUP(A43,A42:A641,[1]Sheet3!P399:P998) -> 10 | M43: =_xlfn.XLOOKUP(A43,A42:A641,[1]Sheet3!Q399:Q998) -> 1387.77 | N43: =_xlfn.XLOOKUP(A43,A42:A641,[1]Sheet3!S399:S998) -> 0.03 | O43: =_xlfn.XLOOKUP(A43,A42:A641,[1]Sheet3!T399:T998) -> 15244.18 | P43: =_xlfn.XLOOKUP(A43,A42:A641,[1]Sheet3!U399:U998) -> 5378.75 | Q43: =_xlfn.XLOOKUP(A43,A42:A641,[1]Sheet3!V399:V998) -> 0.35283958 | R43: =_xlfn.XLOOKUP(A43,A42:A641,[1]Sheet3!W399:W998) -> 88.89 | S43: =_xlfn.XLOOKUP(A43,A42:A641,[1]Sheet3!X399:X998) -> Net Banking | T43: =_xlfn.XLOOKUP(A43,A42:A641,[1]Sheet3!Z399:Z998) -> 4 | U43: =_xlfn.XLOOKUP(A43,A42:A641,[1]Sheet3!AA399:AA998) -> FALSE | V43: =_xlfn.XLOOKUP(A43,A42:A641,[1]Sheet3!AC399:AC998) -> Delivered | W43: =_xlfn.XLOOKUP(A43,A42:A641,[1]Sheet3!AE399:AE998) -> 9
A44: ORD-00287 | B44: =_xlfn.XLOOKUP(A44,A43:A642,[1]Sheet3!C5:C604) -> 43958 | C44: =_xlfn.XLOOKUP(A44,A43:A642,[1]Sheet3!D5:D604) -> CUST58035 | D44: =_xlfn.XLOOKUP(A44,A43:A642,[1]Sheet3!E5:E604) -> Ritu Sharma | E44: =_xlfn.XLOOKUP(A44,A43:A642,[1]Sheet3!G5:G604) -> 9 | F44: =_xlfn.XLOOKUP('Retail Sales'!A6,'Retail Sales'!A5:A604,[1]Sheet3!H5:H604) -> Child | G44: =_xlfn.XLOOKUP(A44,A43:A642,[1]Sheet3!J5:J604) -> Male | H44: =_xlfn.XLOOKUP(A44,A43:A642,[1]Sheet3!K5:K604) -> Central | I44: =_xlfn.XLOOKUP(A44,A43:A642,[1]Sheet3!L5:L604) -> Nagpur | J44: =_xlfn.XLOOKUP(A44,A43:A642,[1]Sheet3!M5:M604) -> Groceries | K44: =_xlfn.XLOOKUP('Retail Sales'!A6,'Retail Sales'!A5:A604,[1]Sheet3!N5:N604) -> Cooking Oil | L44: =_xlfn.XLOOKUP(A44,A43:A642,[1]Sheet3!P5:P604) -> 1 | M44: =_xlfn.XLOOKUP(A44,A43:A642,[1]Sheet3!Q5:Q604) -> 320.06 | N44: =_xlfn.XLOOKUP(A44,A43:A642,[1]Sheet3!S5:S604) -> 0.31 | O44: =_xlfn.XLOOKUP(A44,A43:A642,[1]Sheet3!T5:T604) -> 323.95 | P44: =_xlfn.XLOOKUP(A44,A43:A642,[1]Sheet3!U5:U604) -> 31.38 | Q44: =_xlfn.XLOOKUP(A44,A43:A642,[1]Sheet3!V5:V604) -> 0.0968668 | R44: =_xlfn.XLOOKUP(A44,A43:A642,[1]Sheet3!W5:W604) -> 48.81 | S44: =_xlfn.XLOOKUP(A44,A43:A642,[1]Sheet3!X5:X604) -> Net Banking | T44: =_xlfn.XLOOKUP(A44,A43:A642,[1]Sheet3!Z5:Z604) -> 4 | U44: =_xlfn.XLOOKUP(A44,A43:A642,[1]Sheet3!AA5:AA604) -> FALSE | V44: =_xlfn.XLOOKUP(A44,A43:A642,[1]Sheet3!AC5:AC604) -> Pending | W44: =_xlfn.XLOOKUP(A44,A43:A642,[1]Sheet3!AE5:AE604) -> 4
A45: ORD-00291 | B45: =_xlfn.XLOOKUP(A45,A44:A643,[1]Sheet3!C201:C800) -> 43959 | C45: =_xlfn.XLOOKUP(A45,A44:A643,[1]Sheet3!D201:D800) -> CUST36091 | D45: =_xlfn.XLOOKUP(A45,A44:A643,[1]Sheet3!E201:E800) -> Meera Mehta | E45: =_xlfn.XLOOKUP(A45,A44:A643,[1]Sheet3!G201:G800) -> 43 | F45: =_xlfn.XLOOKUP('Retail Sales'!A202,'Retail Sales'!A201:A800,[1]Sheet3!H201:H800) -> Adult | G45: =_xlfn.XLOOKUP(A45,A44:A643,[1]Sheet3!J201:J800) -> Other | H45: =_xlfn.XLOOKUP(A45,A44:A643,[1]Sheet3!K201:K800) -> North | I45: =_xlfn.XLOOKUP(A45,A44:A643,[1]Sheet3!L201:L800) -> Delhi | J45: =_xlfn.XLOOKUP(A45,A44:A643,[1]Sheet3!M201:M800) -> Electronics | K45: =_xlfn.XLOOKUP('Retail Sales'!A202,'Retail Sales'!A201:A800,[1]Sheet3!N201:N800) -> Laptop | L45: =_xlfn.XLOOKUP(A45,A44:A643,[1]Sheet3!P201:P800) -> 5 | M45: =_xlfn.XLOOKUP(A45,A44:A643,[1]Sheet3!Q201:Q800) -> 16919.29 | N45: =_xlfn.XLOOKUP(A45,A44:A643,[1]Sheet3!S201:S800) -> 0.06 | O45: =_xlfn.XLOOKUP(A45,A44:A643,[1]Sheet3!T201:T800) -> 117489.88 | P45: =_xlfn.XLOOKUP(A45,A44:A643,[1]Sheet3!U201:U800) -> 14930.93 | Q45: =_xlfn.XLOOKUP(A45,A44:A643,[1]Sheet3!V201:V800) -> 0.12708269 | R45: =_xlfn.XLOOKUP(A45,A44:A643,[1]Sheet3!W201:W800) -> 59.99 | S45: =_xlfn.XLOOKUP(A45,A44:A643,[1]Sheet3!X201:X800) -> UPI | T45: =_xlfn.XLOOKUP(A45,A44:A643,[1]Sheet3!Z201:Z800) -> 5 | U45: =_xlfn.XLOOKUP(A45,A44:A643,[1]Sheet3!AA201:AA800) -> TRUE | V45: =_xlfn.XLOOKUP(A45,A44:A643,[1]Sheet3!AC201:AC800) -> Returned | W45: =_xlfn.XLOOKUP(A45,A44:A643,[1]Sheet3!AE201:AE800) -> 10
A46: ORD-00317 | B46: =_xlfn.XLOOKUP(A46,A45:A644,[1]Sheet3!C562:C1161) -> 43970 | C46: =_xlfn.XLOOKUP(A46,A45:A644,[1]Sheet3!D562:D1161) -> CUST52213 | D46: =_xlfn.XLOOKUP(A46,A45:A644,[1]Sheet3!E562:E1161) -> Kavya Iyer | E46: =_xlfn.XLOOKUP(A46,A45:A644,[1]Sheet3!G562:G1161) -> 53 | F46: =_xlfn.XLOOKUP('Retail Sales'!A563,'Retail Sales'!A562:A1161,[1]Sheet3!H562:H1161) -> Senior | G46: =_xlfn.XLOOKUP(A46,A45:A644,[1]Sheet3!J562:J1161) -> Other | H46: =_xlfn.XLOOKUP(A46,A45:A644,[1]Sheet3!K562:K1161) -> South | I46: =_xlfn.XLOOKUP(A46,A45:A644,[1]Sheet3!L562:L1161) -> Bangalore | J46: =_xlfn.XLOOKUP(A46,A45:A644,[1]Sheet3!M562:M1161) -> Groceries | K46: =_xlfn.XLOOKUP('Retail Sales'!A563,'Retail Sales'!A562:A1161,[1]Sheet3!N562:N1161) -> Rice (5kg) | L46: =_xlfn.XLOOKUP(A46,A45:A644,[1]Sheet3!P562:P1161) -> 4 | M46: =_xlfn.XLOOKUP(A46,A45:A644,[1]Sheet3!Q562:Q1161) -> 429.54 | N46: =_xlfn.XLOOKUP(A46,A45:A644,[1]Sheet3!S562:S1161) -> 0.06 | O46: =_xlfn.XLOOKUP(A46,A45:A644,[1]Sheet3!T562:T1161) -> 2163.54 | P46: =_xlfn.XLOOKUP(A46,A45:A644,[1]Sheet3!U562:U1161) -> 148.28 | Q46: =_xlfn.XLOOKUP(A46,A45:A644,[1]Sheet3!V562:V1161) -> 0.068535826 | R46: =_xlfn.XLOOKUP(A46,A45:A644,[1]Sheet3!W562:W1161) -> 61.97 | S46: =_xlfn.XLOOKUP(A46,A45:A644,[1]Sheet3!X562:X1161) -> Credit Card | T46: =_xlfn.XLOOKUP(A46,A45:A644,[1]Sheet3!Z562:Z1161) -> 2 | U46: =_xlfn.XLOOKUP(A46,A45:A644,[1]Sheet3!AA562:AA1161) -> TRUE | V46: =_xlfn.XLOOKUP(A46,A45:A644,[1]Sheet3!AC562:AC1161) -> Returned | W46: =_xlfn.XLOOKUP(A46,A45:A644,[1]Sheet3!AE562:AE1161) -> 7
A47: ORD-00318 | B47: =_xlfn.XLOOKUP(A47,A46:A645,[1]Sheet3!C565:C1164) -> 43971 | C47: =_xlfn.XLOOKUP(A47,A46:A645,[1]Sheet3!D565:D1164) -> CUST80292 | D47: =_xlfn.XLOOKUP(A47,A46:A645,[1]Sheet3!E565:E1164) -> Ritu Shah | E47: =_xlfn.XLOOKUP(A47,A46:A645,[1]Sheet3!G565:G1164) -> 20 | F47: =_xlfn.XLOOKUP('Retail Sales'!A566,'Retail Sales'!A565:A1164,[1]Sheet3!H565:H1164) -> Young Adult | G47: =_xlfn.XLOOKUP(A47,A46:A645,[1]Sheet3!J565:J1164) -> Other | H47: =_xlfn.XLOOKUP(A47,A46:A645,[1]Sheet3!K565:K1164) -> Central | I47: =_xlfn.XLOOKUP(A47,A46:A645,[1]Sheet3!L565:L1164) -> Raipur | J47: =_xlfn.XLOOKUP(A47,A46:A645,[1]Sheet3!M565:M1164) -> Sports | K47: =_xlfn.XLOOKUP('Retail Sales'!A566,'Retail Sales'!A565:A1164,[1]Sheet3!N565:N1164) -> Tennis Racket | L47: =_xlfn.XLOOKUP(A47,A46:A645,[1]Sheet3!P565:P1164) -> 7 | M47: =_xlfn.XLOOKUP(A47,A46:A645,[1]Sheet3!Q565:Q1164) -> 4673.19 | N47: =_xlfn.XLOOKUP(A47,A46:A645,[1]Sheet3!S565:S1164) -> 0.33 | O47: =_xlfn.XLOOKUP(A47,A46:A645,[1]Sheet3!T565:T1164) -> 25140.26 | P47: =_xlfn.XLOOKUP(A47,A46:A645,[1]Sheet3!U565:U1164) -> 7454.48 | Q47: =_xlfn.XLOOKUP(A47,A46:A645,[1]Sheet3!V565:V1164) -> 0.29651563 | R47: =_xlfn.XLOOKUP(A47,A46:A645,[1]Sheet3!W565:W1164) -> 59.8 | S47: =_xlfn.XLOOKUP(A47,A46:A645,[1]Sheet3!X565:X1164) -> Cash on Delivery | T47: =_xlfn.XLOOKUP(A47,A46:A645,[1]Sheet3!Z565:Z1164) -> 1 | U47: =_xlfn.XLOOKUP(A47,A46:A645,[1]Sheet3!AA565:AA1164) -> FALSE | V47: =_xlfn.XLOOKUP(A47,A46:A645,[1]Sheet3!AC565:AC1164) -> Delivered | W47: =_xlfn.XLOOKUP(A47,A46:A645,[1]Sheet3!AE565:AE1164) -> 4
A48: ORD-00322 | B48: =_xlfn.XLOOKUP(A48,A47:A646,[1]Sheet3!C288:C887) -> 43972 | C48: =_xlfn.XLOOKUP(A48,A47:A646,[1]Sheet3!D288:D887) -> CUST34894 | D48: =_xlfn.XLOOKUP(A48,A47:A646,[1]Sheet3!E288:E887) -> Ritu Mehta | E48: =_xlfn.XLOOKUP(A48,A47:A646,[1]Sheet3!G288:G887) -> 32 | F48: =_xlfn.XLOOKUP('Retail Sales'!A289,'Retail Sales'!A288:A887,[1]Sheet3!H288:H887) -> Young Adult | G48: =_xlfn.XLOOKUP(A48,A47:A646,[1]Sheet3!J288:J887) -> Other | H48: =_xlfn.XLOOKUP(A48,A47:A646,[1]Sheet3!K288:K887) -> East | I48: =_xlfn.XLOOKUP(A48,A47:A646,[1]Sheet3!L288:L887) -> Guwahati | J48: =_xlfn.XLOOKUP(A48,A47:A646,[1]Sheet3!M288:M887) -> Electronics | K48: =_xlfn.XLOOKUP('Retail Sales'!A289,'Retail Sales'!A288:A887,[1]Sheet3!N288:N887) -> Smartwatch | L48: =_xlfn.XLOOKUP(A48,A47:A646,[1]Sheet3!P288:P887) -> 7.0954861 | M48: =_xlfn.XLOOKUP(A48,A47:A646,[1]Sheet3!Q288:Q887) -> 59036.18 | N48: =_xlfn.XLOOKUP(A48,A47:A646,[1]Sheet3!S288:S887) -> 0.38 | O48: =_xlfn.XLOOKUP(A48,A47:A646,[1]Sheet3!T288:T887) -> 48186.78 | P48: =_xlfn.XLOOKUP(A48,A47:A646,[1]Sheet3!U288:U887) -> 5073.5 | Q48: =_xlfn.XLOOKUP(A48,A47:A646,[1]Sheet3!V288:V887) -> 0.10528821 | R48: =_xlfn.XLOOKUP(A48,A47:A646,[1]Sheet3!W288:W887) -> 67 | S48: =_xlfn.XLOOKUP(A48,A47:A646,[1]Sheet3!X288:X887) -> Net Banking | T48: =_xlfn.XLOOKUP(A48,A47:A646,[1]Sheet3!Z288:Z887) -> 4 | U48: =_xlfn.XLOOKUP(A48,A47:A646,[1]Sheet3!AA288:AA887) -> FALSE | V48: =_xlfn.XLOOKUP(A48,A47:A646,[1]Sheet3!AC288:AC887) -> Delivered | W48: =_xlfn.XLOOKUP(A48,A47:A646,[1]Sheet3!AE288:AE887) -> 3
A49: ORD-00337 | B49: =_xlfn.XLOOKUP(A49,A48:A647,[1]Sheet3!C316:C915) -> 43977 | C49: =_xlfn.XLOOKUP(A49,A48:A647,[1]Sheet3!D316:D915) -> CUST25152 | D49: =_xlfn.XLOOKUP(A49,A48:A647,[1]Sheet3!E316:E915) -> Shreya Mishra | E49: =_xlfn.XLOOKUP(A49,A48:A647,[1]Sheet3!G316:G915) -> 61 | F49: =_xlfn.XLOOKUP('Retail Sales'!A317,'Retail Sales'!A316:A915,[1]Sheet3!H316:H915) -> Senior | G49: =_xlfn.XLOOKUP(A49,A48:A647,[1]Sheet3!J316:J915) -> Female | H49: =_xlfn.XLOOKUP(A49,A48:A647,[1]Sheet3!K316:K915) -> West | I49: =_xlfn.XLOOKUP(A49,A48:A647,[1]Sheet3!L316:L915) -> Ahmedabad | J49: =_xlfn.XLOOKUP(A49,A48:A647,[1]Sheet3!M316:M915) -> Books | K49: =_xlfn.XLOOKUP('Retail Sales'!A317,'Retail Sales'!A316:A915,[1]Sheet3!N316:N915) -> Cook Book | L49: =_xlfn.XLOOKUP(A49,A48:A647,[1]Sheet3!P316:P915) -> 2 | M49: =_xlfn.XLOOKUP(A49,A48:A647,[1]Sheet3!Q316:Q915) -> 425.83 | N49: =_xlfn.XLOOKUP(A49,A48:A647,[1]Sheet3!S316:S915) -> 0.04 | O49: =_xlfn.XLOOKUP(A49,A48:A647,[1]Sheet3!T316:T915) -> 846.36 | P49: =_xlfn.XLOOKUP(A49,A48:A647,[1]Sheet3!U316:U915) -> 364.43 | Q49: =_xlfn.XLOOKUP(A49,A48:A647,[1]Sheet3!V316:V915) -> 0.43058509 | R49: =_xlfn.XLOOKUP(A49,A48:A647,[1]Sheet3!W316:W915) -> 42.68 | S49: =_xlfn.XLOOKUP(A49,A48:A647,[1]Sheet3!X316:X915) -> UPI | T49: =_xlfn.XLOOKUP(A49,A48:A647,[1]Sheet3!Z316:Z915) -> 4 | U49: =_xlfn.XLOOKUP(A49,A48:A647,[1]Sheet3!AA316:AA915) -> FALSE | V49: =_xlfn.XLOOKUP(A49,A48:A647,[1]Sheet3!AC316:AC915) -> Delivered | W49: =_xlfn.XLOOKUP(A49,A48:A647,[1]Sheet3!AE316:AE915) -> 10
A50: ORD-00339 | B50: =_xlfn.XLOOKUP(A50,A49:A648,[1]Sheet3!C216:C815) -> 43978 | C50: =_xlfn.XLOOKUP(A50,A49:A648,[1]Sheet3!D216:D815) -> CUST65020 | D50: =_xlfn.XLOOKUP(A50,A49:A648,[1]Sheet3!E216:E815) -> Pooja Bhat | E50: =_xlfn.XLOOKUP(A50,A49:A648,[1]Sheet3!G216:G815) -> 28 | F50: =_xlfn.XLOOKUP('Retail Sales'!A217,'Retail Sales'!A216:A815,[1]Sheet3!H216:H815) -> Young Adult | G50: =_xlfn.XLOOKUP(A50,A49:A648,[1]Sheet3!J216:J815) -> Other | H50: =_xlfn.XLOOKUP(A50,A49:A648,[1]Sheet3!K216:K815) -> West | I50: =_xlfn.XLOOKUP(A50,A49:A648,[1]Sheet3!L216:L815) -> Pune | J50: =_xlfn.XLOOKUP(A50,A49:A648,[1]Sheet3!M216:M815) -> Furniture | K50: =_xlfn.XLOOKUP('Retail Sales'!A217,'Retail Sales'!A216:A815,[1]Sheet3!N216:N815) -> Wardrobe | L50: =_xlfn.XLOOKUP(A50,A49:A648,[1]Sheet3!P216:P815) -> 10 | M50: =_xlfn.XLOOKUP(A50,A49:A648,[1]Sheet3!Q216:Q815) -> 2690.93 | N50: =_xlfn.XLOOKUP(A50,A49:A648,[1]Sheet3!S216:S815) -> 0.35 | O50: =_xlfn.XLOOKUP(A50,A49:A648,[1]Sheet3!T216:T815) -> 23373.24 | P50: =_xlfn.XLOOKUP(A50,A49:A648,[1]Sheet3!U216:U815) -> 7410.64 | Q50: =_xlfn.XLOOKUP(A50,A49:A648,[1]Sheet3!V216:V815) -> 0.3170566 | R50: =_xlfn.XLOOKUP(A50,A49:A648,[1]Sheet3!W216:W815) -> 43.86 | S50: =_xlfn.XLOOKUP(A50,A49:A648,[1]Sheet3!X216:X815) -> UPI | T50: =_xlfn.XLOOKUP(A50,A49:A648,[1]Sheet3!Z216:Z815) -> 4 | U50: =_xlfn.XLOOKUP(A50,A49:A648,[1]Sheet3!AA216:AA815) -> TRUE | V50: =_xlfn.XLOOKUP(A50,A49:A648,[1]Sheet3!AC216:AC815) -> Returned | W50: =_xlfn.XLOOKUP(A50,A49:A648,[1]Sheet3!AE216:AE815) -> 4
A51: ORD-00343 | B51: =_xlfn.XLOOKUP(A51,A50:A649,[1]Sheet3!C348:C947) -> 43979 | C51: =_xlfn.XLOOKUP(A51,A50:A649,[1]Sheet3!D348:D947) -> CUST91659 | D51: =_xlfn.XLOOKUP(A51,A50:A649,[1]Sheet3!E348:E947) -> Shreya Verma | E51: =_xlfn.XLOOKUP(A51,A50:A649,[1]Sheet3!G348:G947) -> 20 | F51: =_xlfn.XLOOKUP('Retail Sales'!A349,'Retail Sales'!A348:A947,[1]Sheet3!H348:H947) -> Young Adult | G51: =_xlfn.XLOOKUP(A51,A50:A649,[1]Sheet3!J348:J947) -> Male | H51: =_xlfn.XLOOKUP(A51,A50:A649,[1]Sheet3!K348:K947) -> Central | I51: =_xlfn.XLOOKUP(A51,A50:A649,[1]Sheet3!L348:L947) -> Nagpur | J51: =_xlfn.XLOOKUP(A51,A50:A649,[1]Sheet3!M348:M947) -> Clothing | K51: =_xlfn.XLOOKUP('Retail Sales'!A349,'Retail Sales'!A348:A947,[1]Sheet3!N348:N947) -> Kurta | L51: =_xlfn.XLOOKUP(A51,A50:A649,[1]Sheet3!P348:P947) -> 1 | M51: =_xlfn.XLOOKUP(A51,A50:A649,[1]Sheet3!Q348:Q947) -> 1604.88 | N51: =_xlfn.XLOOKUP(A51,A50:A649,[1]Sheet3!S348:S947) -> 0.22 | O51: =_xlfn.XLOOKUP(A51,A50:A649,[1]Sheet3!T348:T947) -> 1620.42 | P51: =_xlfn.XLOOKUP(A51,A50:A649,[1]Sheet3!U348:U947) -> 414.75 | Q51: =_xlfn.XLOOKUP(A51,A50:A649,[1]Sheet3!V348:V947) -> 0.25595216 | R51: =_xlfn.XLOOKUP(A51,A50:A649,[1]Sheet3!W348:W947) -> 71.08 | S51: =_xlfn.XLOOKUP(A51,A50:A649,[1]Sheet3!X348:X947) -> Debit Card | T51: =_xlfn.XLOOKUP(A51,A50:A649,[1]Sheet3!Z348:Z947) -> 3 | U51: =_xlfn.XLOOKUP(A51,A50:A649,[1]Sheet3!AA348:AA947) -> TRUE | V51: =_xlfn.XLOOKUP(A51,A50:A649,[1]Sheet3!AC348:AC947) -> Returned | W51: =_xlfn.XLOOKUP(A51,A50:A649,[1]Sheet3!AE348:AE947) -> 4
A52: ORD-00346 | B52: =_xlfn.XLOOKUP(A52,A51:A650,[1]Sheet3!C488:C1087) -> 43979 | C52: =_xlfn.XLOOKUP(A52,A51:A650,[1]Sheet3!D488:D1087) -> CUST21580 | D52: =_xlfn.XLOOKUP(A52,A51:A650,[1]Sheet3!E488:E1087) -> Pooja Bhat | E52: =_xlfn.XLOOKUP(A52,A51:A650,[1]Sheet3!G488:G1087) -> 35 | F52: =_xlfn.XLOOKUP('Retail Sales'!A489,'Retail Sales'!A488:A1087,[1]Sheet3!H488:H1087) -> Young Adult | G52: =_xlfn.XLOOKUP(A52,A51:A650,[1]Sheet3!J488:J1087) -> Other | H52: =_xlfn.XLOOKUP(A52,A51:A650,[1]Sheet3!K488:K1087) -> East | I52: =_xlfn.XLOOKUP(A52,A51:A650,[1]Sheet3!L488:L1087) -> Kolkata | J52: =_xlfn.XLOOKUP(A52,A51:A650,[1]Sheet3!M488:M1087) -> Groceries | K52: =_xlfn.XLOOKUP('Retail Sales'!A489,'Retail Sales'!A488:A1087,[1]Sheet3!N488:N1087) -> Sugar | L52: =_xlfn.XLOOKUP(A52,A51:A650,[1]Sheet3!P488:P1087) -> 9 | M52: =_xlfn.XLOOKUP(A52,A51:A650,[1]Sheet3!Q488:Q1087) -> 213.6 | N52: =_xlfn.XLOOKUP(A52,A51:A650,[1]Sheet3!S488:S1087) -> 0.32 | O52: =_xlfn.XLOOKUP(A52,A51:A650,[1]Sheet3!T488:T1087) -> 1665.43 | P52: =_xlfn.XLOOKUP(A52,A51:A650,[1]Sheet3!U488:U1087) -> 193.99 | Q52: =_xlfn.XLOOKUP(A52,A51:A650,[1]Sheet3!V488:V1087) -> 0.11648043 | R52: =_xlfn.XLOOKUP(A52,A51:A650,[1]Sheet3!W488:W1087) -> 101.52 | S52: =_xlfn.XLOOKUP(A52,A51:A650,[1]Sheet3!X488:X1087) -> Net Banking | T52: =_xlfn.XLOOKUP(A52,A51:A650,[1]Sheet3!Z488:Z1087) -> 4 | U52: =_xlfn.XLOOKUP(A52,A51:A650,[1]Sheet3!AA488:AA1087) -> FALSE | V52: =_xlfn.XLOOKUP(A52,A51:A650,[1]Sheet3!AC488:AC1087) -> Cancelled | W52: =_xlfn.XLOOKUP(A52,A51:A650,[1]Sheet3!AE488:AE1087) -> 4
A53: ORD-00350 | B53: =_xlfn.XLOOKUP(A53,A52:A651,[1]Sheet3!C556:C1155) -> 43981 | C53: =_xlfn.XLOOKUP(A53,A52:A651,[1]Sheet3!D556:D1155) -> CUST72810 | D53: =_xlfn.XLOOKUP(A53,A52:A651,[1]Sheet3!E556:E1155) -> Arjun Reddy | E53: =_xlfn.XLOOKUP(A53,A52:A651,[1]Sheet3!G556:G1155) -> 26 | F53: =_xlfn.XLOOKUP('Retail Sales'!A557,'Retail Sales'!A556:A1155,[1]Sheet3!H556:H1155) -> Young Adult | G53: =_xlfn.XLOOKUP(A53,A52:A651,[1]Sheet3!J556:J1155) -> Male | H53: =_xlfn.XLOOKUP(A53,A52:A651,[1]Sheet3!K556:K1155) -> East | I53: =_xlfn.XLOOKUP(A53,A52:A651,[1]Sheet3!L556:L1155) -> Guwahati | J53: =_xlfn.XLOOKUP(A53,A52:A651,[1]Sheet3!M556:M1155) -> Clothing | K53: =_xlfn.XLOOKUP('Retail Sales'!A557,'Retail Sales'!A556:A1155,[1]Sheet3!N556:N1155) -> Kurta | L53: =_xlfn.XLOOKUP(A53,A52:A651,[1]Sheet3!P556:P1155) -> 10 | M53: =_xlfn.XLOOKUP(A53,A52:A651,[1]Sheet3!Q556:Q1155) -> 2738.51 | N53: =_xlfn.XLOOKUP(A53,A52:A651,[1]Sheet3!S556:S1155) -> 0.12 | O53: =_xlfn.XLOOKUP(A53,A52:A651,[1]Sheet3!T556:T1155) -> 31229.97 | P53: =_xlfn.XLOOKUP(A53,A52:A651,[1]Sheet3!U556:U1155) -> 10815.02 | Q53: =_xlfn.XLOOKUP(A53,A52:A651,[1]Sheet3!V556:V1155) -> 0.34630261 | R53: =_xlfn.XLOOKUP(A53,A52:A651,[1]Sheet3!W556:W1155) -> 81.19 | S53: =_xlfn.XLOOKUP(A53,A52:A651,[1]Sheet3!X556:X1155) -> Credit Card | T53: =_xlfn.XLOOKUP(A53,A52:A651,[1]Sheet3!Z556:Z1155) -> 5 | U53: =_xlfn.XLOOKUP(A53,A52:A651,[1]Sheet3!AA556:AA1155) -> FALSE | V53: =_xlfn.XLOOKUP(A53,A52:A651,[1]Sheet3!AC556:AC1155) -> Delivered | W53: =_xlfn.XLOOKUP(A53,A52:A651,[1]Sheet3!AE556:AE1155) -> 4
A54: ORD-00354 | B54: =_xlfn.XLOOKUP(A54,A53:A652,[1]Sheet3!C318:C917) -> 43983 | C54: =_xlfn.XLOOKUP(A54,A53:A652,[1]Sheet3!D318:D917) -> CUST12677 | D54: =_xlfn.XLOOKUP(A54,A53:A652,[1]Sheet3!E318:E917) -> Aditya Shah | E54: =_xlfn.XLOOKUP(A54,A53:A652,[1]Sheet3!G318:G917) -> 41 | F54: =_xlfn.XLOOKUP('Retail Sales'!A319,'Retail Sales'!A318:A917,[1]Sheet3!H318:H917) -> Adult | G54: =_xlfn.XLOOKUP(A54,A53:A652,[1]Sheet3!J318:J917) -> Other | H54: =_xlfn.XLOOKUP(A54,A53:A652,[1]Sheet3!K318:K917) -> North | I54: =_xlfn.XLOOKUP(A54,A53:A652,[1]Sheet3!L318:L917) -> Chandigarh | J54: =_xlfn.XLOOKUP(A54,A53:A652,[1]Sheet3!M318:M917) -> Groceries | K54: =_xlfn.XLOOKUP('Retail Sales'!A319,'Retail Sales'!A318:A917,[1]Sheet3!N318:N917) -> Rice (5kg) | L54: =_xlfn.XLOOKUP(A54,A53:A652,[1]Sheet3!P318:P917) -> 8 | M54: =_xlfn.XLOOKUP(A54,A53:A652,[1]Sheet3!Q318:Q917) -> 294.27 | N54: =_xlfn.XLOOKUP(A54,A53:A652,[1]Sheet3!S318:S917) -> 0.35 | O54: =_xlfn.XLOOKUP(A54,A53:A652,[1]Sheet3!T318:T917) -> 1927.79 | P54: =_xlfn.XLOOKUP(A54,A53:A652,[1]Sheet3!U318:U917) -> 96.62 | Q54: =_xlfn.XLOOKUP(A54,A53:A652,[1]Sheet3!V318:V917) -> 0.050119567 | R54: =_xlfn.XLOOKUP(A54,A53:A652,[1]Sheet3!W318:W917) -> 53.97 | S54: =_xlfn.XLOOKUP(A54,A53:A652,[1]Sheet3!X318:X917) -> Cash on Delivery | T54: =_xlfn.XLOOKUP(A54,A53:A652,[1]Sheet3!Z318:Z917) -> 1 | U54: =_xlfn.XLOOKUP(A54,A53:A652,[1]Sheet3!AA318:AA917) -> FALSE | V54: =_xlfn.XLOOKUP(A54,A53:A652,[1]Sheet3!AC318:AC917) -> Delivered | W54: =_xlfn.XLOOKUP(A54,A53:A652,[1]Sheet3!AE318:AE917) -> 5
A55: ORD-00357 | B55: =_xlfn.XLOOKUP(A55,A54:A653,[1]Sheet3!C58:C657) -> 43984 | C55: =_xlfn.XLOOKUP(A55,A54:A653,[1]Sheet3!D58:D657) -> CUST75375 | D55: =_xlfn.XLOOKUP(A55,A54:A653,[1]Sheet3!E58:E657) -> Priya Joshi | E55: =_xlfn.XLOOKUP(A55,A54:A653,[1]Sheet3!G58:G657) -> 41 | F55: =_xlfn.XLOOKUP('Retail Sales'!A59,'Retail Sales'!A58:A657,[1]Sheet3!H58:H657) -> Adult | G55: =_xlfn.XLOOKUP(A55,A54:A653,[1]Sheet3!J58:J657) -> Female | H55: =_xlfn.XLOOKUP(A55,A54:A653,[1]Sheet3!K58:K657) -> Central | I55: =_xlfn.XLOOKUP(A55,A54:A653,[1]Sheet3!L58:L657) -> Nagpur | J55: =_xlfn.XLOOKUP(A55,A54:A653,[1]Sheet3!M58:M657) -> Clothing | K55: =_xlfn.XLOOKUP('Retail Sales'!A59,'Retail Sales'!A58:A657,[1]Sheet3!N58:N657) -> Jeans | L55: =_xlfn.XLOOKUP(A55,A54:A653,[1]Sheet3!P58:P657) -> 2 | M55: =_xlfn.XLOOKUP(A55,A54:A653,[1]Sheet3!Q58:Q657) -> 1548.43 | N55: =_xlfn.XLOOKUP(A55,A54:A653,[1]Sheet3!S58:S657) -> 0.38 | O55: =_xlfn.XLOOKUP(A55,A54:A653,[1]Sheet3!T58:T657) -> 2480.54 | P55: =_xlfn.XLOOKUP(A55,A54:A653,[1]Sheet3!U58:U657) -> 866.5 | Q55: =_xlfn.XLOOKUP(A55,A54:A653,[1]Sheet3!V58:V657) -> 0.3493191 | R55: =_xlfn.XLOOKUP(A55,A54:A653,[1]Sheet3!W58:W657) -> 49.01 | S55: =_xlfn.XLOOKUP(A55,A54:A653,[1]Sheet3!X58:X657) -> EMI | T55: =_xlfn.XLOOKUP(A55,A54:A653,[1]Sheet3!Z58:Z657) -> 1 | U55: =_xlfn.XLOOKUP(A55,A54:A653,[1]Sheet3!AA58:AA657) -> FALSE | V55: =_xlfn.XLOOKUP(A55,A54:A653,[1]Sheet3!AC58:AC657) -> Delivered | W55: =_xlfn.XLOOKUP(A55,A54:A653,[1]Sheet3!AE58:AE657) -> 5
A56: ORD-00362 | B56: =_xlfn.XLOOKUP(A56,A55:A654,[1]Sheet3!C11:C610) -> 43986 | C56: =_xlfn.XLOOKUP(A56,A55:A654,[1]Sheet3!D11:D610) -> CUST80340 | D56: =_xlfn.XLOOKUP(A56,A55:A654,[1]Sheet3!E11:E610) -> Meera Mishra | E56: =_xlfn.XLOOKUP(A56,A55:A654,[1]Sheet3!G11:G610) -> 51 | F56: =_xlfn.XLOOKUP('Retail Sales'!A12,'Retail Sales'!A11:A610,[1]Sheet3!H11:H610) -> Senior | G56: =_xlfn.XLOOKUP(A56,A55:A654,[1]Sheet3!J11:J610) -> Other | H56: =_xlfn.XLOOKUP(A56,A55:A654,[1]Sheet3!K11:K610) -> Central | I56: =_xlfn.XLOOKUP(A56,A55:A654,[1]Sheet3!L11:L610) -> Raipur | J56: =_xlfn.XLOOKUP(A56,A55:A654,[1]Sheet3!M11:M610) -> Furniture | K56: =_xlfn.XLOOKUP('Retail Sales'!A12,'Retail Sales'!A11:A610,[1]Sheet3!N11:N610) -> Wardrobe | L56: =_xlfn.XLOOKUP(A56,A55:A654,[1]Sheet3!P11:P610) -> 3 | M56: =_xlfn.XLOOKUP(A56,A55:A654,[1]Sheet3!Q11:Q610) -> 24460.8 | N56: =_xlfn.XLOOKUP(A56,A55:A654,[1]Sheet3!S11:S610) -> 0.15 | O56: =_xlfn.XLOOKUP(A56,A55:A654,[1]Sheet3!T11:T610) -> 86997.39 | P56: =_xlfn.XLOOKUP(A56,A55:A654,[1]Sheet3!U11:U610) -> 14762.22 | Q56: =_xlfn.XLOOKUP(A56,A55:A654,[1]Sheet3!V11:V610) -> 0.16968578 | R56: =_xlfn.XLOOKUP(A56,A55:A654,[1]Sheet3!W11:W610) -> 60.11 | S56: =_xlfn.XLOOKUP(A56,A55:A654,[1]Sheet3!X11:X610) -> UPI | T56: =_xlfn.XLOOKUP(A56,A55:A654,[1]Sheet3!Z11:Z610) -> 1 | U56: =_xlfn.XLOOKUP(A56,A55:A654,[1]Sheet3!AA11:AA610) -> FALSE | V56: =_xlfn.XLOOKUP(A56,A55:A654,[1]Sheet3!AC11:AC610) -> Delivered | W56: =_xlfn.XLOOKUP(A56,A55:A654,[1]Sheet3!AE11:AE610) -> 8
A57: ORD-00364 | B57: =_xlfn.XLOOKUP(A57,A56:A655,[1]Sheet3!C56:C655) -> 43986 | C57: =_xlfn.XLOOKUP(A57,A56:A655,[1]Sheet3!D56:D655) -> CUST12024 | D57: =_xlfn.XLOOKUP(A57,A56:A655,[1]Sheet3!E56:E655) -> Shreya Kumar | E57: =_xlfn.XLOOKUP(A57,A56:A655,[1]Sheet3!G56:G655) -> 37 | F57: =_xlfn.XLOOKUP('Retail Sales'!A57,'Retail Sales'!A56:A655,[1]Sheet3!H56:H655) -> Adult | G57: =_xlfn.XLOOKUP(A57,A56:A655,[1]Sheet3!J56:J655) -> Male | H57: =_xlfn.XLOOKUP(A57,A56:A655,[1]Sheet3!K56:K655) -> West | I57: =_xlfn.XLOOKUP(A57,A56:A655,[1]Sheet3!L56:L655) -> Surat | J57: =_xlfn.XLOOKUP(A57,A56:A655,[1]Sheet3!M56:M655) -> Sports | K57: =_xlfn.XLOOKUP('Retail Sales'!A57,'Retail Sales'!A56:A655,[1]Sheet3!N56:N655) -> Football | L57: =_xlfn.XLOOKUP(A57,A56:A655,[1]Sheet3!P56:P655) -> 3 | M57: =_xlfn.XLOOKUP(A57,A56:A655,[1]Sheet3!Q56:Q655) -> 2684.91 | N57: =_xlfn.XLOOKUP(A57,A56:A655,[1]Sheet3!S56:S655) -> 0.15 | O57: =_xlfn.XLOOKUP(A57,A56:A655,[1]Sheet3!T56:T655) -> 9541.81 | P57: =_xlfn.XLOOKUP(A57,A56:A655,[1]Sheet3!U56:U655) -> 2543.29 | Q57: =_xlfn.XLOOKUP(A57,A56:A655,[1]Sheet3!V56:V655) -> 0.26654167 | R57: =_xlfn.XLOOKUP(A57,A56:A655,[1]Sheet3!W56:W655) -> 67.28 | S57: =_xlfn.XLOOKUP(A57,A56:A655,[1]Sheet3!X56:X655) -> Net Banking | T57: =_xlfn.XLOOKUP(A57,A56:A655,[1]Sheet3!Z56:Z655) -> 2 | U57: =_xlfn.XLOOKUP(A57,A56:A655,[1]Sheet3!AA56:AA655) -> FALSE | V57: =_xlfn.XLOOKUP(A57,A56:A655,[1]Sheet3!AC56:AC655) -> Delivered | W57: =_xlfn.XLOOKUP(A57,A56:A655,[1]Sheet3!AE56:AE655) -> 9
A58: ORD-00379 | B58: =_xlfn.XLOOKUP(A58,A57:A656,[1]Sheet3!C483:C1082) -> 43992 | C58: =_xlfn.XLOOKUP(A58,A57:A656,[1]Sheet3!D483:D1082) -> CUST57932 | D58: =_xlfn.XLOOKUP(A58,A57:A656,[1]Sheet3!E483:E1082) -> Rohan Bhat | E58: =_xlfn.XLOOKUP(A58,A57:A656,[1]Sheet3!G483:G1082) -> 24 | F58: =_xlfn.XLOOKUP('Retail Sales'!A484,'Retail Sales'!A483:A1082,[1]Sheet3!H483:H1082) -> Young Adult | G58: =_xlfn.XLOOKUP(A58,A57:A656,[1]Sheet3!J483:J1082) -> Male | H58: =_xlfn.XLOOKUP(A58,A57:A656,[1]Sheet3!K483:K1082) -> Central | I58: =_xlfn.XLOOKUP(A58,A57:A656,[1]Sheet3!L483:L1082) -> Bhopal | J58: =_xlfn.XLOOKUP(A58,A57:A656,[1]Sheet3!M483:M1082) -> Clothing | K58: =_xlfn.XLOOKUP('Retail Sales'!A484,'Retail Sales'!A483:A1082,[1]Sheet3!N483:N1082) -> Jeans | L58: =_xlfn.XLOOKUP(A58,A57:A656,[1]Sheet3!P483:P1082) -> 2 | M58: =_xlfn.XLOOKUP(A58,A57:A656,[1]Sheet3!Q483:Q1082) -> 1835.19 | N58: =_xlfn.XLOOKUP(A58,A57:A656,[1]Sheet3!S483:S1082) -> 0.03 | O58: =_xlfn.XLOOKUP(A58,A57:A656,[1]Sheet3!T483:T1082) -> 4360.69 | P58: =_xlfn.XLOOKUP(A58,A57:A656,[1]Sheet3!U483:U1082) -> 1812.7 | Q58: =_xlfn.XLOOKUP(A58,A57:A656,[1]Sheet3!V483:V1082) -> 0.41569109 | R58: =_xlfn.XLOOKUP(A58,A57:A656,[1]Sheet3!W483:W1082) -> 37.12 | S58: =_xlfn.XLOOKUP(A58,A57:A656,[1]Sheet3!X483:X1082) -> EMI | T58: =_xlfn.XLOOKUP(A58,A57:A656,[1]Sheet3!Z483:Z1082) -> 5 | U58: =_xlfn.XLOOKUP(A58,A57:A656,[1]Sheet3!AA483:AA1082) -> FALSE | V58: =_xlfn.XLOOKUP(A58,A57:A656,[1]Sheet3!AC483:AC1082) -> Delivered | W58: =_xlfn.XLOOKUP(A58,A57:A656,[1]Sheet3!AE483:AE1082) -> 2
A59: ORD-00384 | B59: =_xlfn.XLOOKUP(A59,A58:A657,[1]Sheet3!C413:C1012) -> 43994 | C59: =_xlfn.XLOOKUP(A59,A58:A657,[1]Sheet3!D413:D1012) -> CUST60562 | D59: =_xlfn.XLOOKUP(A59,A58:A657,[1]Sheet3!E413:E1012) -> Kavya Rao | E59: =_xlfn.XLOOKUP(A59,A58:A657,[1]Sheet3!G413:G1012) -> 25 | F59: =_xlfn.XLOOKUP('Retail Sales'!A414,'Retail Sales'!A413:A1012,[1]Sheet3!H413:H1012) -> Young Adult | G59: =_xlfn.XLOOKUP(A59,A58:A657,[1]Sheet3!J413:J1012) -> Male | H59: =_xlfn.XLOOKUP(A59,A58:A657,[1]Sheet3!K413:K1012) -> North | I59: =_xlfn.XLOOKUP(A59,A58:A657,[1]Sheet3!L413:L1012) -> Ludhiana | J59: =_xlfn.XLOOKUP(A59,A58:A657,[1]Sheet3!M413:M1012) -> Clothing | K59: =_xlfn.XLOOKUP('Retail Sales'!A414,'Retail Sales'!A413:A1012,[1]Sheet3!N413:N1012) -> Dress | L59: =_xlfn.XLOOKUP(A59,A58:A657,[1]Sheet3!P413:P1012) -> 10 | M59: =_xlfn.XLOOKUP(A59,A58:A657,[1]Sheet3!Q413:Q1012) -> 658.16 | N59: =_xlfn.XLOOKUP(A59,A58:A657,[1]Sheet3!S413:S1012) -> 0.25 | O59: =_xlfn.XLOOKUP(A59,A58:A657,[1]Sheet3!T413:T1012) -> 6367.6 | P59: =_xlfn.XLOOKUP(A59,A58:A657,[1]Sheet3!U413:U1012) -> 1841.64 | Q59: =_xlfn.XLOOKUP(A59,A58:A657,[1]Sheet3!V413:V1012) -> 0.28922043 | R59: =_xlfn.XLOOKUP(A59,A58:A657,[1]Sheet3!W413:W1012) -> 63.58 | S59: =_xlfn.XLOOKUP(A59,A58:A657,[1]Sheet3!X413:X1012) -> Cash on Delivery | T59: =_xlfn.XLOOKUP(A59,A58:A657,[1]Sheet3!Z413:Z1012) -> 1 | U59: =_xlfn.XLOOKUP(A59,A58:A657,[1]Sheet3!AA413:AA1012) -> FALSE | V59: =_xlfn.XLOOKUP(A59,A58:A657,[1]Sheet3!AC413:AC1012) -> Delivered | W59: =_xlfn.XLOOKUP(A59,A58:A657,[1]Sheet3!AE413:AE1012) -> 7
A60: ORD-00402 | B60: =_xlfn.XLOOKUP(A60,A59:A658,[1]Sheet3!C85:C684) -> 44003 | C60: =_xlfn.XLOOKUP(A60,A59:A658,[1]Sheet3!D85:D684) -> CUST55018 | D60: =_xlfn.XLOOKUP(A60,A59:A658,[1]Sheet3!E85:E684) -> Vikram Nair | E60: =_xlfn.XLOOKUP(A60,A59:A658,[1]Sheet3!G85:G684) -> 37 | F60: =_xlfn.XLOOKUP('Retail Sales'!A86,'Retail Sales'!A85:A684,[1]Sheet3!H85:H684) -> Adult | G60: =_xlfn.XLOOKUP(A60,A59:A658,[1]Sheet3!J85:J684) -> Other | H60: =_xlfn.XLOOKUP(A60,A59:A658,[1]Sheet3!K85:K684) -> South | I60: =_xlfn.XLOOKUP(A60,A59:A658,[1]Sheet3!L85:L684) -> Chennai | J60: =_xlfn.XLOOKUP(A60,A59:A658,[1]Sheet3!M85:M684) -> Electronics | K60: =_xlfn.XLOOKUP('Retail Sales'!A86,'Retail Sales'!A85:A684,[1]Sheet3!N85:N684) -> Headphones | L60: =_xlfn.XLOOKUP(A60,A59:A658,[1]Sheet3!P85:P684) -> 5 | M60: =_xlfn.XLOOKUP(A60,A59:A658,[1]Sheet3!Q85:Q684) -> 28892.57 | N60: =_xlfn.XLOOKUP(A60,A59:A658,[1]Sheet3!S85:S684) -> 0.07 | O60: =_xlfn.XLOOKUP(A60,A59:A658,[1]Sheet3!T85:T684) -> 205453.46 | P60: =_xlfn.XLOOKUP(A60,A59:A658,[1]Sheet3!U85:U684) -> 25286.68 | Q60: =_xlfn.XLOOKUP(A60,A59:A658,[1]Sheet3!V85:V684) -> 0.12307741 | R60: =_xlfn.XLOOKUP(A60,A59:A658,[1]Sheet3!W85:W684) -> 84.72 | S60: =_xlfn.XLOOKUP(A60,A59:A658,[1]Sheet3!X85:X684) -> Debit Card | T60: =_xlfn.XLOOKUP(A60,A59:A658,[1]Sheet3!Z85:Z684) -> 5 | U60: =_xlfn.XLOOKUP(A60,A59:A658,[1]Sheet3!AA85:AA684) -> FALSE | V60: =_xlfn.XLOOKUP(A60,A59:A658,[1]Sheet3!AC85:AC684) -> Delivered | W60: =_xlfn.XLOOKUP(A60,A59:A658,[1]Sheet3!AE85:AE684) -> 6
A61: ORD-00403 | B61: =_xlfn.XLOOKUP(A61,A60:A659,[1]Sheet3!C207:C806) -> 44004 | C61: =_xlfn.XLOOKUP(A61,A60:A659,[1]Sheet3!D207:D806) -> CUST52549 | D61: =_xlfn.XLOOKUP(A61,A60:A659,[1]Sheet3!E207:E806) -> Pooja Rao | E61: =_xlfn.XLOOKUP(A61,A60:A659,[1]Sheet3!G207:G806) -> 32 | F61: =_xlfn.XLOOKUP('Retail Sales'!A208,'Retail Sales'!A207:A806,[1]Sheet3!H207:H806) -> Young Adult | G61: =_xlfn.XLOOKUP(A61,A60:A659,[1]Sheet3!J207:J806) -> Other | H61: =_xlfn.XLOOKUP(A61,A60:A659,[1]Sheet3!K207:K806) -> North | I61: =_xlfn.XLOOKUP(A61,A60:A659,[1]Sheet3!L207:L806) -> Delhi | J61: =_xlfn.XLOOKUP(A61,A60:A659,[1]Sheet3!M207:M806) -> Clothing | K61: =_xlfn.XLOOKUP('Retail Sales'!A208,'Retail Sales'!A207:A806,[1]Sheet3!N207:N806) -> T-Shirt | L61: =_xlfn.XLOOKUP(A61,A60:A659,[1]Sheet3!P207:P806) -> 7 | M61: =_xlfn.XLOOKUP(A61,A60:A659,[1]Sheet3!Q207:Q806) -> 2701.8 | N61: =_xlfn.XLOOKUP(A61,A60:A659,[1]Sheet3!S207:S806) -> 0.09 | O61: =_xlfn.XLOOKUP(A61,A60:A659,[1]Sheet3!T207:T806) -> 22364.16 | P61: =_xlfn.XLOOKUP(A61,A60:A659,[1]Sheet3!U207:U806) -> 8609.23 | Q61: =_xlfn.XLOOKUP(A61,A60:A659,[1]Sheet3!V207:V806) -> 0.38495656 | R61: =_xlfn.XLOOKUP(A61,A60:A659,[1]Sheet3!W207:W806) -> 56.32 | S61: =_xlfn.XLOOKUP(A61,A60:A659,[1]Sheet3!X207:X806) -> Cash on Delivery | T61: =_xlfn.XLOOKUP(A61,A60:A659,[1]Sheet3!Z207:Z806) -> 5 | U61: =_xlfn.XLOOKUP(A61,A60:A659,[1]Sheet3!AA207:AA806) -> TRUE | V61: =_xlfn.XLOOKUP(A61,A60:A659,[1]Sheet3!AC207:AC806) -> Returned | W61: =_xlfn.XLOOKUP(A61,A60:A659,[1]Sheet3!AE207:AE806) -> 2
A62: ORD-00404 | B62: =_xlfn.XLOOKUP(A62,A61:A660,[1]Sheet3!C560:C1159) -> 44004 | C62: =_xlfn.XLOOKUP(A62,A61:A660,[1]Sheet3!D560:D1159) -> CUST02130 | D62: =_xlfn.XLOOKUP(A62,A61:A660,[1]Sheet3!E560:E1159) -> Vikram Shah | E62: =_xlfn.XLOOKUP(A62,A61:A660,[1]Sheet3!G560:G1159) -> 16 | F62: =_xlfn.XLOOKUP('Retail Sales'!A561,'Retail Sales'!A560:A1159,[1]Sheet3!H560:H1159) -> Teen | G62: =_xlfn.XLOOKUP(A62,A61:A660,[1]Sheet3!J560:J1159) -> Female | H62: =_xlfn.XLOOKUP(A62,A61:A660,[1]Sheet3!K560:K1159) -> West | I62: =_xlfn.XLOOKUP(A62,A61:A660,[1]Sheet3!L560:L1159) -> Ahmedabad | J62: =_xlfn.XLOOKUP(A62,A61:A660,[1]Sheet3!M560:M1159) -> Books | K62: =_xlfn.XLOOKUP('Retail Sales'!A561,'Retail Sales'!A560:A1159,[1]Sheet3!N560:N1159) -> Textbook | L62: =_xlfn.XLOOKUP(A62,A61:A660,[1]Sheet3!P560:P1159) -> 3 | M62: =_xlfn.XLOOKUP(A62,A61:A660,[1]Sheet3!Q560:Q1159) -> 541.31 | N62: =_xlfn.XLOOKUP(A62,A61:A660,[1]Sheet3!S560:S1159) -> 0.06 | O62: =_xlfn.XLOOKUP(A62,A61:A660,[1]Sheet3!T560:T1159) -> 2139.34 | P62: =_xlfn.XLOOKUP(A62,A61:A660,[1]Sheet3!U560:U1159) -> 731.39 | Q62: =_xlfn.XLOOKUP(A62,A61:A660,[1]Sheet3!V560:V1159) -> 0.34187647 | R62: =_xlfn.XLOOKUP(A62,A61:A660,[1]Sheet3!W560:W1159) -> 56.62 | S62: =_xlfn.XLOOKUP(A62,A61:A660,[1]Sheet3!X560:X1159) -> Cash on Delivery | T62: =_xlfn.XLOOKUP(A62,A61:A660,[1]Sheet3!Z560:Z1159) -> 5 | U62: =_xlfn.XLOOKUP(A62,A61:A660,[1]Sheet3!AA560:AA1159) -> FALSE | V62: =_xlfn.XLOOKUP(A62,A61:A660,[1]Sheet3!AC560:AC1159) -> Delivered | W62: =_xlfn.XLOOKUP(A62,A61:A660,[1]Sheet3!AE560:AE1159) -> 8
A63: ORD-00409 | B63: =_xlfn.XLOOKUP(A63,A62:A661,[1]Sheet3!C126:C725) -> 44009 | C63: =_xlfn.XLOOKUP(A63,A62:A661,[1]Sheet3!D126:D725) -> CUST97162 | D63: =_xlfn.XLOOKUP(A63,A62:A661,[1]Sheet3!E126:E725) -> Sanjay Mehta | E63: =_xlfn.XLOOKUP(A63,A62:A661,[1]Sheet3!G126:G725) -> 46 | F63: =_xlfn.XLOOKUP('Retail Sales'!A127,'Retail Sales'!A126:A725,[1]Sheet3!H126:H725) -> Adult | G63: =_xlfn.XLOOKUP(A63,A62:A661,[1]Sheet3!J126:J725) -> Female | H63: =_xlfn.XLOOKUP(A63,A62:A661,[1]Sheet3!K126:K725) -> East | I63: =_xlfn.XLOOKUP(A63,A62:A661,[1]Sheet3!L126:L725) -> Bhubaneswar | J63: =_xlfn.XLOOKUP(A63,A62:A661,[1]Sheet3!M126:M725) -> Sports | K63: =_xlfn.XLOOKUP('Retail Sales'!A127,'Retail Sales'!A126:A725,[1]Sheet3!N126:N725) -> Cricket Bat | L63: =_xlfn.XLOOKUP(A63,A62:A661,[1]Sheet3!P126:P725) -> 1 | M63: =_xlfn.XLOOKUP(A63,A62:A661,[1]Sheet3!Q126:Q725) -> 4889.3 | N63: =_xlfn.XLOOKUP(A63,A62:A661,[1]Sheet3!S126:S725) -> 0.16 | O63: =_xlfn.XLOOKUP(A63,A62:A661,[1]Sheet3!T126:T725) -> 5849.95 | P63: =_xlfn.XLOOKUP(A63,A62:A661,[1]Sheet3!U126:U725) -> 1406.77 | Q63: =_xlfn.XLOOKUP(A63,A62:A661,[1]Sheet3!V126:V725) -> 0.24047556 | R63: =_xlfn.XLOOKUP(A63,A62:A661,[1]Sheet3!W126:W725) -> 63.96 | S63: =_xlfn.XLOOKUP(A63,A62:A661,[1]Sheet3!X126:X725) -> Net Banking | T63: =_xlfn.XLOOKUP(A63,A62:A661,[1]Sheet3!Z126:Z725) -> 1 | U63: =_xlfn.XLOOKUP(A63,A62:A661,[1]Sheet3!AA126:AA725) -> FALSE | V63: =_xlfn.XLOOKUP(A63,A62:A661,[1]Sheet3!AC126:AC725) -> Delivered | W63: =_xlfn.XLOOKUP(A63,A62:A661,[1]Sheet3!AE126:AE725) -> 6
A64: ORD-00412 | B64: =_xlfn.XLOOKUP(A64,A63:A662,[1]Sheet3!C30:C629) -> 44013 | C64: =_xlfn.XLOOKUP(A64,A63:A662,[1]Sheet3!D30:D629) -> CUST88814 | D64: =_xlfn.XLOOKUP(A64,A63:A662,[1]Sheet3!E30:E629) -> Rahul Kapoor | E64: =_xlfn.XLOOKUP(A64,A63:A662,[1]Sheet3!G30:G629) -> 51 | F64: =_xlfn.XLOOKUP('Retail Sales'!A31,'Retail Sales'!A30:A629,[1]Sheet3!H30:H629) -> Senior | G64: =_xlfn.XLOOKUP(A64,A63:A662,[1]Sheet3!J30:J629) -> Other | H64: =_xlfn.XLOOKUP(A64,A63:A662,[1]Sheet3!K30:K629) -> West | I64: =_xlfn.XLOOKUP(A64,A63:A662,[1]Sheet3!L30:L629) -> Ahmedabad | J64: =_xlfn.XLOOKUP(A64,A63:A662,[1]Sheet3!M30:M629) -> Books | K64: =_xlfn.XLOOKUP('Retail Sales'!A31,'Retail Sales'!A30:A629,[1]Sheet3!N30:N629) -> Comic Book | L64: =_xlfn.XLOOKUP(A64,A63:A662,[1]Sheet3!P30:P629) -> 8 | M64: =_xlfn.XLOOKUP(A64,A63:A662,[1]Sheet3!Q30:Q629) -> 635.66 | N64: =_xlfn.XLOOKUP(A64,A63:A662,[1]Sheet3!S30:S629) -> 0.34 | O64: =_xlfn.XLOOKUP(A64,A63:A662,[1]Sheet3!T30:T629) -> 3704.84 | P64: =_xlfn.XLOOKUP(A64,A63:A662,[1]Sheet3!U30:U629) -> 1269.07 | Q64: =_xlfn.XLOOKUP(A64,A63:A662,[1]Sheet3!V30:V629) -> 0.34254381 | R64: =_xlfn.XLOOKUP(A64,A63:A662,[1]Sheet3!W30:W629) -> 67.01 | S64: =_xlfn.XLOOKUP(A64,A63:A662,[1]Sheet3!X30:X629) -> Cash on Delivery | T64: =_xlfn.XLOOKUP(A64,A63:A662,[1]Sheet3!Z30:Z629) -> 1 | U64: =_xlfn.XLOOKUP(A64,A63:A662,[1]Sheet3!AA30:AA629) -> FALSE | V64: =_xlfn.XLOOKUP(A64,A63:A662,[1]Sheet3!AC30:AC629) -> Delivered | W64: =_xlfn.XLOOKUP(A64,A63:A662,[1]Sheet3!AE30:AE629) -> 3
A65: ORD-00415 | B65: =_xlfn.XLOOKUP(A65,A64:A663,[1]Sheet3!C43:C642) -> 44013 | C65: =_xlfn.XLOOKUP(A65,A64:A663,[1]Sheet3!D43:D642) -> CUST39948 | D65: =_xlfn.XLOOKUP(A65,A64:A663,[1]Sheet3!E43:E642) -> Nikhil Kapoor | E65: =_xlfn.XLOOKUP(A65,A64:A663,[1]Sheet3!G43:G642) -> 34.294221 | F65: =_xlfn.XLOOKUP('Retail Sales'!A44,'Retail Sales'!A43:A642,[1]Sheet3!H43:H642) -> Young Adult | G65: =_xlfn.XLOOKUP(A65,A64:A663,[1]Sheet3!J43:J642) -> Female | H65: =_xlfn.XLOOKUP(A65,A64:A663,[1]Sheet3!K43:K642) -> North | I65: =_xlfn.XLOOKUP(A65,A64:A663,[1]Sheet3!L43:L642) -> Chandigarh | J65: =_xlfn.XLOOKUP(A65,A64:A663,[1]Sheet3!M43:M642) -> Furniture | K65: =_xlfn.XLOOKUP('Retail Sales'!A44,'Retail Sales'!A43:A642,[1]Sheet3!N43:N642) -> Desk | L65: =_xlfn.XLOOKUP(A65,A64:A663,[1]Sheet3!P43:P642) -> 2 | M65: =_xlfn.XLOOKUP(A65,A64:A663,[1]Sheet3!Q43:Q642) -> 33115.91 | N65: =_xlfn.XLOOKUP(A65,A64:A663,[1]Sheet3!S43:S642) -> 0.28 | O65: =_xlfn.XLOOKUP(A65,A64:A663,[1]Sheet3!T43:T642) -> 53911.88 | P65: =_xlfn.XLOOKUP(A65,A64:A663,[1]Sheet3!U43:U642) -> 13232.77 | Q65: =_xlfn.XLOOKUP(A65,A64:A663,[1]Sheet3!V43:V642) -> 0.24545184 | R65: =_xlfn.XLOOKUP(A65,A64:A663,[1]Sheet3!W43:W642) -> 39.83 | S65: =_xlfn.XLOOKUP(A65,A64:A663,[1]Sheet3!X43:X642) -> EMI | T65: =_xlfn.XLOOKUP(A65,A64:A663,[1]Sheet3!Z43:Z642) -> 5 | U65: =_xlfn.XLOOKUP(A65,A64:A663,[1]Sheet3!AA43:AA642) -> FALSE | V65: =_xlfn.XLOOKUP(A65,A64:A663,[1]Sheet3!AC43:AC642) -> Delivered | W65: =_xlfn.XLOOKUP(A65,A64:A663,[1]Sheet3!AE43:AE642) -> 1
A66: ORD-00422 | B66: =_xlfn.XLOOKUP(A66,A65:A664,[1]Sheet3!C143:C742) -> 44018 | C66: =_xlfn.XLOOKUP(A66,A65:A664,[1]Sheet3!D143:D742) -> CUST44523 | D66: =_xlfn.XLOOKUP(A66,A65:A664,[1]Sheet3!E143:E742) -> Priya Sharma | E66: =_xlfn.XLOOKUP(A66,A65:A664,[1]Sheet3!G143:G742) -> 35 | F66: =_xlfn.XLOOKUP('Retail Sales'!A144,'Retail Sales'!A143:A742,[1]Sheet3!H143:H742) -> Young Adult | G66: =_xlfn.XLOOKUP(A66,A65:A664,[1]Sheet3!J143:J742) -> Other | H66: =_xlfn.XLOOKUP(A66,A65:A664,[1]Sheet3!K143:K742) -> South | I66: =_xlfn.XLOOKUP(A66,A65:A664,[1]Sheet3!L143:L742) -> Bangalore | J66: =_xlfn.XLOOKUP(A66,A65:A664,[1]Sheet3!M143:M742) -> Clothing | K66: =_xlfn.XLOOKUP('Retail Sales'!A144,'Retail Sales'!A143:A742,[1]Sheet3!N143:N742) -> Jacket | L66: =_xlfn.XLOOKUP(A66,A65:A664,[1]Sheet3!P143:P742) -> 2 | M66: =_xlfn.XLOOKUP(A66,A65:A664,[1]Sheet3!Q143:Q742) -> 539.35 | N66: =_xlfn.XLOOKUP(A66,A65:A664,[1]Sheet3!S143:S742) -> 0.23 | O66: =_xlfn.XLOOKUP(A66,A65:A664,[1]Sheet3!T143:T742) -> 1124.22 | P66: =_xlfn.XLOOKUP(A66,A65:A664,[1]Sheet3!U143:U742) -> 289.25 | Q66: =_xlfn.XLOOKUP(A66,A65:A664,[1]Sheet3!V143:V742) -> 0.2572895 | R66: =_xlfn.XLOOKUP(A66,A65:A664,[1]Sheet3!W143:W742) -> 64.96 | S66: =_xlfn.XLOOKUP(A66,A65:A664,[1]Sheet3!X143:X742) -> Cash on Delivery | T66: =_xlfn.XLOOKUP(A66,A65:A664,[1]Sheet3!Z143:Z742) -> 5 | U66: =_xlfn.XLOOKUP(A66,A65:A664,[1]Sheet3!AA143:AA742) -> FALSE | V66: =_xlfn.XLOOKUP(A66,A65:A664,[1]Sheet3!AC143:AC742) -> Delivered | W66: =_xlfn.XLOOKUP(A66,A65:A664,[1]Sheet3!AE143:AE742) -> 8
A67: ORD-00428 | B67: =_xlfn.XLOOKUP(A67,A66:A665,[1]Sheet3!C579:C1178) -> 44020 | C67: =_xlfn.XLOOKUP(A67,A66:A665,[1]Sheet3!D579:D1178) -> CUST48382 | D67: =_xlfn.XLOOKUP(A67,A66:A665,[1]Sheet3!E579:E1178) -> Priya Kumar | E67: =_xlfn.XLOOKUP(A67,A66:A665,[1]Sheet3!G579:G1178) -> 47 | F67: =_xlfn.XLOOKUP('Retail Sales'!A580,'Retail Sales'!A579:A1178,[1]Sheet3!H579:H1178) -> Adult | G67: =_xlfn.XLOOKUP(A67,A66:A665,[1]Sheet3!J579:J1178) -> Female | H67: =_xlfn.XLOOKUP(A67,A66:A665,[1]Sheet3!K579:K1178) -> Central | I67: =_xlfn.XLOOKUP(A67,A66:A665,[1]Sheet3!L579:L1178) -> Nagpur | J67: =_xlfn.XLOOKUP(A67,A66:A665,[1]Sheet3!M579:M1178) -> Groceries | K67: =_xlfn.XLOOKUP('Retail Sales'!A580,'Retail Sales'!A579:A1178,[1]Sheet3!N579:N1178) -> Flour | L67: =_xlfn.XLOOKUP(A67,A66:A665,[1]Sheet3!P579:P1178) -> 4 | M67: =_xlfn.XLOOKUP(A67,A66:A665,[1]Sheet3!Q579:Q1178) -> 443.03 | N67: =_xlfn.XLOOKUP(A67,A66:A665,[1]Sheet3!S579:S1178) -> 0.32 | O67: =_xlfn.XLOOKUP(A67,A66:A665,[1]Sheet3!T579:T1178) -> 1593.89 | P67: =_xlfn.XLOOKUP(A67,A66:A665,[1]Sheet3!U579:U1178) -> 115.6 | Q67: =_xlfn.XLOOKUP(A67,A66:A665,[1]Sheet3!V579:V1178) -> 0.072526962 | R67: =_xlfn.XLOOKUP(A67,A66:A665,[1]Sheet3!W579:W1178) -> 71.82 | S67: =_xlfn.XLOOKUP(A67,A66:A665,[1]Sheet3!X579:X1178) -> Debit Card | T67: =_xlfn.XLOOKUP(A67,A66:A665,[1]Sheet3!Z579:Z1178) -> 4 | U67: =_xlfn.XLOOKUP(A67,A66:A665,[1]Sheet3!AA579:AA1178) -> FALSE | V67: =_xlfn.XLOOKUP(A67,A66:A665,[1]Sheet3!AC579:AC1178) -> Shipped | W67: =_xlfn.XLOOKUP(A67,A66:A665,[1]Sheet3!AE579:AE1178) -> 2
A68: ORD-00436 | B68: =_xlfn.XLOOKUP(A68,A67:A666,[1]Sheet3!C255:C854) -> 44022 | C68: =_xlfn.XLOOKUP(A68,A67:A666,[1]Sheet3!D255:D854) -> CUST18887 | D68: =_xlfn.XLOOKUP(A68,A67:A666,[1]Sheet3!E255:E854) -> Pooja Kapoor | E68: =_xlfn.XLOOKUP(A68,A67:A666,[1]Sheet3!G255:G854) -> 43 | F68: =_xlfn.XLOOKUP('Retail Sales'!A256,'Retail Sales'!A255:A854,[1]Sheet3!H255:H854) -> Adult | G68: =_xlfn.XLOOKUP(A68,A67:A666,[1]Sheet3!J255:J854) -> Female | H68: =_xlfn.XLOOKUP(A68,A67:A666,[1]Sheet3!K255:K854) -> West | I68: =_xlfn.XLOOKUP(A68,A67:A666,[1]Sheet3!L255:L854) -> Pune | J68: =_xlfn.XLOOKUP(A68,A67:A666,[1]Sheet3!M255:M854) -> Books | K68: =_xlfn.XLOOKUP('Retail Sales'!A256,'Retail Sales'!A255:A854,[1]Sheet3!N255:N854) -> Biography | L68: =_xlfn.XLOOKUP(A68,A67:A666,[1]Sheet3!P255:P854) -> 2 | M68: =_xlfn.XLOOKUP(A68,A67:A666,[1]Sheet3!Q255:Q854) -> 449.62 | N68: =_xlfn.XLOOKUP(A68,A67:A666,[1]Sheet3!S255:S854) -> 0.4 | O68: =_xlfn.XLOOKUP(A68,A67:A666,[1]Sheet3!T255:T854) -> 661.09 | P68: =_xlfn.XLOOKUP(A68,A67:A666,[1]Sheet3!U255:U854) -> 247.72 | Q68: =_xlfn.XLOOKUP(A68,A67:A666,[1]Sheet3!V255:V854) -> 0.37471449 | R68: =_xlfn.XLOOKUP(A68,A67:A666,[1]Sheet3!W255:W854) -> 68.85 | S68: =_xlfn.XLOOKUP(A68,A67:A666,[1]Sheet3!X255:X854) -> Debit Card | T68: =_xlfn.XLOOKUP(A68,A67:A666,[1]Sheet3!Z255:Z854) -> 1 | U68: =_xlfn.XLOOKUP(A68,A67:A666,[1]Sheet3!AA255:AA854) -> FALSE | V68: =_xlfn.XLOOKUP(A68,A67:A666,[1]Sheet3!AC255:AC854) -> Delivered | W68: =_xlfn.XLOOKUP(A68,A67:A666,[1]Sheet3!AE255:AE854) -> 6
A69: ORD-00439 | B69: =_xlfn.XLOOKUP(A69,A68:A667,[1]Sheet3!C346:C945) -> 44024 | C69: =_xlfn.XLOOKUP(A69,A68:A667,[1]Sheet3!D346:D945) -> CUST45071 | D69: =_xlfn.XLOOKUP(A69,A68:A667,[1]Sheet3!E346:E945) -> Aditya Nair | E69: =_xlfn.XLOOKUP(A69,A68:A667,[1]Sheet3!G346:G945) -> 22 | F69: =_xlfn.XLOOKUP('Retail Sales'!A347,'Retail Sales'!A346:A945,[1]Sheet3!H346:H945) -> Young Adult | G69: =_xlfn.XLOOKUP(A69,A68:A667,[1]Sheet3!J346:J945) -> Male | H69: =_xlfn.XLOOKUP(A69,A68:A667,[1]Sheet3!K346:K945) -> West | I69: =_xlfn.XLOOKUP(A69,A68:A667,[1]Sheet3!L346:L945) -> Ahmedabad | J69: =_xlfn.XLOOKUP(A69,A68:A667,[1]Sheet3!M346:M945) -> Groceries | K69: =_xlfn.XLOOKUP('Retail Sales'!A347,'Retail Sales'!A346:A945,[1]Sheet3!N346:N945) -> Cooking Oil | L69: =_xlfn.XLOOKUP(A69,A68:A667,[1]Sheet3!P346:P945) -> 2 | M69: =_xlfn.XLOOKUP(A69,A68:A667,[1]Sheet3!Q346:Q945) -> 379.2 | N69: =_xlfn.XLOOKUP(A69,A68:A667,[1]Sheet3!S346:S945) -> 0.2 | O69: =_xlfn.XLOOKUP(A69,A68:A667,[1]Sheet3!T346:T945) -> 658.39 | P69: =_xlfn.XLOOKUP(A69,A68:A667,[1]Sheet3!U346:U945) -> 27.25 | Q69: =_xlfn.XLOOKUP(A69,A68:A667,[1]Sheet3!V346:V945) -> 0.041388842 | R69: =_xlfn.XLOOKUP(A69,A68:A667,[1]Sheet3!W346:W945) -> 67.65 | S69: =_xlfn.XLOOKUP(A69,A68:A667,[1]Sheet3!X346:X945) -> UPI | T69: =_xlfn.XLOOKUP(A69,A68:A667,[1]Sheet3!Z346:Z945) -> 1 | U69: =_xlfn.XLOOKUP(A69,A68:A667,[1]Sheet3!AA346:AA945) -> FALSE | V69: =_xlfn.XLOOKUP(A69,A68:A667,[1]Sheet3!AC346:AC945) -> Delivered | W69: =_xlfn.XLOOKUP(A69,A68:A667,[1]Sheet3!AE346:AE945) -> 7
A70: ORD-00452 | B70: =_xlfn.XLOOKUP(A70,A69:A668,[1]Sheet3!C553:C1152) -> 44030 | C70: =_xlfn.XLOOKUP(A70,A69:A668,[1]Sheet3!D553:D1152) -> CUST52335 | D70: =_xlfn.XLOOKUP(A70,A69:A668,[1]Sheet3!E553:E1152) -> Nisha Patel | E70: =_xlfn.XLOOKUP(A70,A69:A668,[1]Sheet3!G553:G1152) -> 52 | F70: =_xlfn.XLOOKUP('Retail Sales'!A554,'Retail Sales'!A553:A1152,[1]Sheet3!H553:H1152) -> Senior | G70: =_xlfn.XLOOKUP(A70,A69:A668,[1]Sheet3!J553:J1152) -> Male | H70: =_xlfn.XLOOKUP(A70,A69:A668,[1]Sheet3!K553:K1152) -> West | I70: =_xlfn.XLOOKUP(A70,A69:A668,[1]Sheet3!L553:L1152) -> Ahmedabad | J70: =_xlfn.XLOOKUP(A70,A69:A668,[1]Sheet3!M553:M1152) -> Books | K70: =_xlfn.XLOOKUP('Retail Sales'!A554,'Retail Sales'!A553:A1152,[1]Sheet3!N553:N1152) -> Textbook | L70: =_xlfn.XLOOKUP(A70,A69:A668,[1]Sheet3!P553:P1152) -> 4 | M70: =_xlfn.XLOOKUP(A70,A69:A668,[1]Sheet3!Q553:Q1152) -> 565.17 | N70: =_xlfn.XLOOKUP(A70,A69:A668,[1]Sheet3!S553:S1152) -> 0.05 | O70: =_xlfn.XLOOKUP(A70,A69:A668,[1]Sheet3!T553:T1152) -> 2606.02 | P70: =_xlfn.XLOOKUP(A70,A69:A668,[1]Sheet3!U553:U1152) -> 1227.07 | Q70: =_xlfn.XLOOKUP(A70,A69:A668,[1]Sheet3!V553:V1152) -> 0.47085978 | R70: =_xlfn.XLOOKUP(A70,A69:A668,[1]Sheet3!W553:W1152) -> 78.29 | S70: =_xlfn.XLOOKUP(A70,A69:A668,[1]Sheet3!X553:X1152) -> Credit Card | T70: =_xlfn.XLOOKUP(A70,A69:A668,[1]Sheet3!Z553:Z1152) -> 4 | U70: =_xlfn.XLOOKUP(A70,A69:A668,[1]Sheet3!AA553:AA1152) -> FALSE | V70: =_xlfn.XLOOKUP(A70,A69:A668,[1]Sheet3!AC553:AC1152) -> Delivered | W70: =_xlfn.XLOOKUP(A70,A69:A668,[1]Sheet3!AE553:AE1152) -> 5
A71: ORD-00458 | B71: =_xlfn.XLOOKUP(A71,A70:A669,[1]Sheet3!C227:C826) -> 44032 | C71: =_xlfn.XLOOKUP(A71,A70:A669,[1]Sheet3!D227:D826) -> CUST53954 | D71: =_xlfn.XLOOKUP(A71,A70:A669,[1]Sheet3!E227:E826) -> Amit Kapoor | E71: =_xlfn.XLOOKUP(A71,A70:A669,[1]Sheet3!G227:G826) -> 40 | F71: =_xlfn.XLOOKUP('Retail Sales'!A228,'Retail Sales'!A227:A826,[1]Sheet3!H227:H826) -> Adult | G71: =_xlfn.XLOOKUP(A71,A70:A669,[1]Sheet3!J227:J826) -> Other | H71: =_xlfn.XLOOKUP(A71,A70:A669,[1]Sheet3!K227:K826) -> Central | I71: =_xlfn.XLOOKUP(A71,A70:A669,[1]Sheet3!L227:L826) -> Nagpur | J71: =_xlfn.XLOOKUP(A71,A70:A669,[1]Sheet3!M227:M826) -> Books | K71: =_xlfn.XLOOKUP('Retail Sales'!A228,'Retail Sales'!A227:A826,[1]Sheet3!N227:N826) -> Cook Book | L71: =_xlfn.XLOOKUP(A71,A70:A669,[1]Sheet3!P227:P826) -> 4 | M71: =_xlfn.XLOOKUP(A71,A70:A669,[1]Sheet3!Q227:Q826) -> 313.79 | N71: =_xlfn.XLOOKUP(A71,A70:A669,[1]Sheet3!S227:S826) -> 0.37 | O71: =_xlfn.XLOOKUP(A71,A70:A669,[1]Sheet3!T227:T826) -> 885.78 | P71: =_xlfn.XLOOKUP(A71,A70:A669,[1]Sheet3!U227:U826) -> 369.77 | Q71: =_xlfn.XLOOKUP(A71,A70:A669,[1]Sheet3!V227:V826) -> 0.41745129 | R71: =_xlfn.XLOOKUP(A71,A70:A669,[1]Sheet3!W227:W826) -> 43.26 | S71: =_xlfn.XLOOKUP(A71,A70:A669,[1]Sheet3!X227:X826) -> Net Banking | T71: =_xlfn.XLOOKUP(A71,A70:A669,[1]Sheet3!Z227:Z826) -> 2 | U71: =_xlfn.XLOOKUP(A71,A70:A669,[1]Sheet3!AA227:AA826) -> FALSE | V71: =_xlfn.XLOOKUP(A71,A70:A669,[1]Sheet3!AC227:AC826) -> Delivered | W71: =_xlfn.XLOOKUP(A71,A70:A669,[1]Sheet3!AE227:AE826) -> 5
A72: ORD-00465 | B72: =_xlfn.XLOOKUP(A72,A71:A670,[1]Sheet3!C9:C608) -> 44036 | C72: =_xlfn.XLOOKUP(A72,A71:A670,[1]Sheet3!D9:D608) -> CUST23609 | D72: =_xlfn.XLOOKUP(A72,A71:A670,[1]Sheet3!E9:E608) -> Aditya Patel | E72: =_xlfn.XLOOKUP(A72,A71:A670,[1]Sheet3!G9:G608) -> 44 | F72: =_xlfn.XLOOKUP('Retail Sales'!A10,'Retail Sales'!A9:A608,[1]Sheet3!H9:H608) -> Adult | G72: =_xlfn.XLOOKUP(A72,A71:A670,[1]Sheet3!J9:J608) -> Female | H72: =_xlfn.XLOOKUP(A72,A71:A670,[1]Sheet3!K9:K608) -> East | I72: =_xlfn.XLOOKUP(A72,A71:A670,[1]Sheet3!L9:L608) -> Patna | J72: =_xlfn.XLOOKUP(A72,A71:A670,[1]Sheet3!M9:M608) -> Books | K72: =_xlfn.XLOOKUP('Retail Sales'!A10,'Retail Sales'!A9:A608,[1]Sheet3!N9:N608) -> Self-Help Book | L72: =_xlfn.XLOOKUP(A72,A71:A670,[1]Sheet3!P9:P608) -> 8 | M72: =_xlfn.XLOOKUP(A72,A71:A670,[1]Sheet3!Q9:Q608) -> 495.77 | N72: =_xlfn.XLOOKUP(A72,A71:A670,[1]Sheet3!S9:S608) -> 0.37 | O72: =_xlfn.XLOOKUP(A72,A71:A670,[1]Sheet3!T9:T608) -> 2828.82 | P72: =_xlfn.XLOOKUP(A72,A71:A670,[1]Sheet3!U9:U608) -> 1338.88 | Q72: =_xlfn.XLOOKUP(A72,A71:A670,[1]Sheet3!V9:V608) -> 0.47329982 | R72: =_xlfn.XLOOKUP(A72,A71:A670,[1]Sheet3!W9:W608) -> 84.5 | S72: =_xlfn.XLOOKUP(A72,A71:A670,[1]Sheet3!X9:X608) -> Debit Card | T72: =_xlfn.XLOOKUP(A72,A71:A670,[1]Sheet3!Z9:Z608) -> 1 | U72: =_xlfn.XLOOKUP(A72,A71:A670,[1]Sheet3!AA9:AA608) -> FALSE | V72: =_xlfn.XLOOKUP(A72,A71:A670,[1]Sheet3!AC9:AC608) -> Cancelled | W72: =_xlfn.XLOOKUP(A72,A71:A670,[1]Sheet3!AE9:AE608) -> 10
A73: ORD-00485 | B73: =_xlfn.XLOOKUP(A73,A72:A671,[1]Sheet3!C338:C937) -> 44045 | C73: =_xlfn.XLOOKUP(A73,A72:A671,[1]Sheet3!D338:D937) -> CUST67381 | D73: =_xlfn.XLOOKUP(A73,A72:A671,[1]Sheet3!E338:E937) -> Amit Mehta | E73: =_xlfn.XLOOKUP(A73,A72:A671,[1]Sheet3!G338:G937) -> 46 | F73: =_xlfn.XLOOKUP('Retail Sales'!A339,'Retail Sales'!A338:A937,[1]Sheet3!H338:H937) -> Adult | G73: =_xlfn.XLOOKUP(A73,A72:A671,[1]Sheet3!J338:J937) -> Other | H73: =_xlfn.XLOOKUP(A73,A72:A671,[1]Sheet3!K338:K937) -> East | I73: =_xlfn.XLOOKUP(A73,A72:A671,[1]Sheet3!L338:L937) -> Kolkata | J73: =_xlfn.XLOOKUP(A73,A72:A671,[1]Sheet3!M338:M937) -> Electronics | K73: =_xlfn.XLOOKUP('Retail Sales'!A339,'Retail Sales'!A338:A937,[1]Sheet3!N338:N937) -> Laptop | L73: =_xlfn.XLOOKUP(A73,A72:A671,[1]Sheet3!P338:P937) -> 6 | M73: =_xlfn.XLOOKUP(A73,A72:A671,[1]Sheet3!Q338:Q937) -> 76471.27 | N73: =_xlfn.XLOOKUP(A73,A72:A671,[1]Sheet3!S338:S937) -> 0.19793403 | O73: =_xlfn.XLOOKUP(A73,A72:A671,[1]Sheet3!T338:T937) -> 542833.32 | P73: =_xlfn.XLOOKUP(A73,A72:A671,[1]Sheet3!U338:U937) -> 79755.17 | Q73: =_xlfn.XLOOKUP(A73,A72:A671,[1]Sheet3!V338:V937) -> 0.14692387 | R73: =_xlfn.XLOOKUP(A73,A72:A671,[1]Sheet3!W338:W937) -> 71.89 | S73: =_xlfn.XLOOKUP(A73,A72:A671,[1]Sheet3!X338:X937) -> Cash on Delivery | T73: =_xlfn.XLOOKUP(A73,A72:A671,[1]Sheet3!Z338:Z937) -> 5 | U73: =_xlfn.XLOOKUP(A73,A72:A671,[1]Sheet3!AA338:AA937) -> FALSE | V73: =_xlfn.XLOOKUP(A73,A72:A671,[1]Sheet3!AC338:AC937) -> Delivered | W73: =_xlfn.XLOOKUP(A73,A72:A671,[1]Sheet3!AE338:AE937) -> 5
A74: ORD-00489 | B74: =_xlfn.XLOOKUP(A74,A73:A672,[1]Sheet3!C55:C654) -> 44046 | C74: =_xlfn.XLOOKUP(A74,A73:A672,[1]Sheet3!D55:D654) -> CUST85726 | D74: =_xlfn.XLOOKUP(A74,A73:A672,[1]Sheet3!E55:E654) -> Ritu Verma | E74: =_xlfn.XLOOKUP(A74,A73:A672,[1]Sheet3!G55:G654) -> 34 | F74: =_xlfn.XLOOKUP('Retail Sales'!A56,'Retail Sales'!A55:A654,[1]Sheet3!H55:H654) -> Young Adult | G74: =_xlfn.XLOOKUP(A74,A73:A672,[1]Sheet3!J55:J654) -> Male | H74: =_xlfn.XLOOKUP(A74,A73:A672,[1]Sheet3!K55:K654) -> Central | I74: =_xlfn.XLOOKUP(A74,A73:A672,[1]Sheet3!L55:L654) -> Raipur | J74: =_xlfn.XLOOKUP(A74,A73:A672,[1]Sheet3!M55:M654) -> Electronics | K74: =_xlfn.XLOOKUP('Retail Sales'!A56,'Retail Sales'!A55:A654,[1]Sheet3!N55:N654) -> Tablet | L74: =_xlfn.XLOOKUP(A74,A73:A672,[1]Sheet3!P55:P654) -> 2 | M74: =_xlfn.XLOOKUP(A74,A73:A672,[1]Sheet3!Q55:Q654) -> 52363.15 | N74: =_xlfn.XLOOKUP(A74,A73:A672,[1]Sheet3!S55:S654) -> 0.25 | O74: =_xlfn.XLOOKUP(A74,A73:A672,[1]Sheet3!T55:T654) -> 89225.91 | P74: =_xlfn.XLOOKUP(A74,A73:A672,[1]Sheet3!U55:U654) -> 14474.33 | Q74: =_xlfn.XLOOKUP(A74,A73:A672,[1]Sheet3!V55:V654) -> 0.16222115 | R74: =_xlfn.XLOOKUP(A74,A73:A672,[1]Sheet3!W55:W654) -> 45.26 | S74: =_xlfn.XLOOKUP(A74,A73:A672,[1]Sheet3!X55:X654) -> Net Banking | T74: =_xlfn.XLOOKUP(A74,A73:A672,[1]Sheet3!Z55:Z654) -> 2 | U74: =_xlfn.XLOOKUP(A74,A73:A672,[1]Sheet3!AA55:AA654) -> FALSE | V74: =_xlfn.XLOOKUP(A74,A73:A672,[1]Sheet3!AC55:AC654) -> Pending | W74: =_xlfn.XLOOKUP(A74,A73:A672,[1]Sheet3!AE55:AE654) -> 9
A75: ORD-00490 | B75: =_xlfn.XLOOKUP(A75,A74:A673,[1]Sheet3!C168:C767) -> 44047 | C75: =_xlfn.XLOOKUP(A75,A74:A673,[1]Sheet3!D168:D767) -> CUST00642 | D75: =_xlfn.XLOOKUP(A75,A74:A673,[1]Sheet3!E168:E767) -> Kavya Das | E75: =_xlfn.XLOOKUP(A75,A74:A673,[1]Sheet3!G168:G767) -> 40 | F75: =_xlfn.XLOOKUP('Retail Sales'!A169,'Retail Sales'!A168:A767,[1]Sheet3!H168:H767) -> Adult | G75: =_xlfn.XLOOKUP(A75,A74:A673,[1]Sheet3!J168:J767) -> Male | H75: =_xlfn.XLOOKUP(A75,A74:A673,[1]Sheet3!K168:K767) -> South | I75: =_xlfn.XLOOKUP(A75,A74:A673,[1]Sheet3!L168:L767) -> Chennai | J75: =_xlfn.XLOOKUP(A75,A74:A673,[1]Sheet3!M168:M767) -> Furniture | K75: =_xlfn.XLOOKUP('Retail Sales'!A169,'Retail Sales'!A168:A767,[1]Sheet3!N168:N767) -> Wardrobe | L75: =_xlfn.XLOOKUP(A75,A74:A673,[1]Sheet3!P168:P767) -> 5 | M75: =_xlfn.XLOOKUP(A75,A74:A673,[1]Sheet3!Q168:Q767) -> 12250.19 | N75: =_xlfn.XLOOKUP(A75,A74:A673,[1]Sheet3!S168:S767) -> 0.32 | O75: =_xlfn.XLOOKUP(A75,A74:A673,[1]Sheet3!T168:T767) -> 45443.23 | P75: =_xlfn.XLOOKUP(A75,A74:A673,[1]Sheet3!U168:U767) -> 11573.16 | Q75: =_xlfn.XLOOKUP(A75,A74:A673,[1]Sheet3!V168:V767) -> 0.25467292 | R75: =_xlfn.XLOOKUP(A75,A74:A673,[1]Sheet3!W168:W767) -> 71.75 | S75: =_xlfn.XLOOKUP(A75,A74:A673,[1]Sheet3!X168:X767) -> EMI | T75: =_xlfn.XLOOKUP(A75,A74:A673,[1]Sheet3!Z168:Z767) -> 3 | U75: =_xlfn.XLOOKUP(A75,A74:A673,[1]Sheet3!AA168:AA767) -> FALSE | V75: =_xlfn.XLOOKUP(A75,A74:A673,[1]Sheet3!AC168:AC767) -> Delivered | W75: =_xlfn.XLOOKUP(A75,A74:A673,[1]Sheet3!AE168:AE767) -> 6
A76: ORD-00495 | B76: =_xlfn.XLOOKUP(A76,A75:A674,[1]Sheet3!C491:C1090) -> 44048 | C76: =_xlfn.XLOOKUP(A76,A75:A674,[1]Sheet3!D491:D1090) -> CUST95892 | D76: =_xlfn.XLOOKUP(A76,A75:A674,[1]Sheet3!E491:E1090) -> Vikram Gupta | E76: =_xlfn.XLOOKUP(A76,A75:A674,[1]Sheet3!G491:G1090) -> 40 | F76: =_xlfn.XLOOKUP('Retail Sales'!A492,'Retail Sales'!A491:A1090,[1]Sheet3!H491:H1090) -> Adult | G76: =_xlfn.XLOOKUP(A76,A75:A674,[1]Sheet3!J491:J1090) -> Other | H76: =_xlfn.XLOOKUP(A76,A75:A674,[1]Sheet3!K491:K1090) -> East | I76: =_xlfn.XLOOKUP(A76,A75:A674,[1]Sheet3!L491:L1090) -> Guwahati | J76: =_xlfn.XLOOKUP(A76,A75:A674,[1]Sheet3!M491:M1090) -> Groceries | K76: =_xlfn.XLOOKUP('Retail Sales'!A492,'Retail Sales'!A491:A1090,[1]Sheet3!N491:N1090) -> Rice (5kg) | L76: =_xlfn.XLOOKUP(A76,A75:A674,[1]Sheet3!P491:P1090) -> 4 | M76: =_xlfn.XLOOKUP(A76,A75:A674,[1]Sheet3!Q491:Q1090) -> 57.97 | N76: =_xlfn.XLOOKUP(A76,A75:A674,[1]Sheet3!S491:S1090) -> 0.1 | O76: =_xlfn.XLOOKUP(A76,A75:A674,[1]Sheet3!T491:T1090) -> 258.54 | P76: =_xlfn.XLOOKUP(A76,A75:A674,[1]Sheet3!U491:U1090) -> 16.67 | Q76: =_xlfn.XLOOKUP(A76,A75:A674,[1]Sheet3!V491:V1090) -> 0.06447745 | R76: =_xlfn.XLOOKUP(A76,A75:A674,[1]Sheet3!W491:W1090) -> 74.15 | S76: =_xlfn.XLOOKUP(A76,A75:A674,[1]Sheet3!X491:X1090) -> Net Banking | T76: =_xlfn.XLOOKUP(A76,A75:A674,[1]Sheet3!Z491:Z1090) -> 3 | U76: =_xlfn.XLOOKUP(A76,A75:A674,[1]Sheet3!AA491:AA1090) -> FALSE | V76: =_xlfn.XLOOKUP(A76,A75:A674,[1]Sheet3!AC491:AC1090) -> Delivered | W76: =_xlfn.XLOOKUP(A76,A75:A674,[1]Sheet3!AE491:AE1090) -> 9
A77: ORD-00522 | B77: =_xlfn.XLOOKUP(A77,A76:A675,[1]Sheet3!C440:C1039) -> 44062 | C77: =_xlfn.XLOOKUP(A77,A76:A675,[1]Sheet3!D440:D1039) -> CUST28496 | D77: =_xlfn.XLOOKUP(A77,A76:A675,[1]Sheet3!E440:E1039) -> Ritu Gupta | E77: =_xlfn.XLOOKUP(A77,A76:A675,[1]Sheet3!G440:G1039) -> 49 | F77: =_xlfn.XLOOKUP('Retail Sales'!A441,'Retail Sales'!A440:A1039,[1]Sheet3!H440:H1039) -> Adult | G77: =_xlfn.XLOOKUP(A77,A76:A675,[1]Sheet3!J440:J1039) -> Female | H77: =_xlfn.XLOOKUP(A77,A76:A675,[1]Sheet3!K440:K1039) -> South | I77: =_xlfn.XLOOKUP(A77,A76:A675,[1]Sheet3!L440:L1039) -> Hyderabad | J77: =_xlfn.XLOOKUP(A77,A76:A675,[1]Sheet3!M440:M1039) -> Furniture | K77: =_xlfn.XLOOKUP('Retail Sales'!A441,'Retail Sales'!A440:A1039,[1]Sheet3!N440:N1039) -> Desk | L77: =_xlfn.XLOOKUP(A77,A76:A675,[1]Sheet3!P440:P1039) -> 3 | M77: =_xlfn.XLOOKUP(A77,A76:A675,[1]Sheet3!Q440:Q1039) -> 28093.41 | N77: =_xlfn.XLOOKUP(A77,A76:A675,[1]Sheet3!S440:S1039) -> 0.11 | O77: =_xlfn.XLOOKUP(A77,A76:A675,[1]Sheet3!T440:T1039) -> 80865.4 | P77: =_xlfn.XLOOKUP(A77,A76:A675,[1]Sheet3!U440:U1039) -> 14166.32 | Q77: =_xlfn.XLOOKUP(A77,A76:A675,[1]Sheet3!V440:V1039) -> 0.17518395 | R77: =_xlfn.XLOOKUP(A77,A76:A675,[1]Sheet3!W440:W1039) -> 69.8 | S77: =_xlfn.XLOOKUP(A77,A76:A675,[1]Sheet3!X440:X1039) -> Net Banking | T77: =_xlfn.XLOOKUP(A77,A76:A675,[1]Sheet3!Z440:Z1039) -> 3 | U77: =_xlfn.XLOOKUP(A77,A76:A675,[1]Sheet3!AA440:AA1039) -> TRUE | V77: =_xlfn.XLOOKUP(A77,A76:A675,[1]Sheet3!AC440:AC1039) -> Returned | W77: =_xlfn.XLOOKUP(A77,A76:A675,[1]Sheet3!AE440:AE1039) -> 3
A78: ORD-00528 | B78: =_xlfn.XLOOKUP(A78,A77:A676,[1]Sheet3!C127:C726) -> 44064 | C78: =_xlfn.XLOOKUP(A78,A77:A676,[1]Sheet3!D127:D726) -> CUST94563 | D78: =_xlfn.XLOOKUP(A78,A77:A676,[1]Sheet3!E127:E726) -> Amit Das | E78: =_xlfn.XLOOKUP(A78,A77:A676,[1]Sheet3!G127:G726) -> 56 | F78: =_xlfn.XLOOKUP('Retail Sales'!A128,'Retail Sales'!A127:A726,[1]Sheet3!H127:H726) -> Senior | G78: =_xlfn.XLOOKUP(A78,A77:A676,[1]Sheet3!J127:J726) -> Male | H78: =_xlfn.XLOOKUP(A78,A77:A676,[1]Sheet3!K127:K726) -> East | I78: =_xlfn.XLOOKUP(A78,A77:A676,[1]Sheet3!L127:L726) -> Bhubaneswar | J78: =_xlfn.XLOOKUP(A78,A77:A676,[1]Sheet3!M127:M726) -> Clothing | K78: =_xlfn.XLOOKUP('Retail Sales'!A128,'Retail Sales'!A127:A726,[1]Sheet3!N127:N726) -> Dress | L78: =_xlfn.XLOOKUP(A78,A77:A676,[1]Sheet3!P127:P726) -> 5 | M78: =_xlfn.XLOOKUP(A78,A77:A676,[1]Sheet3!Q127:Q726) -> 2614.79 | N78: =_xlfn.XLOOKUP(A78,A77:A676,[1]Sheet3!S127:S726) -> 0.12 | O78: =_xlfn.XLOOKUP(A78,A77:A676,[1]Sheet3!T127:T726) -> 12884.93 | P78: =_xlfn.XLOOKUP(A78,A77:A676,[1]Sheet3!U127:U726) -> 2796.07 | Q78: =_xlfn.XLOOKUP(A78,A77:A676,[1]Sheet3!V127:V726) -> 0.21700312 | R78: =_xlfn.XLOOKUP(A78,A77:A676,[1]Sheet3!W127:W726) -> 55.45 | S78: =_xlfn.XLOOKUP(A78,A77:A676,[1]Sheet3!X127:X726) -> Credit Card | T78: =_xlfn.XLOOKUP(A78,A77:A676,[1]Sheet3!Z127:Z726) -> 4 | U78: =_xlfn.XLOOKUP(A78,A77:A676,[1]Sheet3!AA127:AA726) -> TRUE | V78: =_xlfn.XLOOKUP(A78,A77:A676,[1]Sheet3!AC127:AC726) -> Returned | W78: =_xlfn.XLOOKUP(A78,A77:A676,[1]Sheet3!AE127:AE726) -> 9
A79: ORD-00530 | B79: =_xlfn.XLOOKUP(A79,A78:A677,[1]Sheet3!C203:C802) -> 44065 | C79: =_xlfn.XLOOKUP(A79,A78:A677,[1]Sheet3!D203:D802) -> CUST91144 | D79: =_xlfn.XLOOKUP(A79,A78:A677,[1]Sheet3!E203:E802) -> Sanjay Iyer | E79: =_xlfn.XLOOKUP(A79,A78:A677,[1]Sheet3!G203:G802) -> 29 | F79: =_xlfn.XLOOKUP('Retail Sales'!A204,'Retail Sales'!A203:A802,[1]Sheet3!H203:H802) -> Young Adult | G79: =_xlfn.XLOOKUP(A79,A78:A677,[1]Sheet3!J203:J802) -> Male | H79: =_xlfn.XLOOKUP(A79,A78:A677,[1]Sheet3!K203:K802) -> East | I79: =_xlfn.XLOOKUP(A79,A78:A677,[1]Sheet3!L203:L802) -> Patna | J79: =_xlfn.XLOOKUP(A79,A78:A677,[1]Sheet3!M203:M802) -> Beauty | K79: =_xlfn.XLOOKUP('Retail Sales'!A204,'Retail Sales'!A203:A802,[1]Sheet3!N203:N802) -> Lipstick | L79: =_xlfn.XLOOKUP(A79,A78:A677,[1]Sheet3!P203:P802) -> 1 | M79: =_xlfn.XLOOKUP(A79,A78:A677,[1]Sheet3!Q203:Q802) -> 357.7 | N79: =_xlfn.XLOOKUP(A79,A78:A677,[1]Sheet3!S203:S802) -> 0.24 | O79: =_xlfn.XLOOKUP(A79,A78:A677,[1]Sheet3!T203:T802) -> 286.61 | P79: =_xlfn.XLOOKUP(A79,A78:A677,[1]Sheet3!U203:U802) -> 137.45 | Q79: =_xlfn.XLOOKUP(A79,A78:A677,[1]Sheet3!V203:V802) -> 0.47957154 | R79: =_xlfn.XLOOKUP(A79,A78:A677,[1]Sheet3!W203:W802) -> 95.23 | S79: =_xlfn.XLOOKUP(A79,A78:A677,[1]Sheet3!X203:X802) -> Credit Card | T79: =_xlfn.XLOOKUP(A79,A78:A677,[1]Sheet3!Z203:Z802) -> 3 | U79: =_xlfn.XLOOKUP(A79,A78:A677,[1]Sheet3!AA203:AA802) -> FALSE | V79: =_xlfn.XLOOKUP(A79,A78:A677,[1]Sheet3!AC203:AC802) -> Delivered | W79: =_xlfn.XLOOKUP(A79,A78:A677,[1]Sheet3!AE203:AE802) -> 1
A80: ORD-00540 | B80: =_xlfn.XLOOKUP(A80,A79:A678,[1]Sheet3!C141:C740) -> 44069 | C80: =_xlfn.XLOOKUP(A80,A79:A678,[1]Sheet3!D141:D740) -> CUST59198 | D80: =_xlfn.XLOOKUP(A80,A79:A678,[1]Sheet3!E141:E740) -> Priya Das | E80: =_xlfn.XLOOKUP(A80,A79:A678,[1]Sheet3!G141:G740) -> 29 | F80: =_xlfn.XLOOKUP('Retail Sales'!A142,'Retail Sales'!A141:A740,[1]Sheet3!H141:H740) -> Young Adult | G80: =_xlfn.XLOOKUP(A80,A79:A678,[1]Sheet3!J141:J740) -> Other | H80: =_xlfn.XLOOKUP(A80,A79:A678,[1]Sheet3!K141:K740) -> East | I80: =_xlfn.XLOOKUP(A80,A79:A678,[1]Sheet3!L141:L740) -> Patna | J80: =_xlfn.XLOOKUP(A80,A79:A678,[1]Sheet3!M141:M740) -> Beauty | K80: =_xlfn.XLOOKUP('Retail Sales'!A142,'Retail Sales'!A141:A740,[1]Sheet3!N141:N740) -> Face Cream | L80: =_xlfn.XLOOKUP(A80,A79:A678,[1]Sheet3!P141:P740) -> 7.0954861 | M80: =_xlfn.XLOOKUP(A80,A79:A678,[1]Sheet3!Q141:Q740) -> 1644.33 | N80: =_xlfn.XLOOKUP(A80,A79:A678,[1]Sheet3!S141:S740) -> 0.31 | O80: =_xlfn.XLOOKUP(A80,A79:A678,[1]Sheet3!T141:T740) -> 1186.66 | P80: =_xlfn.XLOOKUP(A80,A79:A678,[1]Sheet3!U141:U740) -> 470.96 | Q80: =_xlfn.XLOOKUP(A80,A79:A678,[1]Sheet3!V141:V740) -> 0.39687863 | R80: =_xlfn.XLOOKUP(A80,A79:A678,[1]Sheet3!W141:W740) -> 68.12 | S80: =_xlfn.XLOOKUP(A80,A79:A678,[1]Sheet3!X141:X740) -> Cash on Delivery | T80: =_xlfn.XLOOKUP(A80,A79:A678,[1]Sheet3!Z141:Z740) -> 5 | U80: =_xlfn.XLOOKUP(A80,A79:A678,[1]Sheet3!AA141:AA740) -> TRUE | V80: =_xlfn.XLOOKUP(A80,A79:A678,[1]Sheet3!AC141:AC740) -> Returned | W80: =_xlfn.XLOOKUP(A80,A79:A678,[1]Sheet3!AE141:AE740) -> 2
A81: ORD-00542 | B81: =_xlfn.XLOOKUP(A81,A80:A679,[1]Sheet3!C178:C777) -> 44072 | C81: =_xlfn.XLOOKUP(A81,A80:A679,[1]Sheet3!D178:D777) -> CUST19508 | D81: =_xlfn.XLOOKUP(A81,A80:A679,[1]Sheet3!E178:E777) -> Arjun Rao | E81: =_xlfn.XLOOKUP(A81,A80:A679,[1]Sheet3!G178:G777) -> 28 | F81: =_xlfn.XLOOKUP('Retail Sales'!A179,'Retail Sales'!A178:A777,[1]Sheet3!H178:H777) -> Young Adult | G81: =_xlfn.XLOOKUP(A81,A80:A679,[1]Sheet3!J178:J777) -> Male | H81: =_xlfn.XLOOKUP(A81,A80:A679,[1]Sheet3!K178:K777) -> West | I81: =_xlfn.XLOOKUP(A81,A80:A679,[1]Sheet3!L178:L777) -> Pune | J81: =_xlfn.XLOOKUP(A81,A80:A679,[1]Sheet3!M178:M777) -> Electronics | K81: =_xlfn.XLOOKUP('Retail Sales'!A179,'Retail Sales'!A178:A777,[1]Sheet3!N178:N777) -> Smartwatch | L81: =_xlfn.XLOOKUP(A81,A80:A679,[1]Sheet3!P178:P777) -> 7.0954861 | M81: =_xlfn.XLOOKUP(A81,A80:A679,[1]Sheet3!Q178:Q777) -> 9189.44 | N81: =_xlfn.XLOOKUP(A81,A80:A679,[1]Sheet3!S178:S777) -> 0.19 | O81: =_xlfn.XLOOKUP(A81,A80:A679,[1]Sheet3!T178:T777) -> 8306.29 | P81: =_xlfn.XLOOKUP(A81,A80:A679,[1]Sheet3!U178:U777) -> 916.95 | Q81: =_xlfn.XLOOKUP(A81,A80:A679,[1]Sheet3!V178:V777) -> 0.11039224 | R81: =_xlfn.XLOOKUP(A81,A80:A679,[1]Sheet3!W178:W777) -> 59.91 | S81: =_xlfn.XLOOKUP(A81,A80:A679,[1]Sheet3!X178:X777) -> Debit Card | T81: =_xlfn.XLOOKUP(A81,A80:A679,[1]Sheet3!Z178:Z777) -> 4 | U81: =_xlfn.XLOOKUP(A81,A80:A679,[1]Sheet3!AA178:AA777) -> FALSE | V81: =_xlfn.XLOOKUP(A81,A80:A679,[1]Sheet3!AC178:AC777) -> Delivered | W81: =_xlfn.XLOOKUP(A81,A80:A679,[1]Sheet3!AE178:AE777) -> 5
A82: ORD-00559 | B82: =_xlfn.XLOOKUP(A82,A81:A680,[1]Sheet3!C328:C927) -> 44079 | C82: =_xlfn.XLOOKUP(A82,A81:A680,[1]Sheet3!D328:D927) -> CUST34558 | D82: =_xlfn.XLOOKUP(A82,A81:A680,[1]Sheet3!E328:E927) -> Amit Bhat | E82: =_xlfn.XLOOKUP(A82,A81:A680,[1]Sheet3!G328:G927) -> 46 | F82: =_xlfn.XLOOKUP('Retail Sales'!A329,'Retail Sales'!A328:A927,[1]Sheet3!H328:H927) -> Adult | G82: =_xlfn.XLOOKUP(A82,A81:A680,[1]Sheet3!J328:J927) -> Other | H82: =_xlfn.XLOOKUP(A82,A81:A680,[1]Sheet3!K328:K927) -> West | I82: =_xlfn.XLOOKUP(A82,A81:A680,[1]Sheet3!L328:L927) -> Mumbai | J82: =_xlfn.XLOOKUP(A82,A81:A680,[1]Sheet3!M328:M927) -> Clothing | K82: =_xlfn.XLOOKUP('Retail Sales'!A329,'Retail Sales'!A328:A927,[1]Sheet3!N328:N927) -> Jeans | L82: =_xlfn.XLOOKUP(A82,A81:A680,[1]Sheet3!P328:P927) -> 8 | M82: =_xlfn.XLOOKUP(A82,A81:A680,[1]Sheet3!Q328:Q927) -> 2151.16 | N82: =_xlfn.XLOOKUP(A82,A81:A680,[1]Sheet3!S328:S927) -> 0.12 | O82: =_xlfn.XLOOKUP(A82,A81:A680,[1]Sheet3!T328:T927) -> 15432.22 | P82: =_xlfn.XLOOKUP(A82,A81:A680,[1]Sheet3!U328:U927) -> 4651.88 | Q82: =_xlfn.XLOOKUP(A82,A81:A680,[1]Sheet3!V328:V927) -> 0.30143946 | R82: =_xlfn.XLOOKUP(A82,A81:A680,[1]Sheet3!W328:W927) -> 67.35 | S82: =_xlfn.XLOOKUP(A82,A81:A680,[1]Sheet3!X328:X927) -> Cash on Delivery | T82: =_xlfn.XLOOKUP(A82,A81:A680,[1]Sheet3!Z328:Z927) -> 4 | U82: =_xlfn.XLOOKUP(A82,A81:A680,[1]Sheet3!AA328:AA927) -> TRUE | V82: =_xlfn.XLOOKUP(A82,A81:A680,[1]Sheet3!AC328:AC927) -> Returned | W82: =_xlfn.XLOOKUP(A82,A81:A680,[1]Sheet3!AE328:AE927) -> 4
A83: ORD-00563 | B83: =_xlfn.XLOOKUP(A83,A82:A681,[1]Sheet3!C393:C992) -> 44081 | C83: =_xlfn.XLOOKUP(A83,A82:A681,[1]Sheet3!D393:D992) -> CUST44323 | D83: =_xlfn.XLOOKUP(A83,A82:A681,[1]Sheet3!E393:E992) -> Ritu Bose | E83: =_xlfn.XLOOKUP(A83,A82:A681,[1]Sheet3!G393:G992) -> 33 | F83: =_xlfn.XLOOKUP('Retail Sales'!A394,'Retail Sales'!A393:A992,[1]Sheet3!H393:H992) -> Young Adult | G83: =_xlfn.XLOOKUP(A83,A82:A681,[1]Sheet3!J393:J992) -> Female | H83: =_xlfn.XLOOKUP(A83,A82:A681,[1]Sheet3!K393:K992) -> South | I83: =_xlfn.XLOOKUP(A83,A82:A681,[1]Sheet3!L393:L992) -> Bangalore | J83: =_xlfn.XLOOKUP(A83,A82:A681,[1]Sheet3!M393:M992) -> Books | K83: =_xlfn.XLOOKUP('Retail Sales'!A394,'Retail Sales'!A393:A992,[1]Sheet3!N393:N992) -> Cook Book | L83: =_xlfn.XLOOKUP(A83,A82:A681,[1]Sheet3!P393:P992) -> 6 | M83: =_xlfn.XLOOKUP(A83,A82:A681,[1]Sheet3!Q393:Q992) -> 1105.96 | N83: =_xlfn.XLOOKUP(A83,A82:A681,[1]Sheet3!S393:S992) -> 0.29 | O83: =_xlfn.XLOOKUP(A83,A82:A681,[1]Sheet3!T393:T992) -> 5241.79 | P83: =_xlfn.XLOOKUP(A83,A82:A681,[1]Sheet3!U393:U992) -> 1716.01 | Q83: =_xlfn.XLOOKUP(A83,A82:A681,[1]Sheet3!V393:V992) -> 0.32737099 | R83: =_xlfn.XLOOKUP(A83,A82:A681,[1]Sheet3!W393:W992) -> 67.65 | S83: =_xlfn.XLOOKUP(A83,A82:A681,[1]Sheet3!X393:X992) -> Debit Card | T83: =_xlfn.XLOOKUP(A83,A82:A681,[1]Sheet3!Z393:Z992) -> 3 | U83: =_xlfn.XLOOKUP(A83,A82:A681,[1]Sheet3!AA393:AA992) -> TRUE | V83: =_xlfn.XLOOKUP(A83,A82:A681,[1]Sheet3!AC393:AC992) -> Returned | W83: =_xlfn.XLOOKUP(A83,A82:A681,[1]Sheet3!AE393:AE992) -> 5
A84: ORD-00566 | B84: =_xlfn.XLOOKUP(A84,A83:A682,[1]Sheet3!C438:C1037) -> 44083 | C84: =_xlfn.XLOOKUP(A84,A83:A682,[1]Sheet3!D438:D1037) -> CUST67628 | D84: =_xlfn.XLOOKUP(A84,A83:A682,[1]Sheet3!E438:E1037) -> Meera Chatterjee | E84: =_xlfn.XLOOKUP(A84,A83:A682,[1]Sheet3!G438:G1037) -> 25 | F84: =_xlfn.XLOOKUP('Retail Sales'!A439,'Retail Sales'!A438:A1037,[1]Sheet3!H438:H1037) -> Young Adult | G84: =_xlfn.XLOOKUP(A84,A83:A682,[1]Sheet3!J438:J1037) -> Other | H84: =_xlfn.XLOOKUP(A84,A83:A682,[1]Sheet3!K438:K1037) -> North | I84: =_xlfn.XLOOKUP(A84,A83:A682,[1]Sheet3!L438:L1037) -> Amritsar | J84: =_xlfn.XLOOKUP(A84,A83:A682,[1]Sheet3!M438:M1037) -> Sports | K84: =_xlfn.XLOOKUP('Retail Sales'!A439,'Retail Sales'!A438:A1037,[1]Sheet3!N438:N1037) -> Dumbbells | L84: =_xlfn.XLOOKUP(A84,A83:A682,[1]Sheet3!P438:P1037) -> 7.0954861 | M84: =_xlfn.XLOOKUP(A84,A83:A682,[1]Sheet3!Q438:Q1037) -> 603.71 | N84: =_xlfn.XLOOKUP(A84,A83:A682,[1]Sheet3!S438:S1037) -> 0.39 | O84: =_xlfn.XLOOKUP(A84,A83:A682,[1]Sheet3!T438:T1037) -> 373.9 | P84: =_xlfn.XLOOKUP(A84,A83:A682,[1]Sheet3!U438:U1037) -> 76.01 | Q84: =_xlfn.XLOOKUP(A84,A83:A682,[1]Sheet3!V438:V1037) -> 0.20328965 | R84: =_xlfn.XLOOKUP(A84,A83:A682,[1]Sheet3!W438:W1037) -> 68.01 | S84: =_xlfn.XLOOKUP(A84,A83:A682,[1]Sheet3!X438:X1037) -> Net Banking | T84: =_xlfn.XLOOKUP(A84,A83:A682,[1]Sheet3!Z438:Z1037) -> 3 | U84: =_xlfn.XLOOKUP(A84,A83:A682,[1]Sheet3!AA438:AA1037) -> FALSE | V84: =_xlfn.XLOOKUP(A84,A83:A682,[1]Sheet3!AC438:AC1037) -> Shipped | W84: =_xlfn.XLOOKUP(A84,A83:A682,[1]Sheet3!AE438:AE1037) -> 9
A85: ORD-00571 | B85: =_xlfn.XLOOKUP(A85,A84:A683,[1]Sheet3!C539:C1138) -> 44084 | C85: =_xlfn.XLOOKUP(A85,A84:A683,[1]Sheet3!D539:D1138) -> CUST29775 | D85: =_xlfn.XLOOKUP(A85,A84:A683,[1]Sheet3!E539:E1138) -> Deepa Sharma | E85: =_xlfn.XLOOKUP(A85,A84:A683,[1]Sheet3!G539:G1138) -> 16 | F85: =_xlfn.XLOOKUP('Retail Sales'!A540,'Retail Sales'!A539:A1138,[1]Sheet3!H539:H1138) -> Teen | G85: =_xlfn.XLOOKUP(A85,A84:A683,[1]Sheet3!J539:J1138) -> Other | H85: =_xlfn.XLOOKUP(A85,A84:A683,[1]Sheet3!K539:K1138) -> Central | I85: =_xlfn.XLOOKUP(A85,A84:A683,[1]Sheet3!L539:L1138) -> Raipur | J85: =_xlfn.XLOOKUP(A85,A84:A683,[1]Sheet3!M539:M1138) -> Books | K85: =_xlfn.XLOOKUP('Retail Sales'!A540,'Retail Sales'!A539:A1138,[1]Sheet3!N539:N1138) -> Biography | L85: =_xlfn.XLOOKUP(A85,A84:A683,[1]Sheet3!P539:P1138) -> 1 | M85: =_xlfn.XLOOKUP(A85,A84:A683,[1]Sheet3!Q539:Q1138) -> 565.12 | N85: =_xlfn.XLOOKUP(A85,A84:A683,[1]Sheet3!S539:S1138) -> 0.08 | O85: =_xlfn.XLOOKUP(A85,A84:A683,[1]Sheet3!T539:T1138) -> 539.57 | P85: =_xlfn.XLOOKUP(A85,A84:A683,[1]Sheet3!U539:U1138) -> 249.41 | Q85: =_xlfn.XLOOKUP(A85,A84:A683,[1]Sheet3!V539:V1138) -> 0.46223845 | R85: =_xlfn.XLOOKUP(A85,A84:A683,[1]Sheet3!W539:W1138) -> 49.52 | S85: =_xlfn.XLOOKUP(A85,A84:A683,[1]Sheet3!X539:X1138) -> UPI | T85: =_xlfn.XLOOKUP(A85,A84:A683,[1]Sheet3!Z539:Z1138) -> 4 | U85: =_xlfn.XLOOKUP(A85,A84:A683,[1]Sheet3!AA539:AA1138) -> FALSE | V85: =_xlfn.XLOOKUP(A85,A84:A683,[1]Sheet3!AC539:AC1138) -> Delivered | W85: =_xlfn.XLOOKUP(A85,A84:A683,[1]Sheet3!AE539:AE1138) -> 4
A86: ORD-00575 | B86: =_xlfn.XLOOKUP(A86,A85:A684,[1]Sheet3!C370:C969) -> 44088 | C86: =_xlfn.XLOOKUP(A86,A85:A684,[1]Sheet3!D370:D969) -> CUST39101 | D86: =_xlfn.XLOOKUP(A86,A85:A684,[1]Sheet3!E370:E969) -> Sunita Mehta | E86: =_xlfn.XLOOKUP(A86,A85:A684,[1]Sheet3!G370:G969) -> 32 | F86: =_xlfn.XLOOKUP('Retail Sales'!A371,'Retail Sales'!A370:A969,[1]Sheet3!H370:H969) -> Young Adult | G86: =_xlfn.XLOOKUP(A86,A85:A684,[1]Sheet3!J370:J969) -> Other | H86: =_xlfn.XLOOKUP(A86,A85:A684,[1]Sheet3!K370:K969) -> East | I86: =_xlfn.XLOOKUP(A86,A85:A684,[1]Sheet3!L370:L969) -> Guwahati | J86: =_xlfn.XLOOKUP(A86,A85:A684,[1]Sheet3!M370:M969) -> Furniture | K86: =_xlfn.XLOOKUP('Retail Sales'!A371,'Retail Sales'!A370:A969,[1]Sheet3!N370:N969) -> Bookshelf | L86: =_xlfn.XLOOKUP(A86,A85:A684,[1]Sheet3!P370:P969) -> 7 | M86: =_xlfn.XLOOKUP(A86,A85:A684,[1]Sheet3!Q370:Q969) -> 5932.53 | N86: =_xlfn.XLOOKUP(A86,A85:A684,[1]Sheet3!S370:S969) -> 0.39 | O86: =_xlfn.XLOOKUP(A86,A85:A684,[1]Sheet3!T370:T969) -> 23093.12 | P86: =_xlfn.XLOOKUP(A86,A85:A684,[1]Sheet3!U370:U969) -> 8164.97 | Q86: =_xlfn.XLOOKUP(A86,A85:A684,[1]Sheet3!V370:V969) -> 0.35356721 | R86: =_xlfn.XLOOKUP(A86,A85:A684,[1]Sheet3!W370:W969) -> 84.41 | S86: =_xlfn.XLOOKUP(A86,A85:A684,[1]Sheet3!X370:X969) -> UPI | T86: =_xlfn.XLOOKUP(A86,A85:A684,[1]Sheet3!Z370:Z969) -> 3 | U86: =_xlfn.XLOOKUP(A86,A85:A684,[1]Sheet3!AA370:AA969) -> FALSE | V86: =_xlfn.XLOOKUP(A86,A85:A684,[1]Sheet3!AC370:AC969) -> Delivered | W86: =_xlfn.XLOOKUP(A86,A85:A684,[1]Sheet3!AE370:AE969) -> 1
A87: ORD-00582 | B87: =_xlfn.XLOOKUP(A87,A86:A685,[1]Sheet3!C538:C1137) -> 44091 | C87: =_xlfn.XLOOKUP(A87,A86:A685,[1]Sheet3!D538:D1137) -> CUST42583 | D87: =_xlfn.XLOOKUP(A87,A86:A685,[1]Sheet3!E538:E1137) -> Nisha Rao | E87: =_xlfn.XLOOKUP(A87,A86:A685,[1]Sheet3!G538:G1137) -> 31 | F87: =_xlfn.XLOOKUP('Retail Sales'!A539,'Retail Sales'!A538:A1137,[1]Sheet3!H538:H1137) -> Young Adult | G87: =_xlfn.XLOOKUP(A87,A86:A685,[1]Sheet3!J538:J1137) -> Other | H87: =_xlfn.XLOOKUP(A87,A86:A685,[1]Sheet3!K538:K1137) -> South | I87: =_xlfn.XLOOKUP(A87,A86:A685,[1]Sheet3!L538:L1137) -> Bangalore | J87: =_xlfn.XLOOKUP(A87,A86:A685,[1]Sheet3!M538:M1137) -> Books | K87: =_xlfn.XLOOKUP('Retail Sales'!A539,'Retail Sales'!A538:A1137,[1]Sheet3!N538:N1137) -> Cook Book | L87: =_xlfn.XLOOKUP(A87,A86:A685,[1]Sheet3!P538:P1137) -> 1 | M87: =_xlfn.XLOOKUP(A87,A86:A685,[1]Sheet3!Q538:Q1137) -> 587.49 | N87: =_xlfn.XLOOKUP(A87,A86:A685,[1]Sheet3!S538:S1137) -> 0.09 | O87: =_xlfn.XLOOKUP(A87,A86:A685,[1]Sheet3!T538:T1137) -> 560.43 | P87: =_xlfn.XLOOKUP(A87,A86:A685,[1]Sheet3!U538:U1137) -> 178.2 | Q87: =_xlfn.XLOOKUP(A87,A86:A685,[1]Sheet3!V538:V1137) -> 0.31797013 | R87: =_xlfn.XLOOKUP(A87,A86:A685,[1]Sheet3!W538:W1137) -> 82.7 | S87: =_xlfn.XLOOKUP(A87,A86:A685,[1]Sheet3!X538:X1137) -> Debit Card | T87: =_xlfn.XLOOKUP(A87,A86:A685,[1]Sheet3!Z538:Z1137) -> 3 | U87: =_xlfn.XLOOKUP(A87,A86:A685,[1]Sheet3!AA538:AA1137) -> FALSE | V87: =_xlfn.XLOOKUP(A87,A86:A685,[1]Sheet3!AC538:AC1137) -> Delivered | W87: =_xlfn.XLOOKUP(A87,A86:A685,[1]Sheet3!AE538:AE1137) -> 6
A88: ORD-00591 | B88: =_xlfn.XLOOKUP(A88,A87:A686,[1]Sheet3!C160:C759) -> 44095 | C88: =_xlfn.XLOOKUP(A88,A87:A686,[1]Sheet3!D160:D759) -> CUST49777 | D88: =_xlfn.XLOOKUP(A88,A87:A686,[1]Sheet3!E160:E759) -> Pooja Shah | E88: =_xlfn.XLOOKUP(A88,A87:A686,[1]Sheet3!G160:G759) -> 33 | F88: =_xlfn.XLOOKUP('Retail Sales'!A161,'Retail Sales'!A160:A759,[1]Sheet3!H160:H759) -> Young Adult | G88: =_xlfn.XLOOKUP(A88,A87:A686,[1]Sheet3!J160:J759) -> Female | H88: =_xlfn.XLOOKUP(A88,A87:A686,[1]Sheet3!K160:K759) -> South | I88: =_xlfn.XLOOKUP(A88,A87:A686,[1]Sheet3!L160:L759) -> Hyderabad | J88: =_xlfn.XLOOKUP(A88,A87:A686,[1]Sheet3!M160:M759) -> Groceries | K88: =_xlfn.XLOOKUP('Retail Sales'!A161,'Retail Sales'!A160:A759,[1]Sheet3!N160:N759) -> Tea | L88: =_xlfn.XLOOKUP(A88,A87:A686,[1]Sheet3!P160:P759) -> 1 | M88: =_xlfn.XLOOKUP(A88,A87:A686,[1]Sheet3!Q160:Q759) -> 389.24 | N88: =_xlfn.XLOOKUP(A88,A87:A686,[1]Sheet3!S160:S759) -> 0.23 | O88: =_xlfn.XLOOKUP(A88,A87:A686,[1]Sheet3!T160:T759) -> 313.86 | P88: =_xlfn.XLOOKUP(A88,A87:A686,[1]Sheet3!U160:U759) -> 22.71 | Q88: =_xlfn.XLOOKUP(A88,A87:A686,[1]Sheet3!V160:V759) -> 0.072357102 | R88: =_xlfn.XLOOKUP(A88,A87:A686,[1]Sheet3!W160:W759) -> 66.8 | S88: =_xlfn.XLOOKUP(A88,A87:A686,[1]Sheet3!X160:X759) -> Net Banking | T88: =_xlfn.XLOOKUP(A88,A87:A686,[1]Sheet3!Z160:Z759) -> 5 | U88: =_xlfn.XLOOKUP(A88,A87:A686,[1]Sheet3!AA160:AA759) -> FALSE | V88: =_xlfn.XLOOKUP(A88,A87:A686,[1]Sheet3!AC160:AC759) -> Delivered | W88: =_xlfn.XLOOKUP(A88,A87:A686,[1]Sheet3!AE160:AE759) -> 10
A89: ORD-00593 | B89: =_xlfn.XLOOKUP(A89,A88:A687,[1]Sheet3!C87:C686) -> 44096 | C89: =_xlfn.XLOOKUP(A89,A88:A687,[1]Sheet3!D87:D686) -> CUST21963 | D89: =_xlfn.XLOOKUP(A89,A88:A687,[1]Sheet3!E87:E686) -> Priya Bhat | E89: =_xlfn.XLOOKUP(A89,A88:A687,[1]Sheet3!G87:G686) -> 38 | F89: =_xlfn.XLOOKUP('Retail Sales'!A88,'Retail Sales'!A87:A686,[1]Sheet3!H87:H686) -> Adult | G89: =_xlfn.XLOOKUP(A89,A88:A687,[1]Sheet3!J87:J686) -> Other | H89: =_xlfn.XLOOKUP(A89,A88:A687,[1]Sheet3!K87:K686) -> Central | I89: =_xlfn.XLOOKUP(A89,A88:A687,[1]Sheet3!L87:L686) -> Bhopal | J89: =_xlfn.XLOOKUP(A89,A88:A687,[1]Sheet3!M87:M686) -> Furniture | K89: =_xlfn.XLOOKUP('Retail Sales'!A88,'Retail Sales'!A87:A686,[1]Sheet3!N87:N686) -> Wardrobe | L89: =_xlfn.XLOOKUP(A89,A88:A687,[1]Sheet3!P87:P686) -> 8 | M89: =_xlfn.XLOOKUP(A89,A88:A687,[1]Sheet3!Q87:Q686) -> 30292.85 | N89: =_xlfn.XLOOKUP(A89,A88:A687,[1]Sheet3!S87:S686) -> 0.29 | O89: =_xlfn.XLOOKUP(A89,A88:A687,[1]Sheet3!T87:T686) -> 173004.24 | P89: =_xlfn.XLOOKUP(A89,A88:A687,[1]Sheet3!U87:U686) -> 45465.04 | Q89: =_xlfn.XLOOKUP(A89,A88:A687,[1]Sheet3!V87:V686) -> 0.26279726 | R89: =_xlfn.XLOOKUP(A89,A88:A687,[1]Sheet3!W87:W686) -> 51.64 | S89: =_xlfn.XLOOKUP(A89,A88:A687,[1]Sheet3!X87:X686) -> EMI | T89: =_xlfn.XLOOKUP(A89,A88:A687,[1]Sheet3!Z87:Z686) -> 3 | U89: =_xlfn.XLOOKUP(A89,A88:A687,[1]Sheet3!AA87:AA686) -> FALSE | V89: =_xlfn.XLOOKUP(A89,A88:A687,[1]Sheet3!AC87:AC686) -> Delivered | W89: =_xlfn.XLOOKUP(A89,A88:A687,[1]Sheet3!AE87:AE686) -> 5
A90: ORD-00597 | B90: =_xlfn.XLOOKUP(A90,A89:A688,[1]Sheet3!C377:C976) -> 44098 | C90: =_xlfn.XLOOKUP(A90,A89:A688,[1]Sheet3!D377:D976) -> CUST03651 | D90: =_xlfn.XLOOKUP(A90,A89:A688,[1]Sheet3!E377:E976) -> Arjun Patel | E90: =_xlfn.XLOOKUP(A90,A89:A688,[1]Sheet3!G377:G976) -> 55 | F90: =_xlfn.XLOOKUP('Retail Sales'!A378,'Retail Sales'!A377:A976,[1]Sheet3!H377:H976) -> Senior | G90: =_xlfn.XLOOKUP(A90,A89:A688,[1]Sheet3!J377:J976) -> Female | H90: =_xlfn.XLOOKUP(A90,A89:A688,[1]Sheet3!K377:K976) -> West | I90: =_xlfn.XLOOKUP(A90,A89:A688,[1]Sheet3!L377:L976) -> Surat | J90: =_xlfn.XLOOKUP(A90,A89:A688,[1]Sheet3!M377:M976) -> Electronics | K90: =_xlfn.XLOOKUP('Retail Sales'!A378,'Retail Sales'!A377:A976,[1]Sheet3!N377:N976) -> Tablet | L90: =_xlfn.XLOOKUP(A90,A89:A688,[1]Sheet3!P377:P976) -> 1 | M90: =_xlfn.XLOOKUP(A90,A89:A688,[1]Sheet3!Q377:Q976) -> 38379.55 | N90: =_xlfn.XLOOKUP(A90,A89:A688,[1]Sheet3!S377:S976) -> 0.18 | O90: =_xlfn.XLOOKUP(A90,A89:A688,[1]Sheet3!T377:T976) -> 33725.89 | P90: =_xlfn.XLOOKUP(A90,A89:A688,[1]Sheet3!U377:U976) -> 4708.06 | Q90: =_xlfn.XLOOKUP(A90,A89:A688,[1]Sheet3!V377:V976) -> 0.1395978 | R90: =_xlfn.XLOOKUP(A90,A89:A688,[1]Sheet3!W377:W976) -> 49.85 | S90: =_xlfn.XLOOKUP(A90,A89:A688,[1]Sheet3!X377:X976) -> EMI | T90: =_xlfn.XLOOKUP(A90,A89:A688,[1]Sheet3!Z377:Z976) -> 2 | U90: =_xlfn.XLOOKUP(A90,A89:A688,[1]Sheet3!AA377:AA976) -> FALSE | V90: =_xlfn.XLOOKUP(A90,A89:A688,[1]Sheet3!AC377:AC976) -> Delivered | W90: =_xlfn.XLOOKUP(A90,A89:A688,[1]Sheet3!AE377:AE976) -> 5
A91: ORD-00601 | B91: =_xlfn.XLOOKUP(A91,A90:A689,[1]Sheet3!C215:C814) -> 44099 | C91: =_xlfn.XLOOKUP(A91,A90:A689,[1]Sheet3!D215:D814) -> CUST39660 | D91: =_xlfn.XLOOKUP(A91,A90:A689,[1]Sheet3!E215:E814) -> Priya Pillai | E91: =_xlfn.XLOOKUP(A91,A90:A689,[1]Sheet3!G215:G814) -> 53 | F91: =_xlfn.XLOOKUP('Retail Sales'!A216,'Retail Sales'!A215:A814,[1]Sheet3!H215:H814) -> Senior | G91: =_xlfn.XLOOKUP(A91,A90:A689,[1]Sheet3!J215:J814) -> Male | H91: =_xlfn.XLOOKUP(A91,A90:A689,[1]Sheet3!K215:K814) -> South | I91: =_xlfn.XLOOKUP(A91,A90:A689,[1]Sheet3!L215:L814) -> Kochi | J91: =_xlfn.XLOOKUP(A91,A90:A689,[1]Sheet3!M215:M814) -> Books | K91: =_xlfn.XLOOKUP('Retail Sales'!A216,'Retail Sales'!A215:A814,[1]Sheet3!N215:N814) -> Textbook | L91: =_xlfn.XLOOKUP(A91,A90:A689,[1]Sheet3!P215:P814) -> 7 | M91: =_xlfn.XLOOKUP(A91,A90:A689,[1]Sheet3!Q215:Q814) -> 298.01 | N91: =_xlfn.XLOOKUP(A91,A90:A689,[1]Sheet3!S215:S814) -> 0.2 | O91: =_xlfn.XLOOKUP(A91,A90:A689,[1]Sheet3!T215:T814) -> 1735.77 | P91: =_xlfn.XLOOKUP(A91,A90:A689,[1]Sheet3!U215:U814) -> 683.51 | Q91: =_xlfn.XLOOKUP(A91,A90:A689,[1]Sheet3!V215:V814) -> 0.39377913 | R91: =_xlfn.XLOOKUP(A91,A90:A689,[1]Sheet3!W215:W814) -> 71.67 | S91: =_xlfn.XLOOKUP(A91,A90:A689,[1]Sheet3!X215:X814) -> EMI | T91: =_xlfn.XLOOKUP(A91,A90:A689,[1]Sheet3!Z215:Z814) -> 2 | U91: =_xlfn.XLOOKUP(A91,A90:A689,[1]Sheet3!AA215:AA814) -> TRUE | V91: =_xlfn.XLOOKUP(A91,A90:A689,[1]Sheet3!AC215:AC814) -> Returned | W91: =_xlfn.XLOOKUP(A91,A90:A689,[1]Sheet3!AE215:AE814) -> 2
A92: ORD-00617 | B92: =_xlfn.XLOOKUP(A92,A91:A690,[1]Sheet3!C500:C1099) -> 44107 | C92: =_xlfn.XLOOKUP(A92,A91:A690,[1]Sheet3!D500:D1099) -> CUST56731 | D92: =_xlfn.XLOOKUP(A92,A91:A690,[1]Sheet3!E500:E1099) -> Rohan Bhat | E92: =_xlfn.XLOOKUP(A92,A91:A690,[1]Sheet3!G500:G1099) -> 52 | F92: =_xlfn.XLOOKUP('Retail Sales'!A501,'Retail Sales'!A500:A1099,[1]Sheet3!H500:H1099) -> Senior | G92: =_xlfn.XLOOKUP(A92,A91:A690,[1]Sheet3!J500:J1099) -> Female | H92: =_xlfn.XLOOKUP(A92,A91:A690,[1]Sheet3!K500:K1099) -> South | I92: =_xlfn.XLOOKUP(A92,A91:A690,[1]Sheet3!L500:L1099) -> Bangalore | J92: =_xlfn.XLOOKUP(A92,A91:A690,[1]Sheet3!M500:M1099) -> Electronics | K92: =_xlfn.XLOOKUP('Retail Sales'!A501,'Retail Sales'!A500:A1099,[1]Sheet3!N500:N1099) -> Smartwatch | L92: =_xlfn.XLOOKUP(A92,A91:A690,[1]Sheet3!P500:P1099) -> 4 | M92: =_xlfn.XLOOKUP(A92,A91:A690,[1]Sheet3!Q500:Q1099) -> 72305.61 | N92: =_xlfn.XLOOKUP(A92,A91:A690,[1]Sheet3!S500:S1099) -> 0.03 | O92: =_xlfn.XLOOKUP(A92,A91:A690,[1]Sheet3!T500:T1099) -> 221219.87 | P92: =_xlfn.XLOOKUP(A92,A91:A690,[1]Sheet3!U500:U1099) -> 28168.08 | Q92: =_xlfn.XLOOKUP(A92,A91:A690,[1]Sheet3!V500:V1099) -> 0.1273307 | R92: =_xlfn.XLOOKUP(A92,A91:A690,[1]Sheet3!W500:W1099) -> 54.29 | S92: =_xlfn.XLOOKUP(A92,A91:A690,[1]Sheet3!X500:X1099) -> Debit Card | T92: =_xlfn.XLOOKUP(A92,A91:A690,[1]Sheet3!Z500:Z1099) -> 4 | U92: =_xlfn.XLOOKUP(A92,A91:A690,[1]Sheet3!AA500:AA1099) -> TRUE | V92: =_xlfn.XLOOKUP(A92,A91:A690,[1]Sheet3!AC500:AC1099) -> Returned | W92: =_xlfn.XLOOKUP(A92,A91:A690,[1]Sheet3!AE500:AE1099) -> 10
A93: ORD-00619 | B93: =_xlfn.XLOOKUP(A93,A92:A691,[1]Sheet3!C546:C1145) -> 44108 | C93: =_xlfn.XLOOKUP(A93,A92:A691,[1]Sheet3!D546:D1145) -> CUST73824 | D93: =_xlfn.XLOOKUP(A93,A92:A691,[1]Sheet3!E546:E1145) -> Rohan Kapoor | E93: =_xlfn.XLOOKUP(A93,A92:A691,[1]Sheet3!G546:G1145) -> 36 | F93: =_xlfn.XLOOKUP('Retail Sales'!A547,'Retail Sales'!A546:A1145,[1]Sheet3!H546:H1145) -> Adult | G93: =_xlfn.XLOOKUP(A93,A92:A691,[1]Sheet3!J546:J1145) -> Male | H93: =_xlfn.XLOOKUP(A93,A92:A691,[1]Sheet3!K546:K1145) -> Central | I93: =_xlfn.XLOOKUP(A93,A92:A691,[1]Sheet3!L546:L1145) -> Raipur | J93: =_xlfn.XLOOKUP(A93,A92:A691,[1]Sheet3!M546:M1145) -> Furniture | K93: =_xlfn.XLOOKUP('Retail Sales'!A547,'Retail Sales'!A546:A1145,[1]Sheet3!N546:N1145) -> Wardrobe | L93: =_xlfn.XLOOKUP(A93,A92:A691,[1]Sheet3!P546:P1145) -> 5 | M93: =_xlfn.XLOOKUP(A93,A92:A691,[1]Sheet3!Q546:Q1145) -> 11291.76 | N93: =_xlfn.XLOOKUP(A93,A92:A691,[1]Sheet3!S546:S1145) -> 0.4 | O93: =_xlfn.XLOOKUP(A93,A92:A691,[1]Sheet3!T546:T1145) -> 21297.23 | P93: =_xlfn.XLOOKUP(A93,A92:A691,[1]Sheet3!U546:U1145) -> 5332.78 | Q93: =_xlfn.XLOOKUP(A93,A92:A691,[1]Sheet3!V546:V1145) -> 0.25039782 | R93: =_xlfn.XLOOKUP(A93,A92:A691,[1]Sheet3!W546:W1145) -> 40.67 | S93: =_xlfn.XLOOKUP(A93,A92:A691,[1]Sheet3!X546:X1145) -> Credit Card | T93: =_xlfn.XLOOKUP(A93,A92:A691,[1]Sheet3!Z546:Z1145) -> 4 | U93: =_xlfn.XLOOKUP(A93,A92:A691,[1]Sheet3!AA546:AA1145) -> FALSE | V93: =_xlfn.XLOOKUP(A93,A92:A691,[1]Sheet3!AC546:AC1145) -> Shipped | W93: =_xlfn.XLOOKUP(A93,A92:A691,[1]Sheet3!AE546:AE1145) -> 5
A94: ORD-00629 | B94: =_xlfn.XLOOKUP(A94,A93:A692,[1]Sheet3!C344:C943) -> 44113 | C94: =_xlfn.XLOOKUP(A94,A93:A692,[1]Sheet3!D344:D943) -> CUST51786 | D94: =_xlfn.XLOOKUP(A94,A93:A692,[1]Sheet3!E344:E943) -> Kavya Joshi | E94: =_xlfn.XLOOKUP(A94,A93:A692,[1]Sheet3!G344:G943) -> 48 | F94: =_xlfn.XLOOKUP('Retail Sales'!A345,'Retail Sales'!A344:A943,[1]Sheet3!H344:H943) -> Adult | G94: =_xlfn.XLOOKUP(A94,A93:A692,[1]Sheet3!J344:J943) -> Male | H94: =_xlfn.XLOOKUP(A94,A93:A692,[1]Sheet3!K344:K943) -> Central | I94: =_xlfn.XLOOKUP(A94,A93:A692,[1]Sheet3!L344:L943) -> Bhopal | J94: =_xlfn.XLOOKUP(A94,A93:A692,[1]Sheet3!M344:M943) -> Beauty | K94: =_xlfn.XLOOKUP('Retail Sales'!A345,'Retail Sales'!A344:A943,[1]Sheet3!N344:N943) -> Perfume | L94: =_xlfn.XLOOKUP(A94,A93:A692,[1]Sheet3!P344:P943) -> 9 | M94: =_xlfn.XLOOKUP(A94,A93:A692,[1]Sheet3!Q344:Q943) -> 1406.56 | N94: =_xlfn.XLOOKUP(A94,A93:A692,[1]Sheet3!S344:S943) -> 0.1 | O94: =_xlfn.XLOOKUP(A94,A93:A692,[1]Sheet3!T344:T943) -> 8925.05 | P94: =_xlfn.XLOOKUP(A94,A93:A692,[1]Sheet3!U344:U943) -> 3776.97 | Q94: =_xlfn.XLOOKUP(A94,A93:A692,[1]Sheet3!V344:V943) -> 0.42318755 | R94: =_xlfn.XLOOKUP(A94,A93:A692,[1]Sheet3!W344:W943) -> 39.94 | S94: =_xlfn.XLOOKUP(A94,A93:A692,[1]Sheet3!X344:X943) -> Cash on Delivery | T94: =_xlfn.XLOOKUP(A94,A93:A692,[1]Sheet3!Z344:Z943) -> 3 | U94: =_xlfn.XLOOKUP(A94,A93:A692,[1]Sheet3!AA344:AA943) -> FALSE | V94: =_xlfn.XLOOKUP(A94,A93:A692,[1]Sheet3!AC344:AC943) -> Delivered | W94: =_xlfn.XLOOKUP(A94,A93:A692,[1]Sheet3!AE344:AE943) -> 5
A95: ORD-00634 | B95: =_xlfn.XLOOKUP(A95,A94:A693,[1]Sheet3!C90:C689) -> 44115 | C95: =_xlfn.XLOOKUP(A95,A94:A693,[1]Sheet3!D90:D689) -> CUST01277 | D95: =_xlfn.XLOOKUP(A95,A94:A693,[1]Sheet3!E90:E689) -> Sanjay Iyer | E95: =_xlfn.XLOOKUP(A95,A94:A693,[1]Sheet3!G90:G689) -> 22 | F95: =_xlfn.XLOOKUP('Retail Sales'!A91,'Retail Sales'!A90:A689,[1]Sheet3!H90:H689) -> Young Adult | G95: =_xlfn.XLOOKUP(A95,A94:A693,[1]Sheet3!J90:J689) -> Female | H95: =_xlfn.XLOOKUP(A95,A94:A693,[1]Sheet3!K90:K689) -> West | I95: =_xlfn.XLOOKUP(A95,A94:A693,[1]Sheet3!L90:L689) -> Surat | J95: =_xlfn.XLOOKUP(A95,A94:A693,[1]Sheet3!M90:M689) -> Furniture | K95: =_xlfn.XLOOKUP('Retail Sales'!A91,'Retail Sales'!A90:A689,[1]Sheet3!N90:N689) -> Bookshelf | L95: =_xlfn.XLOOKUP(A95,A94:A693,[1]Sheet3!P90:P689) -> 7 | M95: =_xlfn.XLOOKUP(A95,A94:A693,[1]Sheet3!Q90:Q689) -> 34455.92 | N95: =_xlfn.XLOOKUP(A95,A94:A693,[1]Sheet3!S90:S689) -> 0.28 | O95: =_xlfn.XLOOKUP(A95,A94:A693,[1]Sheet3!T90:T689) -> 149044.86 | P95: =_xlfn.XLOOKUP(A95,A94:A693,[1]Sheet3!U90:U689) -> 39164.43 | Q95: =_xlfn.XLOOKUP(A95,A94:A693,[1]Sheet3!V90:V689) -> 0.26276941 | R95: =_xlfn.XLOOKUP(A95,A94:A693,[1]Sheet3!W90:W689) -> 54.2 | S95: =_xlfn.XLOOKUP(A95,A94:A693,[1]Sheet3!X90:X689) -> Debit Card | T95: =_xlfn.XLOOKUP(A95,A94:A693,[1]Sheet3!Z90:Z689) -> 3 | U95: =_xlfn.XLOOKUP(A95,A94:A693,[1]Sheet3!AA90:AA689) -> FALSE | V95: =_xlfn.XLOOKUP(A95,A94:A693,[1]Sheet3!AC90:AC689) -> Delivered | W95: =_xlfn.XLOOKUP(A95,A94:A693,[1]Sheet3!AE90:AE689) -> 7
A96: ORD-00644 | B96: =_xlfn.XLOOKUP(A96,A95:A694,[1]Sheet3!C384:C983) -> 44118 | C96: =_xlfn.XLOOKUP(A96,A95:A694,[1]Sheet3!D384:D983) -> CUST94203 | D96: =_xlfn.XLOOKUP(A96,A95:A694,[1]Sheet3!E384:E983) -> Sanjay Nair | E96: =_xlfn.XLOOKUP(A96,A95:A694,[1]Sheet3!G384:G983) -> 34 | F96: =_xlfn.XLOOKUP('Retail Sales'!A385,'Retail Sales'!A384:A983,[1]Sheet3!H384:H983) -> Young Adult | G96: =_xlfn.XLOOKUP(A96,A95:A694,[1]Sheet3!J384:J983) -> Other | H96: =_xlfn.XLOOKUP(A96,A95:A694,[1]Sheet3!K384:K983) -> Central | I96: =_xlfn.XLOOKUP(A96,A95:A694,[1]Sheet3!L384:L983) -> Bhopal | J96: =_xlfn.XLOOKUP(A96,A95:A694,[1]Sheet3!M384:M983) -> Furniture | K96: =_xlfn.XLOOKUP('Retail Sales'!A385,'Retail Sales'!A384:A983,[1]Sheet3!N384:N983) -> Bed Frame | L96: =_xlfn.XLOOKUP(A96,A95:A694,[1]Sheet3!P384:P983) -> 4 | M96: =_xlfn.XLOOKUP(A96,A95:A694,[1]Sheet3!Q384:Q983) -> 22879.02 | N96: =_xlfn.XLOOKUP(A96,A95:A694,[1]Sheet3!S384:S983) -> 0.1 | O96: =_xlfn.XLOOKUP(A96,A95:A694,[1]Sheet3!T384:T983) -> 63905.82 | P96: =_xlfn.XLOOKUP(A96,A95:A694,[1]Sheet3!U384:U983) -> 18612.63 | Q96: =_xlfn.XLOOKUP(A96,A95:A694,[1]Sheet3!V384:V983) -> 0.29125094 | R96: =_xlfn.XLOOKUP(A96,A95:A694,[1]Sheet3!W384:W983) -> 53.94 | S96: =_xlfn.XLOOKUP(A96,A95:A694,[1]Sheet3!X384:X983) -> Cash on Delivery | T96: =_xlfn.XLOOKUP(A96,A95:A694,[1]Sheet3!Z384:Z983) -> 1 | U96: =_xlfn.XLOOKUP(A96,A95:A694,[1]Sheet3!AA384:AA983) -> FALSE | V96: =_xlfn.XLOOKUP(A96,A95:A694,[1]Sheet3!AC384:AC983) -> Cancelled | W96: =_xlfn.XLOOKUP(A96,A95:A694,[1]Sheet3!AE384:AE983) -> 6
A97: ORD-00653 | B97: =_xlfn.XLOOKUP(A97,A96:A695,[1]Sheet3!C169:C768) -> 44124 | C97: =_xlfn.XLOOKUP(A97,A96:A695,[1]Sheet3!D169:D768) -> CUST35559 | D97: =_xlfn.XLOOKUP(A97,A96:A695,[1]Sheet3!E169:E768) -> Ritu Nair | E97: =_xlfn.XLOOKUP(A97,A96:A695,[1]Sheet3!G169:G768) -> 22 | F97: =_xlfn.XLOOKUP('Retail Sales'!A170,'Retail Sales'!A169:A768,[1]Sheet3!H169:H768) -> Young Adult | G97: =_xlfn.XLOOKUP(A97,A96:A695,[1]Sheet3!J169:J768) -> Female | H97: =_xlfn.XLOOKUP(A97,A96:A695,[1]Sheet3!K169:K768) -> Central | I97: =_xlfn.XLOOKUP(A97,A96:A695,[1]Sheet3!L169:L768) -> Nagpur | J97: =_xlfn.XLOOKUP(A97,A96:A695,[1]Sheet3!M169:M768) -> Books | K97: =_xlfn.XLOOKUP('Retail Sales'!A170,'Retail Sales'!A169:A768,[1]Sheet3!N169:N768) -> Textbook | L97: =_xlfn.XLOOKUP(A97,A96:A695,[1]Sheet3!P169:P768) -> 3 | M97: =_xlfn.XLOOKUP(A97,A96:A695,[1]Sheet3!Q169:Q768) -> 835.42 | N97: =_xlfn.XLOOKUP(A97,A96:A695,[1]Sheet3!S169:S768) -> 0.33 | O97: =_xlfn.XLOOKUP(A97,A96:A695,[1]Sheet3!T169:T768) -> 1423.3 | P97: =_xlfn.XLOOKUP(A97,A96:A695,[1]Sheet3!U169:U768) -> 458.44 | Q97: =_xlfn.XLOOKUP(A97,A96:A695,[1]Sheet3!V169:V768) -> 0.32209654 | R97: =_xlfn.XLOOKUP(A97,A96:A695,[1]Sheet3!W169:W768) -> 55.32 | S97: =_xlfn.XLOOKUP(A97,A96:A695,[1]Sheet3!X169:X768) -> Cash on Delivery | T97: =_xlfn.XLOOKUP(A97,A96:A695,[1]Sheet3!Z169:Z768) -> 5 | U97: =_xlfn.XLOOKUP(A97,A96:A695,[1]Sheet3!AA169:AA768) -> FALSE | V97: =_xlfn.XLOOKUP(A97,A96:A695,[1]Sheet3!AC169:AC768) -> Delivered | W97: =_xlfn.XLOOKUP(A97,A96:A695,[1]Sheet3!AE169:AE768) -> 1
A98: ORD-00656 | B98: =_xlfn.XLOOKUP(A98,A97:A696,[1]Sheet3!C448:C1047) -> 44126 | C98: =_xlfn.XLOOKUP(A98,A97:A696,[1]Sheet3!D448:D1047) -> CUST42875 | D98: =_xlfn.XLOOKUP(A98,A97:A696,[1]Sheet3!E448:E1047) -> Sanjay Verma | E98: =_xlfn.XLOOKUP(A98,A97:A696,[1]Sheet3!G448:G1047) -> 26 | F98: =_xlfn.XLOOKUP('Retail Sales'!A449,'Retail Sales'!A448:A1047,[1]Sheet3!H448:H1047) -> Young Adult | G98: =_xlfn.XLOOKUP(A98,A97:A696,[1]Sheet3!J448:J1047) -> Other | H98: =_xlfn.XLOOKUP(A98,A97:A696,[1]Sheet3!K448:K1047) -> South | I98: =_xlfn.XLOOKUP(A98,A97:A696,[1]Sheet3!L448:L1047) -> Hyderabad | J98: =_xlfn.XLOOKUP(A98,A97:A696,[1]Sheet3!M448:M1047) -> Sports | K98: =_xlfn.XLOOKUP('Retail Sales'!A449,'Retail Sales'!A448:A1047,[1]Sheet3!N448:N1047) -> Cycle | L98: =_xlfn.XLOOKUP(A98,A97:A696,[1]Sheet3!P448:P1047) -> 1 | M98: =_xlfn.XLOOKUP(A98,A97:A696,[1]Sheet3!Q448:Q1047) -> 12380.73 | N98: =_xlfn.XLOOKUP(A98,A97:A696,[1]Sheet3!S448:S1047) -> 0.24 | O98: =_xlfn.XLOOKUP(A98,A97:A696,[1]Sheet3!T448:T1047) -> 8294.3 | P98: =_xlfn.XLOOKUP(A98,A97:A696,[1]Sheet3!U448:U1047) -> 2144.64 | Q98: =_xlfn.XLOOKUP(A98,A97:A696,[1]Sheet3!V448:V1047) -> 0.25856793 | R98: =_xlfn.XLOOKUP(A98,A97:A696,[1]Sheet3!W448:W1047) -> 80.23 | S98: =_xlfn.XLOOKUP(A98,A97:A696,[1]Sheet3!X448:X1047) -> Credit Card | T98: =_xlfn.XLOOKUP(A98,A97:A696,[1]Sheet3!Z448:Z1047) -> 4 | U98: =_xlfn.XLOOKUP(A98,A97:A696,[1]Sheet3!AA448:AA1047) -> FALSE | V98: =_xlfn.XLOOKUP(A98,A97:A696,[1]Sheet3!AC448:AC1047) -> Cancelled | W98: =_xlfn.XLOOKUP(A98,A97:A696,[1]Sheet3!AE448:AE1047) -> 5
A99: ORD-00664 | B99: =_xlfn.XLOOKUP(A99,A98:A697,[1]Sheet3!C487:C1086) -> 44132 | C99: =_xlfn.XLOOKUP(A99,A98:A697,[1]Sheet3!D487:D1086) -> CUST76842 | D99: =_xlfn.XLOOKUP(A99,A98:A697,[1]Sheet3!E487:E1086) -> Shreya Gupta | E99: =_xlfn.XLOOKUP(A99,A98:A697,[1]Sheet3!G487:G1086) -> 47 | F99: =_xlfn.XLOOKUP('Retail Sales'!A488,'Retail Sales'!A487:A1086,[1]Sheet3!H487:H1086) -> Adult | G99: =_xlfn.XLOOKUP(A99,A98:A697,[1]Sheet3!J487:J1086) -> Female | H99: =_xlfn.XLOOKUP(A99,A98:A697,[1]Sheet3!K487:K1086) -> South | I99: =_xlfn.XLOOKUP(A99,A98:A697,[1]Sheet3!L487:L1086) -> Hyderabad | J99: =_xlfn.XLOOKUP(A99,A98:A697,[1]Sheet3!M487:M1086) -> Books | K99: =_xlfn.XLOOKUP('Retail Sales'!A488,'Retail Sales'!A487:A1086,[1]Sheet3!N487:N1086) -> Textbook | L99: =_xlfn.XLOOKUP(A99,A98:A697,[1]Sheet3!P487:P1086) -> 8 | M99: =_xlfn.XLOOKUP(A99,A98:A697,[1]Sheet3!Q487:Q1086) -> 513.63 | N99: =_xlfn.XLOOKUP(A99,A98:A697,[1]Sheet3!S487:S1086) -> 0.17 | O99: =_xlfn.XLOOKUP(A99,A98:A697,[1]Sheet3!T487:T1086) -> 2804.09 | P99: =_xlfn.XLOOKUP(A99,A98:A697,[1]Sheet3!U487:U1086) -> 1009.57 | Q99: =_xlfn.XLOOKUP(A99,A98:A697,[1]Sheet3!V487:V1086) -> 0.36003481 | R99: =_xlfn.XLOOKUP(A99,A98:A697,[1]Sheet3!W487:W1086) -> 48.54 | S99: =_xlfn.XLOOKUP(A99,A98:A697,[1]Sheet3!X487:X1086) -> Cash on Delivery | T99: =_xlfn.XLOOKUP(A99,A98:A697,[1]Sheet3!Z487:Z1086) -> 4 | U99: =_xlfn.XLOOKUP(A99,A98:A697,[1]Sheet3!AA487:AA1086) -> FALSE | V99: =_xlfn.XLOOKUP(A99,A98:A697,[1]Sheet3!AC487:AC1086) -> Delivered | W99: =_xlfn.XLOOKUP(A99,A98:A697,[1]Sheet3!AE487:AE1086) -> 1
A100: ORD-00669 | B100: =_xlfn.XLOOKUP(A100,A99:A698,[1]Sheet3!C524:C1123) -> 44133 | C100: =_xlfn.XLOOKUP(A100,A99:A698,[1]Sheet3!D524:D1123) -> CUST66974 | D100: =_xlfn.XLOOKUP(A100,A99:A698,[1]Sheet3!E524:E1123) -> Aarav Sharma | E100: =_xlfn.XLOOKUP(A100,A99:A698,[1]Sheet3!G524:G1123) -> 34.294221 | F100: =_xlfn.XLOOKUP('Retail Sales'!A525,'Retail Sales'!A524:A1123,[1]Sheet3!H524:H1123) -> Young Adult | G100: =_xlfn.XLOOKUP(A100,A99:A698,[1]Sheet3!J524:J1123) -> Other | H100: =_xlfn.XLOOKUP(A100,A99:A698,[1]Sheet3!K524:K1123) -> East | I100: =_xlfn.XLOOKUP(A100,A99:A698,[1]Sheet3!L524:L1123) -> Guwahati | J100: =_xlfn.XLOOKUP(A100,A99:A698,[1]Sheet3!M524:M1123) -> Clothing | K100: =_xlfn.XLOOKUP('Retail Sales'!A525,'Retail Sales'!A524:A1123,[1]Sheet3!N524:N1123) -> Kurta | L100: =_xlfn.XLOOKUP(A100,A99:A698,[1]Sheet3!P524:P1123) -> 3 | M100: =_xlfn.XLOOKUP(A100,A99:A698,[1]Sheet3!Q524:Q1123) -> 562.94 | N100: =_xlfn.XLOOKUP(A100,A99:A698,[1]Sheet3!S524:S1123) -> 0.27 | O100: =_xlfn.XLOOKUP(A100,A99:A698,[1]Sheet3!T524:T1123) -> 1022.04 | P100: =_xlfn.XLOOKUP(A100,A99:A698,[1]Sheet3!U524:U1123) -> 309.8 | Q100: =_xlfn.XLOOKUP(A100,A99:A698,[1]Sheet3!V524:V1123) -> 0.30311925 | R100: =_xlfn.XLOOKUP(A100,A99:A698,[1]Sheet3!W524:W1123) -> 88.97 | S100: =_xlfn.XLOOKUP(A100,A99:A698,[1]Sheet3!X524:X1123) -> UPI | T100: =_xlfn.XLOOKUP(A100,A99:A698,[1]Sheet3!Z524:Z1123) -> 2 | U100: =_xlfn.XLOOKUP(A100,A99:A698,[1]Sheet3!AA524:AA1123) -> TRUE | V100: =_xlfn.XLOOKUP(A100,A99:A698,[1]Sheet3!AC524:AC1123) -> Returned | W100: =_xlfn.XLOOKUP(A100,A99:A698,[1]Sheet3!AE524:AE1123) -> 1
...
